Workbook

Sheet Cleaned
A1: CITY | B1: Population | C1: QCODE | D1: Region | E1: How often are bills issued? - Selected Choice | F1: How often are bills issued? - Other (Please Specify) - Text | G1: What methods of payment are accepted? (Check all that apply) [Cash] | H1: What methods of payment are accepted? (Check all that apply) [Check] | I1: What methods of payment are accepted? (Check all that apply) [Credit/Debit] | J1: What methods of payment are accepted? (Check all that apply) [Direct Deposit] | K1: What methods of payment are accepted? (Check all that apply) [Money Order] | L1: What methods of payment are accepted? (Check all that apply) [e-check] | M1: Do you provide paperless billing? | N1: What methods of enforcement are used for late or nonpayments? (Check all that Apply) - Selected Choice [Collections] | O1: What methods of enforcement are used for late or nonpayments? (Check all that Apply) - Selected Choice [Disconnect Water Service] | P1: What methods of enforcement are used for late or nonpayments? (Check all that Apply) - Selected Choice [Late Fee] | Q1: What methods of enforcement are used for late or nonpayments? (Check all that Apply) - Selected Choice [Late Fee and Interest] | R1: What methods of enforcement are used for late or nonpayments? (Check all that Apply) - Selected Choice [Lien on Property] | S1: What methods of enforcement are used for late or nonpayments? (Check all that Apply) - Selected Choice [Other (Please Specify)] | T1: What methods of enforcement are used for late or nonpayments? (Check all that Apply) - Other (Please Specify) - Text | U1: What is the late fee rate? | V1: What is the interest rate? | W1: How many days past due date are allowed before the late fee is assessed? | X1: What is the penalties amount and interest rate? - Penalties Amount | Y1: What is the penalties amount and interest rate? - Interest Rate | Z1: How many days after due date before you disconnect water service? | AA1: What dollar amount or number of days late triggers collections? - Dollar Amount | AB1: What dollar amount or number of days late triggers collections? - Days | AC1: Does the city provide waivers, discounts or reductions to certain utility customers? | AD1: Please describe these waivers, discounts and reductions: | AE1: Does your city provide credit or make any billing adjustments for leaks or billing errors? | AF1: For what services are adjustments made for customer water leaks | AG1: If a leak is detected, how far back does the city make adjustments to the water bill? - Days | AH1: If a leak is detected, how far back does the city make adjustments to the water bill? - Other Comments | AI1: Please describe what you do for wastewater adjustments. | AJ1: What percentage of rate revenue is obligated to debt services for the following systems? - Rate Revenue - Water - % | AK1: What percentage of rate revenue is obligated to debt services for the following systems? - Rate Revenue - Wastewater - % | AL1: What percentage of rate revenue is obligated to debt services for the following systems? - Rate Revenue - Stormwater - % | AM1: What percentage of rate revenue is obligated to debt services for the following systems? - Not Applicable - Water | AN1: What percentage of rate revenue is obligated to debt services for the following systems? - Not Applicable - Wastewater | AO1: What percentage of rate revenue is obligated to debt services for the following systems? - Not Applicable - Stormwater | AP1: Does your city maintain an asset management system for the following services? - Water | AQ1: Does your city maintain an asset management system for the following services? - Wastewater | AR1: Does your city maintain an asset management system for the following services? - Stormwater | AS1: What was the last year you did a Rate Study for the following services? - Water | AT1: What was the last year you did a Rate Study for the following services? - Wastewater | AU1: What was the last year you did a Rate Study for the following services? - Stormwater | AV1: What was the last year you did a Methodology Update for the following services? - Water | AW1: What was the last year you did a Methodology Update for the following services? - Wastewater | AX1: What was the last year you did a Methodology Update for the following services? - Stormwater | AY1: Does your city require accounts to be in the name of the property owner? | AZ1: How does your city handle billing for vacant properties? - Selected Choice | BA1: How does your city handle billing for vacant properties? - Charge a vacant rate upon request of the owner. (Please Explain) - Text | BB1: How does your city handle billing for vacant properties? - Other (Please Specify) - Text | BC1: What other account fees or charges are included on the utility bill? (Check all that apply) - Selected Choice [Backflow] | BD1: What other account fees or charges are included on the utility bill? (Check all that apply) - Selected Choice [New Account] | BE1: What other account fees or charges are included on the utility bill? (Check all that apply) - Selected Choice [None] | BF1: What other account fees or charges are included on the utility bill? (Check all that apply) - Selected Choice [Other (Please Specify)] | BG1: What other account fees or charges are included on the utility bill? (Check all that apply) - Selected Choice [Shutoff] | BH1: What other account fees or charges are included on the utility bill? (Check all that apply) - Selected Choice [Tampering] | BI1: What other account fees or charges are included on the utility bill? (Check all that apply) - Other (Please Specify) - Text | BJ1: Is stormwater included in the utility bill? | BK1: What general government fees are included on the utility bill? (Check all that apply) - Selected Choice [Fire] | BL1: What general government fees are included on the utility bill? (Check all that apply) - Selected Choice [Library] | BM1: What general government fees are included on the utility bill? (Check all that apply) - Selected Choice [Other (Please Specify)] | BN1: What general government fees are included on the utility bill? (Check all that apply) - Selected Choice [Parks & Recreation] | BO1: What general government fees are included on the utility bill? (Check all that apply) - Selected Choice [Police] | BP1: What general government fees are included on the utility bill? (Check all that apply) - Selected Choice [Streets & Streetlights] | BQ1: What general government fees are included on the utility bill? (Check all that apply) - Selected Choice [Surface Water Management] | BR1: What general government fees are included on the utility bill? (Check all that apply) - Other (Please Specify) - Text | BS1: Does city ordinance have an automatic CPI/Income adjustment for the following services? - Water | BT1: Does city ordinance have an automatic CPI/Income adjustment for the following services? - Wastewater | BU1: Does city ordinance have an automatic CPI/Income adjustment for the following services? - Stormwater | BV1: Does your city charge for drinking water service? | BW1: What was the last effective date of your city's most recent rate change for water services? (Please respond with the year only) | BX1: Overall, did the rate increase or decrease at the most recent rate change? Please also include the percent (%) change. - Selected Choice | BY1: Overall, did the rate increase or decrease at the most recent rate change? Please also include the percent (%) change. - Increase (% Increase) - Text | BZ1: Why did the city change water rates? (Check all that apply) - Selected Choice [Capital Improvement] | CA1: Why did the city change water rates? (Check all that apply) - Selected Choice [Inflation/ CPI] | CB1: Why did the city change water rates? (Check all that apply) - Selected Choice [Labor Costs] | CC1: Why did the city change water rates? (Check all that apply) - Selected Choice [Other (Please Specify)] | CD1: Why did the city change water rates? (Check all that apply) - Selected Choice [State/ Federal Mandate] | CE1: Why did the city change water rates? (Check all that apply) - Selected Choice [Treatment Costs] | CF1: Why did the city change water rates? (Check all that apply) - Other (Please Specify) - Text | CG1: What is the rate structure for your city's water service? - Selected Choice | CH1: What is the rate structure for your city's water service? - Other (Please Specify) - Text | CI1: For water services, if you were to bill a residential customer for 5,000 gallons (6.684 CCFs) with a 3/4'' meter size, what dollar amount would you bill them, including the base rate? | CJ1: Does your city charge for wastewater service? | CK1: What was the last effective date of your city's most recent rate change for wastewater services? (Please respond with the year only) | CL1: Overall, did the rate increase or decrease at the most recent rate change? Please include percent (%) change. - Selected Choice | CM1: Overall, did the rate increase or decrease at the most recent rate change? Please include percent (%) change. - Increase (% Increase) - Text | CN1: Why did the city change wastewater rates? (Check all that apply) - Selected Choice [Capital Improvement] | CO1: Why did the city change wastewater rates? (Check all that apply) - Selected Choice [Inflation/ CPI] | CP1: Why did the city change wastewater rates? (Check all that apply) - Selected Choice [Labor Costs] | CQ1: Why did the city change wastewater rates? (Check all that apply) - Selected Choice [Other (Please Specify)] | CR1: Why did the city change wastewater rates? (Check all that apply) - Selected Choice [State/ Federal Mandate] | CS1: Why did the city change wastewater rates? (Check all that apply) - Selected Choice [Treatment Costs] | CT1: Why did the city change wastewater rates? (Check all that apply) - Other (Please Specify) - Text | CU1: What is the rate structure for your city's wastewater service? - Selected Choice | CV1: What is the rate structure for your city's wastewater service? - Other (Please Specify) - Text | CW1: For wastewater services, if you were to bill a residential customer for 5,000 gallons (6.684 CCFs) with a 3/4'' meter size, what dollar amount would you bill them, including the base rate? | CX1: Does your city charge for stormwater service? | CY1: What was the last effective date of your city's most recent rate change for stormwater services? (Please respond with the year only) | CZ1: Overall, did the rate increase or decrease at the most recent rate change? Please include the percent (%) change. - Selected Choice | DA1: Overall, did the rate increase or decrease at the most recent rate change? Please include the percent (%) change. - Increase (% Increase) - Text | DB1: Is your city subject to an MS4 Phase I or Phase II (DEQ Issued Stormwater) Permit? | DC1: Why did the city change stormwater rates? (Check all that apply) - Selected Choice [Capital Improvement] | DD1: Why did the city change stormwater rates? (Check all that apply) - Selected Choice [Inflation/ CPI] | DE1: Why did the city change stormwater rates? (Check all that apply) - Selected Choice [Labor Costs] | DF1: Why did the city change stormwater rates? (Check all that apply) - Selected Choice [Other (Please Specify)] | DG1: Why did the city change stormwater rates? (Check all that apply) - Selected Choice [State/ Federal Mandate] | DH1: Why did the city change stormwater rates? (Check all that apply) - Selected Choice [Treatment Costs] | DI1: Why did the city change stormwater rates? (Check all that apply) - Other (Please Specify) - Text | DJ1: What is the rate structure for your city's stormwater service? - Selected Choice | DK1: What is the rate structure for your city's stormwater service? - Other (Please Specify) - Text | DL1: Does your city offer stormwater fee reductions or credits for onsite stormwater management? | DM1: Please describe the reduction or credit (including the amount for onsite stormwater management) | DN1: What does the average house pay for stormwater services (dollars per month)? | DO1: Does your city provide drinking water services? | DP1: What is the service population in 2024? - Service Population (Permanent Residents) - Inside City Limits | DQ1: What is the service population in 2024? - Service Population (Permanent Residents) - Outside City Limits | DR1: What is the service population in 2024? - Service Population (Including Peak Seasonal) - Inside City Limits | DS1: What is the service population in 2024? - Service Population (Including Peak Seasonal) - Outside City Limits | DT1: Please list the number of connections for the following: - Residential - Inside City Limits | DU1: Please list the number of connections for the following: - Residential - Outside City Limits | DV1: Please list the number of connections for the following: - Commercial - Inside City Limits | DW1: Please list the number of connections for the following: - Commercial - Outside City Limits | DX1: Please list the number of connections for the following: - Other - Inside City Limits | DY1: Please list the number of connections for the following: - Other - Outside City Limits | DZ1: What is the annual average water consumption for residential customers (in gallons)? | EA1: Please provide the following facility and water source information: - Total miles of water lines (all sizes), not including service laterals | EB1: Please provide the following facility and water source information: - Total number of pumps and lift stations in your city | EC1: Please provide the following facility and water source information: - How many levels or zones based on elevation do you have? | ED1: Please provide the following facility and water source information: - How far away is the water source from the city (miles)? | EE1: Please provide the following system age and capacity information: - Year of original system construction completion | EF1: Please provide the following system age and capacity information: - Year of last major update | EG1: Please provide the following system age and capacity information: - What is the capacity of your water source? | EH1: Please provide the following system age and capacity information: - What is the design capacity of your water plant(s) (MGD)? | EI1: Please provide the following system age and capacity information: - What was the average daily production in 2024 (MG)? | EJ1: Please provide the following system age and capacity information: - How much of your daily average production is sold (not including city use)? | EK1: Please provide the following system age and capacity information: - What was the peak flow of water treated in a 24-hour period in 2024 ? | EL1: Please list the amount of raw and treated water storage you have for the different types of applicable storage: - Closed Tanks - Raw Water Storage (MG) | EM1: Please list the amount of raw and treated water storage you have for the different types of applicable storage: - Closed Tanks - Treated Water Storage (MG) | EN1: Please list the amount of raw and treated water storage you have for the different types of applicable storage: - Covered Urban Reservoirs - Raw Water Storage (MG) | EO1: Please list the amount of raw and treated water storage you have for the different types of applicable storage: - Covered Urban Reservoirs - Treated Water Storage (MG) | EP1: Please list the amount of raw and treated water storage you have for the different types of applicable storage: - ASR Reservoir - Raw Water Storage (MG) | EQ1: Please list the amount of raw and treated water storage you have for the different types of applicable storage: - ASR Reservoir - Treated Water Storage (MG) | ER1: Please list the amount of raw and treated water storage you have for the different types of applicable storage: - Other (Please Specify) - Text | ES1: Please list the amount of raw and treated water storage you have for the different types of applicable storage: - Other (Please Specify) - Raw Water Storage (MG) | ET1: Please list the amount of raw and treated water storage you have for the different types of applicable storage: - Other (Please Specify) - Treated Water Storage (MG) | EU1: In what year will your daily production exceed design capacity? | EV1: Does your city have an approved water conservation and management plan? | EW1: Do you measure water loss? | EX1: What method is used to determine water loss in the system? - Selected Choice | EY1: What method is used to determine water loss in the system? - Other (Please Specify) - Text | EZ1: What percentage of the system does each type of meter represent? - Radio (%) | FA1: What percentage of the system does each type of meter represent? - Touch (%) | FB1: What percentage of the system does each type of meter represent? - Manual Read (%) | FC1: Do you have any additional comments on water services? | FD1: Does your city provide wastewater services? | FE1: What is the service population in 2024? - Service Population (Permanent Residents) - Inside City Limits | FF1: What is the service population in 2024? - Service Population (Permanent Residents) - Outside City Limits | FG1: What is the service population in 2024? - Service Population (Including Peak Seasonal) - Inside City Limits | FH1: What is the service population in 2024? - Service Population (Including Peak Seasonal) - Outside City Limits | FI1: Please list the number of connections for the following: - Residential - Inside City Limits | FJ1: Please list the number of connections for the following: - Residential - Outside City Limits | FK1: Please list the number of connections for the following: - Commercial - Inside City Limits | FL1: Please list the number of connections for the following: - Commercial - Outside City Limits | FM1: Please list the number of connections for the following: - Other - Inside City Limits | FN1: Please list the number of connections for the following: - Other - Outside City Limits | FO1: What is the annual average wastewater base (volume) for a residential customer (x1000 gal. or 1.337 CCFs)? | FP1: Please provide the following facility, lines, and treatment information: - Total miles of sewer lines (all sizes), not including service laterals | FQ1: Please provide the following facility, lines, and treatment information: - Total number of pumps and lift stations in your city | FR1: Please provide the following facility, lines, and treatment information: - Total number of treatment plants | FS1: Please provide the following facility, lines, and treatment information: - What percent of city wastewater lines also serve stormwater (i.e. combined sewer)? | FT1: What level of wastewater treatment is provided to city wastewater (Check all that apply)? - Selected Choice [Advanced Treatment/ Tertiary] | FU1: What level of wastewater treatment is provided to city wastewater (Check all that apply)? - Selected Choice [Nitrogen Removal] | FV1: What level of wastewater treatment is provided to city wastewater (Check all that apply)? - Selected Choice [Other (Please Specify)] | FW1: What level of wastewater treatment is provided to city wastewater (Check all that apply)? - Selected Choice [Phosphorous Removal] | FX1: What level of wastewater treatment is provided to city wastewater (Check all that apply)? - Selected Choice [Primary] | FY1: What level of wastewater treatment is provided to city wastewater (Check all that apply)? - Selected Choice [Secondary] | FZ1: What level of wastewater treatment is provided to city wastewater (Check all that apply)? - Other (Please Specify) - Text | GA1: Please provide the following system age and capacity information: - Year of original plant construction completion | GB1: Please provide the following system age and capacity information: - Year of last major plant update | GC1: Please provide the following system age and capacity information: - What is the design capacity of your treatment plant(s) in dry weather (MGD)? | GD1: Please provide the following system age and capacity information: - What is the design capacity of your treatment plant(s) in peak wet weather (MGD)? | GE1: Please provide the following system age and capacity information: - What is the total amount of wastewater treated in 2024 (MG)? | GF1: Please provide the following system age and capacity information: - What was the peak wet weather flow in 2024 (MGD)? | GG1: Please provide the following system age and capacity information: - What was the peak dry weather flow in 2024 (MGD)? | GH1: At what percent (%) capacity is the entire wastewater system operating? | GI1: In what year will the wastewater system be at maximum capacity? | GJ1: In what year will your daily production exceed design capacity? | GK1: Does your city administer an industrial wastewater pre-treatment program? | GL1: Does your city apply or provide reclaimed water to public/private property? | GM1: What percentage (%) of total reclaimed water is reused/applied? | GN1: Where does this reuse and application occur (i.e. city park, private golf course, industrial cooling tower, etc.)? | GO1: Does your city apply biosolids to public/ private property? | GP1: Where does this biosolid application occur (i.e. city park, private golf course, etc.)? | GQ1: Does your city landfill biosolids? | GR1: What percentage (%) of biosolids are landfilled? | GS1: Do you have any additional comments on wastewater services? | GT1: Does your city provide stormwater services? | GU1: Please list the number of accounts for the following: - Residential - Inside City Limits | GV1: Please list the number of accounts for the following: - Residential - Outside City Limits | GW1: Please list the number of accounts for the following: - Commercial - Inside City Limits | GX1: Please list the number of accounts for the following: - Commercial - Outside City Limits | GY1: Please list the number of accounts for the following: - Other - Inside City Limits | GZ1: Please list the number of accounts for the following: - Other - Outside City Limits | HA1: Please provide the following facility and water source information: - Total miles of piped system | HB1: Please provide the following facility and water source information: - Total miles of open channels, ditches, and swales | HC1: What is the average Equivalent Dwelling Unit (EDU) for residential in square feet? | HD1: Do you have any additional comments on stormwater services? | HE1: Thank You for participating in this survey. Do you have any additional comments on any topic in this survey?
A2: Heppner | B2: 1205 | C2: 2 | D2: 11 | E2: 1 | G2: 1 | H2: 1 | I2: 1 | J2: 0 | K2: 1 | L2: 0 | M2: 2 | N2: 1 | O2: 1 | P2: 1 | Q2: 0 | R2: 1 | S2: 0 | U2: 5 | W2: 30 | Z2: 60 | AA2: 151 | AB2: 90 | AC2: 1 | AD2: We have an internal fund that pays for discounts for "yard of the month," winners. We have a internal account that contains funds donated for hardship requests. These requests for payment must be heard by our Utilities Committee or Council. The usage of utilities donation funds is not at the discretion of employees. | AE2: 3 | AF2: 2 | AH2: The adjustment for leaks are only made if due to City error. Customer error or damage to customer side of supply is the responsibility of the customer. | AP2: 1 | AQ2: 1 | AR2: 2 | AY2: 1 | AZ2: 4 | BB2: No continued charges if meter is locked and no account is open. | BC2: 1 | BD2: 1 | BE2: 0 | BF2: 1 | BG2: 1 | BH2: 1 | BI2: Deposit for new accounts | BJ2: 2 | BK2: 0 | BL2: 0 | BM2: 1 | BN2: 0 | BO2: 0 | BP2: 0 | BQ2: 0 | BR2: none | BS2: 1 | BT2: 1 | BV2: 1 | BW2: 2025 | BX2: 1 | BY2: 3.2 | BZ2: 0 | CA2: 1 | CB2: 1 | CC2: 1 | CD2: 0 | CE2: 1 | CF2: We use CPI Water/Wastewater to adjust rate | CG2: 1 | CI2: 53.17 | CJ2: 1 | CK2: 2025 | CL2: 1 | CM2: 3.2 | CN2: 0 | CO2: 1 | CP2: 1 | CQ2: 0 | CR2: 0 | CS2: 1 | CU2: 1 | CW2: 50.69 | CX2: 2 | DO2: 1 | DP2: 1200 | DQ2: 100 | DR2: 1200 | DS2: 100 | EM2: 1.35 | EV2: 1 | EW2: 1 | EX2: 2 | EZ2: 40 | FA2: 50 | FB2: 10 | FD2: 1 | GO2: 1 | GP2: Private farmland | GQ2: 2 | GT2: 2
A3: Spray | B3: 141 | C3: 1 | D3: 9 | E3: 1 | G3: 1 | H3: 1 | I3: 0 | J3: 1 | K3: 1 | L3: 1 | M3: 2 | N3: 0 | O3: 0 | P3: 1 | Q3: 0 | R3: 0 | S3: 0 | U3: 10 | W3: 1 | AC3: 1 | AD3: If customer has fallen on hard times, the council will waive a month or if there is a water leak that is not the property owners fault | AE3: 3 | AF3: 2 | AG3: 30 | AM3: 1 | AN3: 1 | AO3: 1 | AY3: 1 | AZ3: 4 | BB3: Still pay monthly rate unless ask for water to be turned off | BC3: 0 | BD3: 1 | BE3: 0 | BF3: 0 | BG3: 1 | BH3: 0 | BJ3: 2 | BK3: 0 | BL3: 0 | BM3: 1 | BN3: 0 | BO3: 0 | BP3: 0 | BQ3: 0 | BR3: none | BV3: 1 | BW3: 2019 | BX3: 1 | BY3: 0.03 | BZ3: 0 | CA3: 1 | CB3: 1 | CC3: 0 | CD3: 0 | CE3: 1 | CG3: 1 | CJ3: 1 | CK3: 2019 | CL3: 1 | CM3: 0.04 | CN3: 0 | CO3: 1 | CP3: 1 | CQ3: 0 | CR3: 0 | CS3: 1 | CU3: 1 | CX3: 2 | DO3: 1 | DP3: 114 | DR3: 124 | DT3: 114 | DV3: 10 | EB3: 1 | ED3: 0.25 | EV3: 1 | EW3: 1 | EX3: 2 | FD3: 1 | FE3: 114 | FG3: 124 | FI3: 114 | FK3: 10 | FQ3: 1 | GA3: 2009 | GK3: 2 | GL3: 2 | GO3: 2 | GQ3: 2 | GT3: 2
A4: Canyon City | B4: 675 | C4: 2 | D4: 12 | E4: 1 | G4: 1 | H4: 1 | I4: 1 | J4: 0 | K4: 0 | L4: 1 | M4: 2 | N4: 0 | O4: 1 | P4: 0 | Q4: 1 | R4: 0 | S4: 0 | V4: 0.01 | X4: 5 | Z4: 30 | AC4: 2 | AE4: 3 | AF4: 2 | AG4: 30 | AM4: 1 | AN4: 1 | AP4: 2 | AQ4: 2 | AY4: 2 | AZ4: 2 | BC4: 1 | BD4: 0 | BE4: 0 | BF4: 0 | BG4: 1 | BH4: 1 | BJ4: 2 | BS4: 2 | BT4: 2 | BU4: 2 | BV4: 1 | BW4: 2024 | BX4: 1 | BY4: 0.02 | BZ4: 1 | CA4: 0 | CB4: 0 | CC4: 0 | CD4: 0 | CE4: 0 | CG4: 1 | CI4: 50.25 | CJ4: 1 | CK4: 2025 | CL4: 1 | CM4: 30 | CN4: 1 | CO4: 0 | CP4: 0 | CQ4: 0 | CR4: 0 | CS4: 0 | CU4: 1 | CW4: 77 | CX4: 2 | DO4: 1 | DP4: 668 | DQ4: 30 | DR4: 668 | DS4: 30 | DT4: 312 | DU4: 5 | DV4: 32 | DW4: 1 | DZ4: 12123 | EV4: 2 | EW4: 2 | FB4: 100 | FC4: currently working on a major water project | FD4: 1 | FE4: 668 | FF4: 6 | FG4: 668 | FH4: 6 | FI4: 312 | FK4: 32 | GO4: 2 | GQ4: 2 | GS4: Our wastewater plant is in a John Day about a mile out of town. | GT4: 2
A5: Nehalem | B5: 299 | C5: 1 | D5: 1 | E5: 1 | G5: 1 | H5: 1 | I5: 1 | J5: 0 | K5: 0 | L5: 0 | M5: 1 | N5: 0 | O5: 1 | P5: 1 | Q5: 0 | R5: 0 | S5: 0 | U5: 10 | W5: 20 | Z5: 90 | AC5: 2 | AE5: 3 | AF5: 2 | AH5: They are allowed up to 50% of an overage 2 times a year | AJ5: 15 | AN5: 1 | AO5: 1 | AP5: 2 | AS5: 2023 | AT5: n/a | AU5: n/a | AV5: 2024 | AW5: n/a | AX5: n/a | AY5: 2 | AZ5: 4 | BB5: if the onwer is hooked up to the system they are still charge the monthly base rate. | BC5: 0 | BD5: 1 | BE5: 0 | BF5: 0 | BG5: 1 | BH5: 1 | BJ5: 2 | BS5: 2 | BV5: 2 | CJ5: 2 | CX5: 2 | DO5: 1 | DP5: 264 | DQ5: 636 | DT5: 264 | DU5: 636 | DZ5: 36850000 | EF5: 2024 | EV5: 1 | EW5: 1 | EX5: 1 | FD5: 2 | GT5: 2
A6: Gates | B6: 573 | C6: 2 | D6: 3 | E6: 1 | G6: 1 | H6: 1 | I6: 0 | J6: 0 | K6: 1 | L6: 0 | M6: 2 | N6: 0 | O6: 1 | P6: 1 | Q6: 0 | R6: 1 | S6: 0 | U6: 5 | Z6: 72 | AC6: 2 | AE6: 3 | AF6: 2 | AG6: 3 | AN6: 1 | AO6: 1 | AP6: 2 | AS6: 2012 | AT6: NA | AU6: NA | AW6: NA | AX6: NA | AY6: 2 | AZ6: 2 | BC6: 0 | BD6: 0 | BE6: 0 | BF6: 1 | BG6: 1 | BH6: 0 | BI6: NSF if needed | BJ6: 2 | BK6: 0 | BL6: 0 | BM6: 1 | BN6: 0 | BO6: 0 | BP6: 0 | BQ6: 0 | BR6: Street Fee | BS6: 2 | BV6: 1 | BW6: 2025 | BX6: 1 | BY6: 0.03 | BZ6: 1 | CA6: 1 | CB6: 1 | CC6: 0 | CD6: 0 | CE6: 1 | CG6: 5 | CH6: Monthly Base Rate (includes 1,000 gl plus $4.00 per 1,000 gls | CI6: 83.43 | CJ6: 2 | CX6: 2 | DO6: 1 | DP6: 500 | DT6: 195 | DU6: 18 | DV6: 4 | DX6: 1 | DZ6: 48000 | EA6: 7 | EB6: 3 | EC6: 2 | ED6: 0 | EE6: 1950 | EF6: 2012 | EH6: 0.3 | EI6: 0.15 | EK6: 210 | EM6: 500000 | EU6: ? | EV6: 1 | EW6: 1 | EX6: 1 | EZ6: 0.98 | FA6: 0.02 | FD6: 2 | GT6: 2
A7: Glendale | B7: 859 | C7: 2 | D7: 7 | E7: 1 | G7: 1 | H7: 1 | I7: 1 | J7: 0 | K7: 1 | L7: 0 | M7: 2 | N7: 1 | O7: 1 | P7: 1 | Q7: 0 | R7: 0 | S7: 0 | U7: 20 | AB7: 30 | AC7: 2 | AE7: 2 | AP7: 1 | AQ7: 1 | AY7: 2 | AZ7: 2 | BJ7: 2 | BS7: 1 | BT7: 1 | BV7: 1 | BW7: 2025 | BX7: 1 | BY7: 3.2 | BZ7: 0 | CA7: 1 | CB7: 1 | CC7: 0 | CD7: 0 | CE7: 1 | CG7: 3 | CI7: 57.25 | CJ7: 1 | CK7: 2025 | CL7: 1 | CM7: 3.2 | CN7: 1 | CO7: 1 | CP7: 1 | CQ7: 0 | CR7: 0 | CS7: 1 | CU7: 1 | CW7: 86 | CX7: 2 | DO7: 1 | DP7: 875 | DR7: 875 | DT7: 350 | DU7: 37 | DV7: 32 | DZ7: 4000 | EB7: 2 | ED7: 0.25 | EE7: 1970 | EF7: 1998 | EG7: 1000000 | EJ7: 70000 | EW7: 1 | EX7: 3 | FB7: 100 | FD7: 1 | FE7: 875 | FG7: 875 | FI7: 350 | FJ7: 7 | FK7: 33 | FL7: 4 | FT7: 0 | FU7: 1 | FV7: 0 | FW7: 1 | FX7: 1 | FY7: 1 | GA7: 1950 | GB7: 2021 | GL7: 2 | GO7: 1 | GP7: private ranch | GQ7: 2 | GT7: 2
A8: Joseph | B8: 1182 | C8: 2 | D8: 11 | E8: 1 | G8: 1 | H8: 1 | I8: 1 | J8: 0 | K8: 1 | L8: 1 | M8: 1 | N8: 0 | O8: 1 | P8: 1 | Q8: 0 | R8: 1 | S8: 0 | U8: 10 | W8: 10 | Z8: 25 | AC8: 2 | AE8: 3 | AH8: as long as the user has been actively working to fix the leak | AJ8: 100 | AK8: 100 | AO8: 1 | AP8: 1 | AQ8: 2 | AT8: unknown | AU8: n/a | AV8: 2024 | AW8: 2023 | AX8: n/a | AY8: 2 | AZ8: 4 | BB8: Water services are discontinued, sewer services continue to be charged. | BC8: 0 | BD8: 0 | BE8: 0 | BF8: 0 | BG8: 1 | BH8: 0 | BJ8: 2 | BK8: 0 | BL8: 0 | BM8: 0 | BN8: 0 | BO8: 0 | BP8: 1 | BQ8: 0 | BS8: 2 | BT8: 2 | BV8: 1 | BW8: 2025 | BX8: 1 | BY8: 61.5 | BZ8: 0 | CA8: 1 | CB8: 0 | CC8: 1 | CD8: 0 | CE8: 1 | CF8: Water Project to upgrade infrastructure | CG8: 1 | CI8: 53 | CJ8: 1 | CK8: 2023 | CL8: 1 | CM8: 64 | CN8: 0 | CO8: 1 | CP8: 0 | CQ8: 1 | CR8: 0 | CS8: 0 | CT8: DEQ required update costs | CU8: 1 | CW8: 43.24 | CX8: 2 | DO8: 1 | DZ8: 144000000 | ED8: 1 | EF8: 2025 | EL8: 9 | EN8: 7 | EO8: 12 | EP8: 9 | EQ8: 8 | EU8: unknown | EV8: 1 | EW8: 1 | EX8: 1 | EZ8: 98 | FA8: 2 | FD8: 1 | GO8: 1 | GP8: Local ranch | GQ8: 2 | GS8: no | GT8: 2
A9: Ashland | B9: 21862 | C9: 5 | D9: 7 | E9: 1 | G9: 1 | H9: 1 | I9: 1 | J9: 0 | K9: 1 | L9: 1 | M9: 1 | N9: 1 | O9: 1 | P9: 0 | Q9: 0 | R9: 0 | S9: 0 | Z9: 45 | AA9: 50 | AB9: 30 | AC9: 1 | AD9: Low income discount of 30% if customer is at or below 200% Federal Poverty Level up to $400. | AE9: 3 | AF9: 3 | AH9: 18 months | AI9: We would look at the same time period the previous year, and give the customer up to 50% credit compared to that time period. If they are a commercial user, we would also decrease their sewer charge accordingly. | AJ9: 7 | AK9: 3 | AL9: 2 | AP9: 1 | AQ9: 1 | AR9: 1 | AS9: 2024 | AT9: 2022 | AU9: 2020 | AV9: 2012 | AW9: 2019 | AX9: 2020 | AY9: 2 | AZ9: 2 | BC9: 0 | BD9: 1 | BE9: 0 | BF9: 0 | BG9: 0 | BH9: 0 | BJ9: 1 | BK9: 1 | BL9: 0 | BM9: 0 | BN9: 1 | BO9: 1 | BP9: 1 | BQ9: 1 | BS9: 2 | BT9: 2 | BU9: 2 | BV9: 1 | BW9: 2025 | BZ9: 1 | CA9: 1 | CB9: 1 | CC9: 1 | CD9: 0 | CE9: 1 | CF9: The rates were increased not by a flat percentage, but looked at each rate class and appropriate charge. We also changed the tier structure. | CG9: 1 | CI9: 58.17 | CJ9: 1 | CK9: 2019 | CL9: 1 | CM9: 4 | CN9: 1 | CO9: 1 | CP9: 1 | CQ9: 0 | CR9: 0 | CS9: 1 | CU9: 4 | CV9: Winter average+flat | CW9: 47.52 | CX9: 1 | CY9: 5 | CZ9: 1 | DA9: 8 | DB9: 1 | DC9: 1 | DD9: 1 | DE9: 1 | DF9: 0 | DG9: 0 | DH9: 1 | DJ9: 1 | DL9: 1 | DN9: 5.43 | DO9: 1 | DP9: 23000 | DT9: 7144 | DU9: 42 | DV9: 763 | DW9: 9 | DX9: 233 | DZ9: 37000 | EA9: 120 | EB9: 3 | EC9: 14 | ED9: 2 | EE9: 1948 | EF9: 1994 | EG9: 800 | EH9: 7.5 | EI9: 2.96 | EJ9: 1 | EK9: 5.7 | EM9: 6.8 | EP9: 2 | EU9: na | EV9: 1 | EW9: 1 | EX9: 1 | EZ9: 0.05 | FB9: 0.95 | FD9: 1 | FE9: 23000 | FI9: 8196 | FJ9: 10 | FK9: 686 | FL9: 5 | FM9: 79 | FN9: 3 | FO9: 2.7 | FP9: 112 | FQ9: 7 | FR9: 2 | FS9: 3 | FT9: 1 | FU9: 0 | FV9: 0 | FW9: 0 | FX9: 0 | FY9: 0 | GA9: 1936 | GB9: 2002 | GC9: 2.4 | GD9: 3.6 | GE9: 800 | GF9: 10.5 | GG9: 2.3 | GH9: 50 | GI9: NA | GJ9: NA | GK9: 1 | GL9: 2 | GM9: 0% | GO9: 2 | GQ9: 1 | GR9: 1 | GT9: 1 | GU9: 7601 | GV9: 6 | GW9: 690 | GY9: 79 | HB9: NA
A10: Irrigon | B10: 2372 | C10: 3 | D10: 11 | E10: 1 | G10: 1 | H10: 1 | I10: 1 | J10: 0 | K10: 1 | L10: 0 | M10: 1 | N10: 0 | O10: 1 | P10: 1 | Q10: 0 | R10: 1 | S10: 0 | U10: 5 | W10: 30 | Z10: 10 | AC10: 2 | AE10: 2 | AG10: 30 | AJ10: 3 | AK10: 4 | AL10: 0 | AP10: 2 | AQ10: 2 | AS10: 2006 | AT10: 2006 | AU10: N/A | AV10: 2006 | AW10: 2006 | AX10: N/A | AY10: 2 | AZ10: 4 | BB10: Revenue Bonds stay static | BC10: 0 | BD10: 0 | BE10: 0 | BF10: 0 | BG10: 1 | BH10: 0 | BJ10: 2 | BK10: 0 | BL10: 0 | BM10: 0 | BN10: 0 | BO10: 1 | BP10: 1 | BQ10: 0 | BS10: 2 | BT10: 2 | BV10: 1 | BX10: 1 | BY10: 2.3 | BZ10: 1 | CA10: 1 | CB10: 1 | CC10: 0 | CD10: 0 | CE10: 0 | CG10: 1 | CJ10: 1 | CL10: 1 | CM10: 2.3 | CN10: 1 | CO10: 1 | CP10: 1 | CQ10: 0 | CR10: 0 | CS10: 1 | CU10: 1 | CW10: 50.82 | CX10: 2 | DO10: 1 | DP10: 2000 | DQ10: 60 | DR10: 2000 | DS10: 60 | DT10: 740 | DU10: 40 | DV10: 25 | DW10: 1 | DX10: 0 | DY10: 1 | DZ10: 90000 | EA10: 22 | EB10: 2 | EC10: 1 | ED10: 2 | EE10: 1965 | EF10: 2024 | EH10: 5 | EI10: 1 | EJ10: 0.99 | EK10: 1 | EL10: 1 | EM10: 1.5 | EN10: 1 | EO10: 1 | EP10: 1 | EQ10: 1 | EU10: Unknown | EV10: 2 | EW10: 1 | EX10: 1 | EZ10: 0.98 | FA10: 0 | FB10: 2 | FC10: N/A | FD10: 1 | FE10: 2000 | FF10: 40 | FG10: 2000 | FH10: 40 | FI10: 740 | FJ10: 9 | FK10: 25 | FL10: 6 | FO10: 18000 | FP10: 13 | FQ10: 10 | FR10: 2 | FS10: 2 | FT10: 0 | FU10: 1 | FV10: 0 | FW10: 0 | FX10: 1 | FY10: 1 | GA10: 2017 | GB10: 2013 | GH10: 50 | GI10: 2035 est | GJ10: 2035 est | GK10: 2 | GL10: 2 | GO10: 2 | GQ10: 2 | GS10: None | GT10: 2 | HE10: Got to Love surveys. So how much can we get?
A11: Long Creek | B11: 173 | C11: 1 | D11: 12 | E11: 1 | G11: 1 | H11: 1 | I11: 1 | J11: 0 | K11: 1 | L11: 0 | M11: 2 | N11: 0 | O11: 1 | P11: 1 | Q11: 0 | R11: 1 | S11: 0 | U11: 10 | W11: 30 | Z11: 60 | AC11: 1 | AD11: Hardship cases are dealt with individually. | AE11: 3 | AF11: 2 | AH11: only for overage charges | AJ11: 0 | AK11: 0 | AL11: 0 | AM11: 1 | AN11: 1 | AO11: 1 | AT11: 2024-2025 | AU11: NA | AW11: NA | AX11: NA | AY11: 2 | AZ11: 2 | BC11: 0 | BD11: 0 | BE11: 1 | BF11: 0 | BG11: 0 | BH11: 0 | BJ11: 2 | BK11: 0 | BL11: 0 | BM11: 1 | BN11: 0 | BO11: 0 | BP11: 0 | BQ11: 0 | BR11: NA | BV11: 1 | BW11: 2025 | BX11: 1 | BY11: 0.035 | BZ11: 0 | CA11: 1 | CB11: 0 | CC11: 1 | CD11: 0 | CE11: 0 | CF11: OVERALL COST INCREASES | CG11: 2 | CI11: 29 | CJ11: 1 | CK11: 2025 | CL11: 1 | CM11: 0.035 | CN11: 0 | CO11: 1 | CP11: 0 | CQ11: 0 | CR11: 0 | CS11: 0 | CU11: 1 | CW11: 26 | CX11: 2 | DO11: 1 | DP11: 175 | DQ11: 0 | DT11: 97 | DV11: 7 | DX11: 5 | DZ11: 1000000 | EB11: 0 | EC11: 1 | EN11: 2 | EU11: undetermined | FD11: 1 | FE11: 175 | GO11: 2 | GQ11: 2 | GT11: 2
A12: Columbia City | B12: 1946 | C12: 3 | D12: 1 | E12: 1 | G12: 1 | H12: 1 | I12: 1 | J12: 1 | K12: 1 | L12: 1 | M12: 1 | N12: 1 | O12: 1 | P12: 1 | Q12: 0 | R12: 1 | S12: 0 | W12: 15 | Z12: 30 | AB12: 60 | AC12: 2 | AE12: 3 | AF12: 3 | AH12: eligible for 2 months leak credit if fixed in a timely manner and the adj is a percentage of what the leak amount is calculated at | AI12: Wastewater leak credits are not done for the months of June - September because only a flat rate is charged during the summer months. October - May the leak credit is calculated for up to 2 months if done in a timely manner and is a percentage of what the leak amount is calculated at | AT12: unk | AW12: unk | AY12: 2 | AZ12: 4 | BB12: Close account with no charges until opened by next occupant unless the property owner requests to have water left on in their name | BC12: 0 | BD12: 0 | BE12: 0 | BF12: 0 | BG12: 1 | BH12: 0 | BJ12: 2 | BS12: 2 | BT12: 2 | BV12: 1 | BW12: 2025 | BX12: 1 | BY12: 15 | BZ12: 1 | CA12: 0 | CB12: 1 | CC12: 0 | CD12: 0 | CE12: 1 | CG12: 1 | CI12: 67.94 | CJ12: 1 | CK12: 2025 | CL12: 1 | CM12: 5 | CN12: 1 | CO12: 0 | CP12: 1 | CQ12: 0 | CR12: 0 | CS12: 1 | CU12: 4 | CV12: Flat rate + water used | CW12: 56.78 | CX12: 2 | DO12: 1 | DP12: 1946 | DT12: 827 | DU12: 9 | DV12: 19 | DX12: 15 | EA12: 13.7 | EB12: 8 | EC12: 5 | ED12: 0 | EE12: 1936 | EF12: 2019 | EG12: 216000 | EH12: 0.72 | EM12: 1.4 | EU12: never | EV12: 1 | EW12: 1 | EX12: 1 | EZ12: 100 | FD12: 1 | FE12: 1946 | FP12: 17.7 | FQ12: 12 | FR12: 1 | FS12: 2 | FT12: 0 | FU12: 0 | FV12: 1 | FW12: 0 | FX12: 0 | FY12: 0 | FZ12: All wastewater is pumped to St Helens to be treated | GO12: 2 | GQ12: 2 | GT12: 2
A13: Seaside | B13: 7268 | C13: 4 | D13: 1 | E13: 2 | G13: 1 | H13: 1 | I13: 1 | J13: 1 | K13: 0 | L13: 1 | M13: 1 | N13: 0 | O13: 1 | P13: 1 | Q13: 0 | R13: 1 | S13: 0 | U13: 0.1 | W13: 40 | Z13: 86 | AC13: 1 | AD13: We provide a discount for repaired water leaks. Billing errors are handled on a case by case basis. | AE13: 3 | AF13: 3 | AH13: To the demonstrated start of the leak (based on usage), as long as repair is done in a reasonable amount of time. | AI13: We offer a one time reduction for repaired leaks. If approved then the City will waive half of the leak amount above a customer's average bill. | AJ13: 33.3 | AK13: 18.5 | AO13: 1 | AP13: 1 | AQ13: 1 | AT13: Unknown | AU13: N/A | AW13: Unknown | AX13: N/A | AY13: 1 | AZ13: 4 | BB13: Charges continue and are the responsibility of the homeowner | BC13: 0 | BD13: 0 | BE13: 0 | BF13: 0 | BG13: 1 | BH13: 1 | BJ13: 2 | BS13: 2 | BT13: 2 | BV13: 2 | CJ13: 1 | CK13: 2025 | CL13: 1 | CM13: 4.1 | CN13: 1 | CO13: 1 | CP13: 1 | CQ13: 0 | CR13: 0 | CS13: 1 | CU13: 4 | CV13: Flat rate for residential, flat rate plus usage for commercial | CW13: 77.29 | CX13: 2 | DO13: 2 | FD13: 1 | FE13: 7500 | FF13: 1000 | FG13: 35000 | FH13: 1500 | FI13: 2964 | FJ13: 8 | FK13: 710 | FO13: 3920445 | FQ13: 26 | FR13: 6 | FS13: 8 | FT13: 0 | FU13: 0 | FV13: 0 | FW13: 0 | FX13: 1 | FY13: 0 | GA13: 1986 | GB13: 2001 | GC13: 2.25 | GD13: 6.75 | GE13: 1095 | GF13: 4 | GG13: 4 | GI13: Unknown | GJ13: Unknown | GK13: 2 | GL13: 2 | GM13: 0% | GO13: 1 | GP13: Given to local and City-owned farms | GQ13: 2 | GT13: 2
A14: Wheeler | B14: 428 | C14: 1 | D14: 1 | E14: 2 | G14: 1 | H14: 1 | I14: 0 | J14: 0 | K14: 0 | L14: 0 | M14: 2 | N14: 0 | O14: 1 | P14: 1 | Q14: 1 | R14: 1 | S14: 1 | T14: Liens are only issued in severe cases - We've never had to use this method before but our code allows it | U14: 0.015 | V14: 0.015 | W14: 0 | Y14: 0.015 | Z14: 105 | AC14: 1 | AD14: If a customer can show hardship, the City Manager has the authority to grant exceptions to the rule - but this must include the creation of a repayment plan that is feasible for both the City and the water customer. | AE14: 3 | AF14: 2 | AJ14: 0.075 | AN14: 1 | AO14: 1 | AP14: 1 | AR14: 1 | AS14: 2023 | AT14: NA | AU14: 2012 | AV14: 2023 | AW14: NA | AX14: 2012 | AY14: 2 | AZ14: 3 | BC14: 0 | BD14: 0 | BE14: 0 | BF14: 0 | BG14: 1 | BH14: 0 | BJ14: 1 | BK14: 0 | BL14: 0 | BM14: 1 | BN14: 0 | BO14: 0 | BP14: 0 | BQ14: 0 | BR14: Traffic & Safety | BS14: 2 | BU14: 2 | BV14: 2 | CJ14: 2 | CX14: 1 | CY14: 3 | CZ14: 1 | DA14: 0.4 | DB14: 3 | DC14: 0 | DD14: 1 | DE14: 0 | DF14: 0 | DG14: 0 | DH14: 0 | DJ14: 1 | DL14: 2 | DN14: 5 | DO14: 1 | DP14: 259 | DQ14: 0 | DR14: 259 | DS14: 0 | DT14: 223 | DU14: 0 | DV14: 30 | DW14: 1 | DX14: 6 | DY14: 1 | DZ14: 62517 | EA14: 4 | EB14: 2 | EC14: 1 | ED14: 2 | EF14: 2016 | EJ14: 0.61 | EL14: 1 | EM14: 52 | EN14: 1 | EO14: 1 | EP14: 1 | EQ14: 1 | EU14: 2050ish | EV14: 2 | EW14: 1 | EX14: 1 | EZ14: 100 | FD14: 2 | GT14: 1 | GU14: 223 | GV14: 1 | GW14: 30 | GX14: 1 | GY14: 6 | GZ14: 1 | HA14: 4
A15: Fairview | B15: 10473 | C15: 4 | D15: 2 | E15: 4 | F15: WATER AND SEWER ARE MONTHLY. SEWER ONLY IS BI-MONTHLY | G15: 0 | H15: 1 | I15: 1 | J15: 1 | K15: 1 | L15: 1 | M15: 2 | N15: 1 | O15: 1 | P15: 1 | Q15: 0 | R15: 1 | S15: 0 | U15: 0.05 | W15: 10 | Z15: 10 | AC15: 1 | AD15: SNOWBIRD IS 35% DISCOUNT FOR SEWER | AE15: 3 | AF15: 2 | AP15: 2 | AQ15: 2 | AR15: 2 | AS15: 2021 | AT15: 2021 | AU15: 2021 | AV15: 2025 | AW15: 2025 | AX15: 2025 | AY15: 1 | BC15: 0 | BD15: 0 | BE15: 0 | BF15: 0 | BG15: 1 | BH15: 1 | BJ15: 1 | BK15: 1 | BL15: 0 | BM15: 1 | BN15: 0 | BO15: 1 | BP15: 0 | BQ15: 0 | BR15: CAPITAL IMPROVEMENT | BS15: 2 | BT15: 2 | BU15: 2 | BV15: 1 | BW15: 2025 | BX15: 1 | BY15: 8 | BZ15: 0 | CA15: 1 | CB15: 0 | CC15: 0 | CD15: 0 | CE15: 0 | CG15: 1 | CI15: 36.19 | CJ15: 1 | CK15: 2025 | CL15: 1 | CM15: 8 | CN15: 0 | CO15: 1 | CP15: 0 | CQ15: 0 | CR15: 0 | CS15: 0 | CU15: 1 | CW15: 37.36 | CX15: 1 | CY15: 7 | CZ15: 1 | DA15: 8 | DB15: 3 | DC15: 0 | DD15: 1 | DE15: 0 | DF15: 0 | DG15: 0 | DH15: 0 | DJ15: 1 | DL15: 1 | DM15: CAN PETITION FOR REDUCTION | DN15: 13.29 | DO15: 1 | FD15: 1 | GO15: 2 | GT15: 1
A16: Bay City | B16: 1598 | C16: 3 | D16: 1 | E16: 1 | G16: 1 | H16: 1 | I16: 1 | J16: 1 | K16: 1 | L16: 1 | M16: 1 | N16: 0 | O16: 1 | P16: 1 | Q16: 0 | R16: 1 | S16: 0 | U16: 0.1 | W16: 2 | Z16: 90 | AC16: 1 | AD16: Summer irrigation waiver of sewer fees; leak credit for sewer fee and 50% of water charge; option to suspend service for vacation time | AE16: 3 | AF16: 3 | AG16: 60 | AI16: In the case of leaks or summer irrigation, we waive the additional consumption (over the base amount, or the average winter consumption volume). | AO16: 1 | AP16: 2 | AQ16: 2 | AS16: 2024 | AT16: 2010 | AU16: never | AV16: 2024 | AW16: 2024 | AX16: N/A | AY16: 2 | AZ16: 4 | BB16: We do not charge water or sewer, but charge Street Maintenance Fee | BC16: 0 | BD16: 1 | BE16: 0 | BF16: 0 | BG16: 1 | BH16: 0 | BJ16: 2 | BK16: 0 | BL16: 0 | BM16: 0 | BN16: 0 | BO16: 0 | BP16: 1 | BQ16: 0 | BS16: 1 | BT16: 1 | BV16: 1 | BW16: 2025 | BX16: 1 | BY16: 30 | BZ16: 1 | CA16: 1 | CB16: 1 | CC16: 0 | CD16: 0 | CE16: 1 | CG16: 1 | CI16: 56 | CJ16: 1 | CK16: 2025 | CL16: 1 | CM16: 3 | CN16: 0 | CO16: 1 | CP16: 0 | CQ16: 0 | CR16: 0 | CS16: 0 | CU16: 4 | CV16: Water consumption | CW16: 54.57 | CX16: 2 | DO16: 1 | DP16: 1600 | DQ16: 60 | DT16: 800 | DU16: 50 | DV16: 4 | DW16: 2 | DZ16: 55000 | EA16: 8 | EB16: 1 | EC16: 2 | ED16: 8 | EE16: 1981 | EF16: 2024 | EG16: 500000000 | EH16: 2.2 | EI16: 0.8 | EJ16: 0.67 | EK16: 1.1 | EM16: 1.3 | EU16: 2050 | EV16: 1 | EW16: 1 | EX16: 1 | EZ16: 95 | FB16: 5 | FD16: 1 | FE16: 1650 | FI16: 823 | FK16: 4 | FO16: 55000 | FP16: 8 | FQ16: 2 | FR16: 2 | FS16: 2 | FT16: 0 | FU16: 0 | FV16: 0 | FW16: 0 | FX16: 1 | FY16: 0 | GA16: 1983 | GB16: 2023 | GC16: 1.4 | GD16: 1.4 | GE16: 90 | GF16: 1.4 | GG16: 0.4 | GH16: 65 | GI16: 2040 | GJ16: 2040 | GK16: 1 | GL16: 2 | GO16: 2 | GQ16: 2 | GT16: 2
A17: Millersburg | B17: 3214 | C17: 3 | D17: 4 | E17: 2 | G17: 1 | H17: 1 | I17: 1 | J17: 0 | K17: 0 | L17: 0 | M17: 1 | N17: 1 | O17: 1 | P17: 0 | Q17: 1 | R17: 0 | S17: 0 | U17: 0 | V17: 0.09 | X17: 0 | Y17: 0.09 | Z17: 49 | AC17: 2 | AE17: 3 | AF17: 3 | AH17: Customer can get credit for one billing cycle (approx. 60 days). There is not a specific | AI17: Where a water leak exists underground between the meter and the building during the monitoring period for wastewater flow charges, the utility may allow for an adjustment on the wastewater variable charges. In order to qualify for a credit, the leak must be large enough to cause the total consumption to be greater than one and one-half the average amount that has been previously charged to the premises, and the leak must be repaired within 30 days after the customer has been notified of such leak. For most customers, the variable charges will be adjusted to reflect past winter water consumption records for the property. For customers that are billed based on actual monthly water consumption, the variable charges will be calculated using an estimate of consumption based either upon the customer's prior use during the same season of the year or upon a reasonable comparison with the use of other customers receiving the same class of service during the same period and under similar circumstances and conditions. Where past water consumption records are not available, the variable charges will be adjusted to reflect the average water consumption for similar accounts. | AK17: 25 | AM17: 1 | AO17: 1 | AP17: 1 | AQ17: 1 | AR17: 1 | AS17: 2021 | AT17: 2021 | AU17: n/a | AV17: 2020 | AW17: 2020 | AX17: 2020 | AY17: 1 | AZ17: 2 | BC17: 0 | BD17: 1 | BE17: 0 | BF17: 0 | BG17: 0 | BH17: 0 | BJ17: 2 | BK17: 0 | BL17: 0 | BM17: 1 | BN17: 0 | BO17: 0 | BP17: 0 | BQ17: 0 | BR17: none | BS17: 2 | BT17: 2 | BV17: 1 | BW17: 2025 | BX17: 1 | BY17: 0.03 | BZ17: 0 | CA17: 0 | CB17: 0 | CC17: 1 | CD17: 0 | CE17: 0 | CF17: Adopted schedule of increases from rate study in 2021 | CG17: 5 | CH17: Flat + Constant Rate | CI17: 33.36 | CJ17: 1 | CK17: 2025 | CL17: 1 | CM17: 0.075 | CN17: 0 | CO17: 0 | CP17: 0 | CQ17: 1 | CR17: 0 | CS17: 0 | CT17: Adopted schedule of rate increases from 2021 | CU17: 4 | CV17: Flat rate plus winter average water consumption used all year | CW17: 76.22 | CX17: 2 | DO17: 1 | DP17: 3214 | DQ17: 0 | DR17: 3214 | DS17: 0 | DT17: 1276 | DU17: 0 | DV17: 105 | DW17: 1 | DX17: 0 | DY17: 1 | DZ17: 116000000 | EB17: 0 | EC17: 1 | ED17: 2.5 | EE17: 2006 | EG17: 46 | EH17: 12 | EL17: 1 | EM17: 5.7 | EN17: 1 | EO17: 1 | EP17: 1 | EQ17: 1 | EU17: Millersburg shares a treatment plant with Albany. Plant operations and production rates are reflective of both communities. Albany operates the plant. | EV17: 1 | EW17: 1 | EX17: 1 | FA17: 100 | FC17: Millersburg shares a treatment plant with Albany. Plant operations and production rates are reflective of both communities. Albany operates the plant. | FD17: 1 | FE17: 3214 | FF17: 0 | FG17: 3214 | FH17: 0 | FI17: 1276 | FJ17: 1 | FK17: 105 | FL17: 1 | FM17: 0 | FN17: 1 | FQ17: 4 | FR17: 2 | FS17: 2 | FT17: 0 | FU17: 0 | FV17: 1 | FW17: 0 | FX17: 1 | FY17: 1 | FZ17: Millersburg and Albany jointly own the wastewater plant. Albany operates the plant and administers Millersburg's industrial pretreatment program. | GK17: 1 | GL17: 2 | GM17: na | GO17: 2 | GQ17: 1 | GR17: 3 | GT17: 1 | GV17: 6 | GX17: 4 | GZ17: 3 | HC17: 4200
A18: Richland | B18: 165 | C18: 1 | D18: 12 | E18: 1 | G18: 1 | H18: 1 | I18: 1 | J18: 0 | K18: 1 | L18: 1 | M18: 2 | N18: 0 | O18: 1 | P18: 1 | Q18: 0 | R18: 0 | S18: 0 | U18: 15 | W18: 30 | Z18: 2 | AC18: 2 | AE18: 3 | AF18: 2 | AG18: 30 | AH18: If we find a month we back out all overages for the current month. | AO18: 1 | AS18: 2022 | AY18: 2 | AZ18: 2 | BC18: 1 | BD18: 1 | BE18: 0 | BF18: 0 | BG18: 0 | BH18: 0 | BJ18: 2 | BV18: 1 | BW18: 2025 | BX18: 1 | BY18: 3 | BZ18: 0 | CA18: 0 | CB18: 0 | CC18: 0 | CD18: 0 | CE18: 1 | CG18: 5 | CH18: Base Rate then overages for anything over the alloted number of gallons | CI18: 48.5 | CJ18: 1 | CU18: 1 | CW18: 32.5 | CX18: 2 | DO18: 1
A19: Scotts Mills | B19: 459 | C19: 1 | D19: 3 | E19: 4 | F19: Every other month | G19: 1 | H19: 1 | I19: 1 | J19: 0 | K19: 1 | L19: 0 | M19: 2 | N19: 1 | O19: 1 | P19: 1 | Q19: 0 | R19: 1 | S19: 0 | U19: 30 | W19: 3 | Z19: 15 | AA19: 400 | AB19: 30 | AC19: 2 | AE19: 3 | AF19: 2 | AH19: Council has to approve it but typically we look at the previous same billing period and cut 50% of the overage credited back to customer. | AJ19: 100 | AN19: 1 | AP19: 1 | AR19: 1 | AY19: 2 | AZ19: 2 | BJ19: 2 | BV19: 1 | BW19: 2025 | BX19: 1 | BY19: 0.5 | BZ19: 1 | CA19: 0 | CB19: 0 | CC19: 0 | CD19: 0 | CE19: 0 | CG19: 1 | CI19: 167.68 | CJ19: 2 | CX19: 2 | DO19: 1
A20: Elgin | B20: 1822 | C20: 3 | D20: 11 | E20: 1 | G20: 1 | H20: 1 | I20: 1 | J20: 0 | K20: 1 | L20: 0 | M20: 1 | N20: 1 | O20: 1 | P20: 1 | Q20: 0 | R20: 1 | S20: 0 | W20: 30 | Z20: 30 | AB20: 30 | AC20: 1 | AD20: City employees and first responders receive water discounts | AE20: 2 | AG20: 0
A21: Canyonville | B21: 1643 | C21: 3 | D21: 7 | E21: 1 | G21: 1 | H21: 1 | I21: 1 | J21: 0 | K21: 0 | L21: 0 | M21: 1 | N21: 1 | O21: 1 | P21: 1 | Q21: 0 | R21: 1 | S21: 0 | U21: 10 | W21: 30 | AA21: 50 | AC21: 1 | AD21: The late fee can be waived if they have not been late during that year. No discounts and no reductions given. | AE21: 3 | AF21: 1 | AH21: We do not make adjustments to water bill unless the water useage is extremely high and then we look at their monthly useage and adjust accordenly. | AI21: Usually will adjust off any of the overage that is calculated by the water overage. | AJ21: 0 | AK21: 23 | AL21: 0 | AP21: 1 | AQ21: 1 | AR21: 1 | AS21: 2023 | AT21: 2015 | AV21: 2015 | AW21: 2015 | AY21: 2 | AZ21: 4 | BB21: Owner required to pay base rate for water/wasetwater | BC21: 0 | BD21: 0 | BE21: 0 | BF21: 1 | BG21: 0 | BH21: 0 | BI21: Deposit of 2 1/2 times the base rate for water/wastewater | BJ21: 2 | BK21: 0 | BL21: 0 | BM21: 1 | BN21: 0 | BO21: 0 | BP21: 0 | BQ21: 0 | BR21: None | BS21: 2 | BT21: 2 | BU21: 2 | BV21: 1 | BW21: 2024 | BX21: 1 | BY21: 12.5 | BZ21: 1 | CA21: 0 | CB21: 0 | CC21: 0 | CD21: 0 | CE21: 0 | CG21: 5 | CH21: base rate plus consumption | CI21: 25.05 | CJ21: 1 | CK21: 2017 | CL21: 1 | CM21: 0.0959 | CN21: 1 | CO21: 0 | CP21: 0 | CQ21: 0 | CR21: 0 | CS21: 0 | CU21: 4 | CV21: flat rate (wtr 1200 cf) plus overage | CW21: 44.56 | CX21: 2 | DO21: 1
A22: Sweet Home | B22: 10116 | C22: 4 | D22: 4 | E22: 1 | G22: 1 | H22: 1 | I22: 1 | J22: 1 | K22: 1 | L22: 1 | M22: 1 | N22: 0 | O22: 1 | P22: 0 | Q22: 1 | R22: 1 | S22: 0 | U22: 5 | X22: 5 | AC22: 1 | AD22: Documentation showing low income is provided along with a completed form. | AE22: 3 | AF22: 3 | AH22: Will adjustment 2 months of bills. Must be requested within 6 months of issue. | AI22: In the winter months and adjustment based on a 12-month average. The adjustment will be made to bring the billing to the 12 month average. | AJ22: 26 | AK22: 17 | AL22: 0 | AP22: 1 | AQ22: 1 | AR22: 1 | AS22: 2023 | AT22: 2023 | AU22: 2023 | AV22: 2023 | AW22: 2023 | AX22: 2023 | AY22: 2 | AZ22: 2 | BC22: 0 | BD22: 0 | BE22: 0 | BF22: 0 | BG22: 0 | BH22: 1 | BJ22: 1 | BK22: 0 | BL22: 0 | BM22: 1 | BN22: 0 | BO22: 0 | BP22: 0 | BQ22: 0 | BR22: None | BS22: 2 | BT22: 2 | BU22: 2 | BV22: 1 | BW22: 2023 | BX22: 1 | BY22: 3 | BZ22: 0 | CA22: 1 | CB22: 1 | CC22: 0 | CD22: 0 | CE22: 1 | CG22: 1 | CI22: 52.8 | CJ22: 1 | CK22: 2023 | CL22: 1 | CM22: 3 | CN22: 1 | CO22: 1 | CP22: 1 | CQ22: 0 | CR22: 0 | CS22: 1 | CU22: 3 | CW22: 79.15 | CX22: 1 | CY22: 6 | CZ22: 1 | DA22: 3 | DB22: 2 | DC22: 1 | DD22: 0 | DE22: 1 | DF22: 0 | DG22: 0 | DH22: 1 | DJ22: 1 | DL22: 2 | DN22: 4 | DO22: 1 | DP22: 10097 | DT22: 3050 | DU22: 14 | DV22: 265 | DW22: 2 | DZ22: 3740 | EA22: 56.72 | EB22: 2 | EC22: 3 | EE22: 2010 | EH22: 6 | EI22: 1.106 | EJ22: 800000 | EK22: 1800 | EO22: 6 | EU22: 2043 | EV22: 1 | EW22: 1 | EZ22: 99.985 | FA22: 0.015 | FD22: 1 | FE22: 10097 | FI22: 3326 | FK22: 15 | FO22: 55.56 | FP22: 50.24 | FQ22: 0 | FR22: 2 | FS22: 2 | FT22: 1 | FU22: 0 | FV22: 0 | FW22: 0 | FX22: 0 | FY22: 1 | GA22: 1947 | GB22: 2023 | GC22: 1.38 | GD22: 7 | GE22: 747.7 | GF22: 7 | GG22: 2.102 | GH22: 100 | GI22: 1994 | GJ22: 1994 | GK22: 2 | GL22: 2 | GM22: N/A | GO22: 2 | GQ22: 1 | GR22: 1 | GT22: 1 | GU22: 3326 | GW22: 15 | HA22: 30.86 | HB22: 46.64 miles | HC22: 3200
A23: Maywood Park | B23: 830 | C23: 2 | D23: 2
A24: Oakridge | B24: 3167 | C24: 3 | D24: 4 | E24: 1 | G24: 1 | H24: 1 | I24: 1 | J24: 1 | K24: 1 | L24: 1 | M24: 1 | N24: 1 | O24: 1 | P24: 1 | Q24: 0 | R24: 1 | S24: 0 | U24: 0.1 | Z24: 65 | AA24: 20 | AB24: 60 | AC24: 2 | AE24: 3 | AF24: 2 | AG24: 60 | AM24: 1 | AN24: 1 | AO24: 1 | AP24: 2 | AQ24: 2 | AR24: 2 | AT24: unknown | AU24: unknown | AW24: unknown | AX24: unknown | AY24: 2 | AZ24: 2 | BC24: 0 | BD24: 0 | BE24: 0 | BF24: 1 | BG24: 0 | BH24: 0 | BI24: $6 Ambulance Service Fee | BJ24: 1 | BK24: 0 | BL24: 0 | BM24: 1 | BN24: 0 | BO24: 0 | BP24: 0 | BQ24: 0 | BR24: $6 Ambulance Service Fee | BS24: 1 | BT24: 1 | BU24: 1 | BV24: 1 | BX24: 1 | BY24: 0.03 | BZ24: 0 | CA24: 1 | CB24: 0 | CC24: 0 | CD24: 0 | CE24: 0 | CG24: 4 | CI24: 114.31 | CJ24: 1 | CL24: 1 | CM24: 3 | CN24: 0 | CO24: 1 | CP24: 0 | CQ24: 0 | CR24: 0 | CS24: 0 | CU24: 1 | CW24: 114.31 | CX24: 1 | CY24: 9 | CZ24: 1 | DA24: 0.03 | DB24: 3 | DC24: 0 | DD24: 1 | DE24: 0 | DF24: 0 | DG24: 0 | DH24: 0 | DJ24: 1 | DL24: 2 | DN24: 6.66 | DO24: 1
A25: Port Orford | B25: 1167 | C25: 2 | D25: 6 | E25: 1 | G25: 1 | H25: 1 | I25: 1 | J25: 1 | K25: 1 | L25: 0 | M25: 2 | N25: 0 | O25: 1 | P25: 1 | Q25: 0 | R25: 1 | S25: 0 | U25: 15 | W25: 7 | Z25: 90 | AC25: 2 | AE25: 3 | AF25: 3 | AG25: 90 | AH25: We only read meters once a month, so people can have one catastrophic leak forgiven each year. Sewer credits are given if the leak is not going to the sewer. | AI25: We adjust at a percentage depending where the leak happened. EX: if the overage was from a leak in the yard, 100% forgiveness on that portion would be given. If there was a leak in the yard but the plumber also fixed a leaky kitchen faucet, 50% would be given. If the shower leaked, no sewer credit would be given. It is up to the team/ me to decide based on evidence submitted.
A26: Rufus | B26: 277 | C26: 1 | D26: 8 | E26: 1 | G26: 1 | H26: 1 | I26: 1 | J26: 0 | K26: 1 | L26: 0 | M26: 2 | N26: 0 | O26: 1 | P26: 1 | Q26: 0 | R26: 1 | S26: 1 | T26: Payment arrangements | U26: 7.5 | W26: 10 | AC26: 2 | AE26: 3 | AF26: 2 | AH26: We will go back to the point leak is detected and adjust 50% of the over average usage | AP26: 1 | AQ26: 1 | AT26: Unsure | AU26: Unsure | AW26: Unsure | AX26: Unsure | AY26: 2 | AZ26: 4 | BB26: only close account at request of owner. If renter moves out, automatically goes into owner's name unless requested to close accout. | BC26: 0 | BD26: 0 | BE26: 0 | BF26: 1 | BG26: 0 | BH26: 0 | BI26: Water maintenance fee and sewer maintenance fee | BJ26: 2 | BS26: 2 | BT26: 2 | BU26: 2 | BV26: 1 | BW26: 2025 | BX26: 1 | BY26: 0.09 | BZ26: 0 | CA26: 1 | CB26: 1 | CC26: 1 | CD26: 1 | CE26: 1 | CF26: Not meeting Debt Service Requiremen | CG26: 5 | CH26: Base rate plus Usage | CJ26: 1 | CK26: 2025 | CL26: 1 | CM26: 0.1 | CN26: 0 | CO26: 1 | CP26: 1 | CQ26: 0 | CR26: 0 | CS26: 1 | CU26: 1 | CW26: 57.5 | CX26: 2 | DO26: 1 | DP26: 277 | DQ26: 1 | DT26: 140 | DV26: 17 | DW26: 2 | DZ26: 36000 | EA26: 2.21 | EB26: 6 | EC26: 2 | ED26: 0 | EE26: 1948 | EF26: 2001 | EG26: 0.8 | EH26: 0.6 | EI26: 22.4 | EJ26: 60000 | EK26: 140000 | EL26: 8 | EM26: 0.8 | EN26: 6 | EO26: 11 | EP26: 8 | EQ26: 7 | EU26: more than 50 years | EV26: 1 | EW26: 1 | EX26: 1 | FB26: 100 | FD26: 1 | FE26: 277 | FF26: 1 | FI26: 139 | FK26: 17 | FL26: 2 | FO26: 58000 | FP26: 2.1 | FQ26: 6 | FR26: 2 | FS26: 2 | FT26: 0 | FU26: 0 | FV26: 1 | FW26: 0 | FX26: 0 | FY26: 0 | FZ26: Lagoon, Natural | GA26: 1976 | GB26: 2010 | GD26: 0.09 | GE26: 9.8 | GF26: 0.036 | GG26: 0.034 | GH26: 0.75 | GI26: 2026- system is being upgraded this year to accomodate issues | GJ26: 2026 - Effulent irrigation is being replaced this fall | GK26: 1 | GL26: 2 | GM26: 70% | GO26: 2 | GS26: Wastewater Treatment plant is replacing most key items for the irrigation system. This will change exceeds capacity to 2050. | GT26: 2
A27: Arlington | B27: 678 | C27: 2 | D27: 8 | E27: 1 | G27: 1 | H27: 1 | I27: 1 | J27: 0 | K27: 1 | L27: 1 | M27: 1 | N27: 1 | O27: 1 | P27: 1 | Q27: 0 | R27: 0 | S27: 0 | U27: 5 | W27: 30 | Z27: 90 | AC27: 1 | AD27: Collections don't happen until someone leaves without paying their final bill. The City waives utility charges for our EMS, Fire Hall, and Police Office. | AE27: 3 | AF27: 2 | AH27: Depending on situation. | AY27: 2 | AZ27: 1 | BA27: They have to come to us to let us know someone has moved out. | BC27: 0 | BD27: 0 | BE27: 0 | BF27: 1 | BG27: 0 | BH27: 0 | BI27: Turn on is charged. | BJ27: 2 | BS27: 2 | BT27: 2 | BU27: 2 | BV27: 1 | BW27: 2023 | BX27: 1 | BY27: 0.05 | BZ27: 0 | CA27: 1 | CB27: 0 | CC27: 0 | CD27: 0 | CE27: 0 | CG27: 5 | CH27: Water, sewer, sanitation, and water overage usage above 7500 gallons per month. Out of town rate for water is $6 more than in town, | CI27: 42 | CJ27: 1 | CK27: 2023 | CL27: 1 | CM27: 0.05 | CN27: 0 | CO27: 1 | CP27: 0 | CQ27: 0 | CR27: 0 | CS27: 0 | CU27: 4 | CV27: Water, sewer, sanitation, and water overage usage above 7500 gallons per month. | CW27: 46 | CX27: 2 | DO27: 1
A28: Halsey | B28: 975 | C28: 2 | D28: 4 | E28: 1 | G28: 1 | H28: 1 | I28: 1 | J28: 0 | K28: 1 | L28: 0 | M28: 1 | N28: 0 | O28: 1 | P28: 1 | Q28: 0 | R28: 0 | S28: 0 | U28: 5 | Z28: 3 | AC28: 2 | AE28: 3 | AF28: 3 | AG28: 30 | AH28: We utilize historical use data and adjust to pre-leak usage | AI28: Wastewater is calculated based on water usage so when water is adjusted due to leak detection we also adjust wastewater to match the adjusted water usage rate calculated on the corrected bill | AM28: 1 | AN28: 1 | AO28: 1 | AP28: 1 | AQ28: 1 | AR28: 2 | AT28: No | AU28: No | AV28: 2022 | AW28: n/a | AX28: n/a | AY28: 2 | AZ28: 4 | BB28: If a property is vacant but the owner has not requested account closure the account remains open and is billed normally. | BC28: 1 | BD28: 1 | BE28: 0 | BF28: 1 | BG28: 1 | BH28: 1 | BI28: Turn on fees | BJ28: 1 | BS28: 1 | BT28: 1 | BU28: 2 | BV28: 1 | BW28: 2025 | BX28: 1 | BY28: 2.5 | BZ28: 0 | CA28: 1 | CB28: 1 | CC28: 0 | CD28: 0 | CE28: 1 | CG28: 1 | CI28: 53.34 | CJ28: 1 | CK28: 2025 | CL28: 1 | CM28: 2.5 | CN28: 0 | CO28: 1 | CP28: 1 | CQ28: 0 | CR28: 0 | CS28: 1 | CU28: 4 | CV28: Flat rate based on water consumption in the month billed | CW28: 47 | CX28: 1 | DB28: 3 | DJ28: 1 | DL28: 2 | DN28: 3 | DO28: 1
A29: Mt. Vernon | B29: 549 | C29: 2 | D29: 12 | E29: 1 | G29: 1 | H29: 1 | I29: 1 | J29: 0 | K29: 1 | L29: 1 | M29: 2 | N29: 1 | O29: 1 | P29: 1 | Q29: 0 | R29: 0 | S29: 0 | W29: 15 | AB29: 15 | AC29: 2 | AE29: 3 | AF29: 2 | AH29: Most people find it by then.
A30: Roseburg | B30: 23910 | C30: 5 | D30: 7 | E30: 4 | F30: every 2 months | G30: 1 | H30: 1 | I30: 1 | J30: 1 | K30: 1 | L30: 0 | M30: 1 | N30: 1 | O30: 1 | P30: 1 | Q30: 0 | R30: 0 | S30: 0 | U30: 20 | W30: 30 | Z30: 45 | AB30: 75 | AC30: 2 | AE30: 3 | AF30: 2 | AG30: 1 | AM30: 1 | AN30: 1 | AO30: 1 | AP30: 1 | AR30: 1 | AS30: 2015 | AT30: n/a | AU30: unknown | AV30: 2015 | AW30: n/a | AX30: unknown | AY30: 2 | AZ30: 4 | BB30: account reverts to the property owner who is responsible for the base water fees and the storm water fees | BC30: 0 | BD30: 1 | BE30: 0 | BF30: 0 | BG30: 1 | BH30: 1 | BJ30: 1 | BS30: 1 | BU30: 1 | BV30: 1 | BW30: 2025 | BX30: 1 | BY30: 2.2 | BZ30: 0 | CA30: 1 | CB30: 0 | CC30: 0 | CD30: 0 | CE30: 0 | CG30: 1 | CI30: 34.21 | CJ30: 2 | CX30: 1 | CY30: 7 | CZ30: 1 | DA30: 2.2 | DB30: 2 | DC30: 0 | DD30: 1 | DE30: 0 | DF30: 0 | DG30: 0 | DH30: 0 | DJ30: 1 | DL30: 1 | DM30: by the amount of permanent reduction to the runoff coefficient for the property due to the retention system. | DN30: 9.43 | DO30: 1 | DP30: 23795 | DQ30: 6000 | DT30: 7498 | DU30: 2466 | DV30: 1388 | DW30: 3 | DX30: 107 | DY30: 3 | DZ30: 120000 | EA30: 195 | EB30: 21 | EC30: 27 | ED30: 5 | EE30: 1935 | EF30: 1992 | EG30: 20 | EH30: 12 | EI30: 5.814 | EJ30: 2.061 | EK30: 8.872 | EL30: 1 | EM30: 11.2 | EN30: 1 | EO30: 1 | EP30: 1 | EQ30: 1 | ER30: N/A | ES30: 0 | ET30: 0 | EU30: It has not exceeded capacity | EV30: 1 | EW30: 1 | EX30: 1 | EZ30: 0 | FA30: 0.5 | FB30: 99.5 | FC30: none | FD30: 2 | GT30: 1 | GU30: 7498 | GV30: 1 | GW30: 1388 | GX30: 1 | GY30: 107 | GZ30: 1 | HA30: 104 | HB30: unknown | HC30: 3000 | HD30: none
A31: Ione | B31: 342 | C31: 1 | D31: 11 | E31: 1 | G31: 1 | H31: 1 | I31: 1 | J31: 1 | K31: 1 | L31: 0 | M31: 2 | N31: 1 | O31: 1 | P31: 1 | Q31: 0 | R31: 0 | S31: 0 | U31: 25 | W31: 30 | Z31: 60 | AB31: 75 | AC31: 2 | AE31: 3 | AF31: 2 | AG31: 30 | AJ31: 75 | AP31: 1 | AY31: 2 | AZ31: 2 | BC31: 0 | BD31: 0 | BE31: 0 | BF31: 0 | BG31: 1 | BH31: 0 | BJ31: 2 | BS31: 2 | BV31: 1 | BW31: 2021 | BX31: 1 | BY31: 0.02 | BZ31: 0 | CA31: 1 | CB31: 1 | CC31: 0 | CD31: 0 | CE31: 0 | CG31: 1 | CI31: 47.85 | CJ31: 2 | CX31: 2 | DO31: 1
A32: Joseph | B32: 1182 | C32: 2 | D32: 11 | E32: 1 | G32: 1 | H32: 1 | I32: 1 | J32: 0 | K32: 1 | L32: 1 | M32: 1 | N32: 1 | O32: 1 | P32: 1 | Q32: 0 | R32: 0 | S32: 0
A33: Yamhill | B33: 1309 | C33: 2 | D33: 3 | E33: 1 | G33: 1 | H33: 1 | I33: 1 | J33: 0 | K33: 1 | L33: 1 | M33: 1 | N33: 0 | O33: 1 | P33: 1 | Q33: 0 | R33: 1 | S33: 0 | U33: 5 | W33: 30 | Z33: 90 | AC33: 2 | AE33: 3 | AF33: 2 | AG33: 30 | AH33: Or since they are notified of possible leak | AJ33: 18 | AK33: 16 | AO33: 1 | AP33: 2 | AQ33: 2 | AR33: 2 | AS33: 2023 | AT33: 2023 | AU33: N/A | AV33: 2023 | AW33: 2023 | AY33: 2 | AZ33: 1 | BA33: Water used only, no base rate. No sewer charge. | BC33: 1 | BD33: 1 | BE33: 0 | BF33: 1 | BG33: 1 | BH33: 1 | BI33: City services fees for police and stormwater | BJ33: 1 | BK33: 0 | BL33: 0 | BM33: 0 | BN33: 0 | BO33: 1 | BP33: 0 | BQ33: 0 | BS33: 2 | BT33: 2 | BU33: 2 | BV33: 2 | CJ33: 2 | CX33: 1 | CY33: 4 | CZ33: 1 | DB33: 3 | DC33: 0 | DD33: 1 | DE33: 0 | DF33: 0 | DG33: 0 | DH33: 0 | DJ33: 1 | DL33: 2 | DN33: 2 | DO33: 1
A34: Imbler | B34: 253 | C34: 1 | D34: 11 | E34: 1 | G34: 1 | H34: 1 | I34: 0 | J34: 0 | K34: 0 | L34: 0 | M34: 1 | N34: 0 | O34: 1 | P34: 1 | Q34: 0 | R34: 0 | S34: 0 | AC34: 2 | AE34: 2
A35: Ukiah | B35: 277 | C35: 1 | D35: 11 | E35: 1 | G35: 1 | H35: 1 | I35: 1 | J35: 1 | K35: 1 | L35: 0 | M35: 2 | N35: 0 | O35: 1 | P35: 1 | Q35: 0 | R35: 1 | S35: 0 | U35: 0.0005 | W35: 60 | Z35: 30 | AC35: 2 | AE35: 3 | AF35: 2 | AG35: 60
A36: St. Helens | B36: 14552 | C36: 5 | D36: 1 | E36: 1 | G36: 1 | H36: 1 | I36: 1 | J36: 1 | K36: 1 | L36: 1 | M36: 1 | N36: 0 | O36: 1 | P36: 1 | Q36: 0 | R36: 1 | S36: 0 | U36: 25 | W36: 10 | Z36: 20 | AC36: 2 | AE36: 3 | AF36: 2 | AH36: 2 months | AJ36: 12 | AK36: 14 | AO36: 1 | AS36: 2021 | AT36: 2021 | AU36: 2021 | AY36: 2 | AZ36: 4 | BB36: Charge base rates to vacant properties. | BC36: 0 | BD36: 0 | BE36: 0 | BF36: 0 | BG36: 1 | BH36: 1 | BJ36: 1 | BK36: 0 | BL36: 0 | BM36: 1 | BN36: 0 | BO36: 0 | BP36: 0 | BQ36: 0 | BR36: Public Safety Facility Fee | BS36: 2 | BT36: 2 | BU36: 2 | BV36: 1 | BW36: 2025 | BX36: 1 | BY36: 2.99 | BZ36: 1 | CA36: 0 | CB36: 1 | CC36: 0 | CD36: 0 | CE36: 1 | CG36: 1 | CI36: 53.64 | CJ36: 1 | CK36: 2025 | CL36: 1 | CM36: 9.26 | CN36: 1 | CO36: 0 | CP36: 1 | CQ36: 0 | CR36: 0 | CS36: 1 | CU36: 4 | CV36: Flat + volume(water). Winter average avail | CW36: 77.92 | CX36: 1 | CY36: 7 | CZ36: 1 | DA36: 0.99 | DC36: 1 | DD36: 0 | DE36: 1 | DF36: 0 | DG36: 0 | DH36: 1 | DJ36: 2 | DK36: Flat rate per EDU | DL36: 2 | DN36: 19.86 | DO36: 1 | FD36: 1 | GO36: 2 | GQ36: 2 | GS36: No | GT36: 1 | HD36: No
A37: Cascade Locks | B37: 1412 | C37: 3 | D37: 8
A38: Paisley | B38: 260 | C38: 1 | D38: 10 | E38: 1 | G38: 1 | H38: 1 | I38: 1 | J38: 0 | K38: 1 | L38: 0 | M38: 1 | N38: 0 | O38: 1 | P38: 1 | Q38: 0 | R38: 0 | S38: 0 | U38: 0.015 | W38: 1 | Z38: 90 | AC38: 2 | AE38: 3 | AF38: 2 | AG38: 30 | AH38: Customer needs to make an effort of fixing leak and talking to water maintenance to make adjustments on bill.
A39: Cave Junction | B39: 2103 | C39: 3 | D39: 7 | E39: 1 | G39: 1 | H39: 1 | I39: 0 | J39: 0 | K39: 1 | L39: 0 | M39: 2 | N39: 0 | O39: 1 | P39: 1 | Q39: 0 | R39: 0 | S39: 0 | U39: 25 | W39: 30 | Z39: 43 | AC39: 2 | AE39: 2 | AG39: 0 | AH39: Customer is responsible for any leaks on their side of the meter
A40: Malin | B40: 736 | C40: 2 | D40: 10 | E40: 2 | G40: 1 | H40: 1 | I40: 1 | J40: 0 | K40: 0 | L40: 0 | M40: 2 | N40: 1 | O40: 1 | P40: 0 | Q40: 1 | R40: 1 | S40: 0 | U40: 0.015 | V40: 0.015 | X40: 0.015 | Y40: 0.015 | Z40: 60 | AB40: 60 | AC40: 1 | AD40: 10% discount for veterans. Non profit organizations pay $25 per year. | AE40: 3 | AF40: 2 | AG40: 30
A41: Vernonia | B41: 2433 | C41: 3 | D41: 1 | E41: 1 | G41: 1 | H41: 1 | I41: 1 | J41: 0 | K41: 1 | L41: 1 | M41: 1 | N41: 1 | O41: 1 | P41: 1 | Q41: 0 | R41: 0 | S41: 0
A42: West Linn | B42: 27568 | C42: 5 | D42: 2 | E42: 1 | G42: 1 | H42: 1 | I42: 1 | J42: 1 | K42: 1 | L42: 0 | M42: 1 | N42: 1 | O42: 1 | P42: 1 | Q42: 0 | R42: 0 | S42: 0 | U42: 0.02 | W42: 10 | AA42: 200 | AB42: 90 | AC42: 1 | AD42: We have a low income assistance program that is based off of 185% of the Federal Poverty line. If customer applies and provides proof of income that their household income is below that limit, then they get approximately a $70 reduction on their bill. | AE42: 3 | AF42: 3 | AG42: 365 | AH42: We allow customers to apply for a leak adjustment up to 12 months after the leak occurred. We compare the current water usage with the prior year, split the overage and provide a credit. For residential customers, sewer charges are flat so no credit. For commercial customers, we do provide a sewer credit if applicable. | AI42: For sewer, residential customers have flat sewer charges so there is no adjustment because they receive the same flat rate. For commercial customers, we charge them the same amount of water CCUs. The first 10 CCUs are included in base billing and then after that there is a per CCU fee. If a commercial property has a leak adjustment, then we do also review sewer charges and provide a pro-rated rebate over 10 CCUs. | AY42: 2 | AZ42: 2 | BC42: 0 | BD42: 0 | BE42: 0 | BF42: 0 | BG42: 1 | BH42: 0 | BJ42: 1 | BK42: 0 | BL42: 0 | BM42: 0 | BN42: 1 | BO42: 0 | BP42: 1 | BQ42: 1 | BV42: 2 | CJ42: 1 | CK42: 2025 | CL42: 1 | CM42: 5 | CN42: 0 | CO42: 1 | CP42: 0 | CQ42: 0 | CR42: 0 | CS42: 0 | CU42: 1 | CX42: 1 | CY42: 7 | CZ42: 1 | DA42: 5 | DC42: 0 | DD42: 1 | DE42: 0 | DF42: 0 | DG42: 0 | DH42: 0 | DJ42: 1 | DL42: 1 | DM42: free | DO42: 1 | FD42: 1 | GO42: 2 | GT42: 1
A43: Gresham | B43: 115233 | C43: 5 | D43: 2 | E43: 2
A44: Cornelius | B44: 14490 | C44: 5 | D44: 2 | E44: 1 | G44: 1 | H44: 1 | I44: 1 | J44: 1 | K44: 1 | L44: 1 | M44: 1 | N44: 1 | O44: 1 | P44: 0 | Q44: 0 | R44: 0 | S44: 0 | AA44: 25 | AB44: 30 | AC44: 1 | AD44: Senior Discount of $5 per month. Utility relief for those that qualify - Max of $300 per year up to two monthly bills. | AE44: 3 | AF44: 3 | AH44: Typically only 30 days. If the leak crossed multiple billing cycles we will go back 60 days. | AI44: A portion of the Wastewater (sewer) billing is based on the customers prior year 6 month average for the months of October-April. If a leak occurred during these 6 months then we exclude the leak month and re-calculate the average. | AJ44: 4 | AN44: 1 | AO44: 1 | AP44: 1 | AQ44: 1 | AR44: 1 | AS44: 2019 | AT44: 2019 | AU44: 2019 | AV44: 2019 | AW44: 2019 | AX44: 2019 | AY44: 2 | AZ44: 4 | BB44: All properties charged for Stormwater whether vacant or occupied. | BC44: 1 | BD44: 1 | BE44: 0 | BF44: 1 | BG44: 1 | BH44: 1 | BI44: General Service Fee | BJ44: 1 | BK44: 0 | BL44: 0 | BM44: 1 | BN44: 0 | BO44: 0 | BP44: 0 | BQ44: 0 | BR44: General Services Fee | BS44: 2 | BT44: 2 | BU44: 2 | BV44: 1 | BW44: 2025 | BX44: 1 | BY44: 0.02 | BZ44: 1 | CA44: 0 | CB44: 1 | CC44: 0 | CD44: 0 | CE44: 1 | CG44: 1 | CI44: 48.6 | CJ44: 1 | CK44: 2025 | CL44: 1 | CM44: 0.03 | CN44: 1 | CO44: 0 | CP44: 1 | CQ44: 1 | CR44: 0 | CS44: 1 | CT44: Passthrough fee from partner agency CWS | CU44: 4 | CV44: Flat rate plus winter average | CW44: 68.52 | CX44: 1 | CY44: 7 | CZ44: 1 | DA44: 0.03 | DB44: 3 | DC44: 1 | DD44: 0 | DE44: 1 | DF44: 1 | DG44: 0 | DH44: 1 | DI44: passthrough fee from partner agency CWS | DJ44: 1 | DL44: 1 | DM44: The credit is for System Development Charges only. Customers still pay the full monthly service fees. | DN44: 16.3 | DO44: 1 | DP44: 14389 | DR44: 14389 | DT44: 3934 | DV44: 263 | DZ44: 6000 | EA44: 44.9 | EI44: 1.003 | EJ44: 1 | EQ44: 2 | EU44: Unknown | EV44: 2 | EW44: 1 | EX44: 1 | EZ44: 99.99 | FB44: 0.01 | FC44: Water is purchased wholesale from the City of Cornelius. Cornelius has a water tower and an ASR Resevoir | FD44: 1 | FE44: 14389 | FG44: 14389 | FI44: 3934 | FK44: 263 | FO44: 6000 | FP44: 38.09 | FR44: 7 | FS44: 9 | FT44: 0 | FU44: 0 | FV44: 1 | FW44: 0 | FX44: 0 | FY44: 0 | FZ44: Unknown - treatment is handled by CWS | GI44: Unknown - managed by CWS | GJ44: Unknown - managed by CWS | GK44: 2 | GL44: 2 | GM44: Unknown - managed by CWS | GO44: 2 | GQ44: 2 | GS44: Wastewater (sewer) is treated and managed by CWS | GT44: 1 | GU44: 3934 | GW44: 263 | HA44: 34.97 | HB44: Unknown | HC44: 2640
A45: Gresham | B45: 115233 | C45: 5 | D45: 2 | E45: 2 | G45: 1 | H45: 1 | I45: 1 | J45: 1 | K45: 1 | L45: 1 | M45: 1 | N45: 1 | O45: 1 | P45: 1 | Q45: 0 | R45: 1 | S45: 1 | T45: robo call prior to disconnect; email reminders at certain trigger points
A46: Vernonia | B46: 2433 | C46: 3 | D46: 1 | E46: 1 | G46: 1 | H46: 1 | I46: 1 | J46: 1 | K46: 1 | L46: 1 | M46: 1 | N46: 1 | O46: 1 | P46: 1 | Q46: 0 | R46: 0 | S46: 0 | U46: 0.06 | W46: 15 | Z46: 25 | AB46: 60 | AC46: 2 | AE46: 3 | AF46: 2 | AG46: 30 | AH46: Customer must fix water leak within 30 days to receive leak forgiveness. | AJ46: 0.112 | AK46: 0.369 | AO46: 1 | AP46: 1 | AQ46: 1 | AR46: 1 | AS46: 2012 | AT46: 2013 | AU46: n/a | AV46: 2023 | AW46: 2023 | AX46: n/a | AY46: 2 | AZ46: 4 | BB46: Most vacate property owners choose to close their utility account, however some property owners choose to leave utilities on and pay a normal bill. It is the account holders responsibility to close the account. | BC46: 0 | BD46: 1 | BE46: 0 | BF46: 1 | BG46: 1 | BH46: 0 | BI46: Restricting access to water meter by vehicle, vegetation, etc | BJ46: 2 | BK46: 0 | BL46: 0 | BM46: 0 | BN46: 1 | BO46: 0 | BP46: 0 | BQ46: 0 | BS46: 2 | BT46: 2 | BV46: 1 | BW46: 2025 | BX46: 1 | BY46: 0.018 | BZ46: 0 | CA46: 0 | CB46: 0 | CC46: 1 | CD46: 0 | CE46: 0 | CF46: Utility rates are adjusted annually based on next fiscal year's budget | CG46: 5 | CH46: Base + consumption | CI46: 56.75 | CJ46: 1 | CK46: 2025 | CL46: 1 | CM46: 0.118 | CN46: 1 | CO46: 0 | CP46: 0 | CQ46: 1 | CR46: 0 | CS46: 0 | CT46: Utility rates are adjusted annually based on next fiscal year's budget | CU46: 4 | CV46: Base + consumption (winter average) | CW46: 66.55 | CX46: 2 | DO46: 1 | DP46: 2400 | DQ46: 175 | DR46: 2400 | DS46: 175 | DT46: 948 | DU46: 73 | DV46: 61 | DW46: 1 | DX46: 23 | DY46: 1 | DZ46: 60000 | EA46: 21.8 | EB46: 3 | EC46: 3 | ED46: 0 | EE46: 1928 | EF46: 1999 | EG46: 500 | EH46: 1 | EI46: 0.25 | EJ46: 0.9 | EK46: 0.35 | EL46: 1 | EM46: 0 | EN46: 1 | EO46: 2 | EP46: 1 | EQ46: 1 | EU46: unknown | EV46: 2 | EW46: 2 | EX46: 3 | EZ46: 34 | FB46: 66 | FD46: 1 | FE46: 2400 | FF46: 20 | FG46: 2400 | FH46: 20 | FI46: 940 | FJ46: 3 | FK46: 61 | FL46: 1 | FM46: 23 | FN46: 1 | FO46: 60000 | FP46: 17.2 | FQ46: 4 | FR46: 2 | FS46: 2 | FT46: 0 | FU46: 0 | FV46: 0 | FW46: 0 | FX46: 1 | FY46: 1 | GA46: 1960 | GB46: 2015 | GC46: 2 | GD46: 2 | GE46: 131.5 | GF46: 2 | GG46: 0.12 | GH46: 50 | GI46: unknown | GJ46: unknown | GK46: 2 | GL46: 2 | GM46: 0 | GO46: 2 | GQ46: 2 | GT46: 2
A47: Lake Oswego | B47: 41474 | C47: 5 | D47: 2 | E47: 1 | G47: 1 | H47: 1 | I47: 1 | J47: 1 | K47: 1 | L47: 1 | M47: 1 | N47: 1 | O47: 1 | P47: 1 | Q47: 0 | R47: 0 | S47: 0 | W47: 30 | Z47: 4 | AB47: 180 | AC47: 1 | AD47: 50% reduction for households below the poverty line | AE47: 3 | AF47: 3 | AH47: Up to two billing cycles | AI47: Based on water winter time consumption. Will use previous year's read. | AJ47: 41 | AK47: 34 | AL47: 0 | AP47: 1 | AQ47: 1 | AR47: 1 | AS47: 2020 | AT47: 2014 | AU47: 2009 | AV47: 2009 | AY47: 2 | AZ47: 2 | BC47: 0 | BD47: 0 | BE47: 0 | BF47: 1 | BG47: 0 | BH47: 0 | BI47: Street Maintenance | BJ47: 1 | BK47: 0 | BL47: 0 | BM47: 0 | BN47: 0 | BO47: 0 | BP47: 1 | BQ47: 1 | BS47: 2 | BT47: 2 | BU47: 2 | BV47: 1 | BW47: 2025 | BX47: 1 | BY47: 2 | BZ47: 1 | CA47: 1 | CB47: 0 | CC47: 0 | CD47: 0 | CE47: 0 | CG47: 1 | CI47: 52.02 | CJ47: 1 | CK47: 2025 | CL47: 1 | CM47: 0.039 | CN47: 1 | CO47: 1 | CP47: 0 | CQ47: 0 | CR47: 0 | CS47: 0 | CU47: 2 | CW47: 86.34 | CX47: 1 | CY47: 7 | CZ47: 1 | DA47: 0.03 | DB47: 1 | DC47: 1 | DD47: 1 | DE47: 0 | DF47: 0 | DG47: 0 | DH47: 0 | DJ47: 1 | DL47: 2 | DN47: 23.11 | DO47: 1 | DP47: 41131 | DQ47: 250 | DR47: 41131 | DS47: 250 | DT47: 11672 | DU47: 132 | DV47: 485 | DZ47: 6573 | EA47: 230 | EC47: 17 | ED47: 2.5 | EE47: 1968 | EF47: 2017 | EH47: 38 | EI47: 11.59 | EJ47: 6.8 | EK47: 21.7 | EM47: 28.7 | EO47: 4 | EU47: 2045 | EV47: 1 | EW47: 1 | EX47: 2 | EZ47: 0.98 | FB47: 0.02 | FC47: AMI conversion should be completed by the end of 2025 | FD47: 1 | FE47: 41131 | FG47: 41131 | FI47: 12666 | FK47: 445 | FO47: 8 | FP47: 189 | FQ47: 12 | FR47: 1 | FS47: 2 | FT47: 0 | FU47: 0 | FV47: 1 | FW47: 0 | FX47: 0 | FY47: 0 | FZ47: Operated by Portland - BES | GK47: 2 | GL47: 2 | GO47: 2 | GT47: 1 | GU47: 12412 | GW47: 479 | HA47: 171 | HB47: 10 | HC47: 3030
A48: Dallas | B48: 17924 | C48: 5 | D48: 3 | E48: 1 | G48: 1 | H48: 1 | I48: 1 | J48: 1 | K48: 1 | L48: 1 | M48: 1 | N48: 0 | O48: 1 | P48: 1 | Q48: 0 | R48: 0 | S48: 0 | U48: 11 | W48: 7 | AC48: 2 | AE48: 3 | AF48: 2 | AG48: 90 | AJ48: 16 | AK48: 5 | AL48: 2 | AP48: 1 | AQ48: 1 | AR48: 1 | AS48: 2016 | AT48: 2016 | AU48: 2016 | AY48: 2 | AZ48: 2 | BC48: 0 | BD48: 1 | BE48: 0 | BF48: 1 | BG48: 1 | BH48: 1 | BI48: Public Safety Fee | BJ48: 1 | BK48: 1 | BL48: 0 | BM48: 0 | BN48: 0 | BO48: 1 | BP48: 0 | BQ48: 0 | BS48: 2 | BT48: 2 | BU48: 2 | BV48: 1 | BW48: 2025 | BX48: 1 | BY48: 0.15 | BZ48: 1 | CA48: 1 | CB48: 0 | CC48: 0 | CD48: 0 | CE48: 1 | CG48: 4 | CI48: 61.28 | CJ48: 1 | CK48: 2019 | CL48: 1 | CM48: 0.0275 | CN48: 1 | CO48: 1 | CP48: 1 | CQ48: 0 | CR48: 0 | CS48: 1 | CU48: 1 | CW48: 45.21 | CX48: 1 | CY48: 7 | CZ48: 1 | DA48: 0.15 | DB48: 1 | DC48: 1 | DD48: 1 | DE48: 1 | DF48: 0 | DG48: 0 | DH48: 0 | DJ48: 1 | DL48: 2 | DN48: 16 | DO48: 1
A49: Rockaway Beach | B49: 1533 | C49: 3 | D49: 1 | E49: 2 | G49: 1 | H49: 1 | I49: 1 | J49: 1 | K49: 1 | L49: 1 | M49: 1 | N49: 1 | O49: 1 | P49: 1 | Q49: 0 | R49: 1 | S49: 0 | U49: 1.15 | W49: 60 | Z49: 90 | AB49: 90 | AC49: 2 | AE49: 3 | AF49: 2 | AG49: 30 | AM49: 1 | AN49: 1 | AO49: 1 | AP49: 1 | AQ49: 1 | AR49: 2 | AS49: 2017 | AT49: 2025 | AV49: 2017 | AW49: 2025 | AY49: 1 | AZ49: 4 | BB49: unless shut off w/fee, bills continue | BC49: 0 | BD49: 1 | BE49: 0 | BF49: 0 | BG49: 1 | BH49: 0 | BJ49: 2 | BK49: 0 | BL49: 0 | BM49: 1 | BN49: 0 | BO49: 0 | BP49: 0 | BQ49: 0 | BR49: Emergency Services (covers fire, police, or other) | BS49: 2 | BT49: 2 | BV49: 2 | CJ49: 1 | CK49: 2025 | CL49: 1 | CN49: 1 | CO49: 1 | CP49: 1 | CQ49: 0 | CR49: 0 | CS49: 1 | CU49: 1 | CX49: 2 | DO49: 2 | FD49: 1 | FE49: 1447 | FI49: 2557 | FK49: 86 | FM49: 20 | GO49: 2 | GQ49: 2 | GT49: 2
A50: Grants Pass | B50: 40380 | C50: 5 | D50: 7 | E50: 1 | G50: 1 | H50: 1 | I50: 1 | J50: 0 | K50: 1 | L50: 1 | M50: 1 | N50: 1 | O50: 1 | P50: 1 | Q50: 0 | R50: 1 | S50: 0 | AA50: 150 | AC50: 2 | AE50: 3 | AF50: 3 | AH50: Maximum of three bills, leak must be repaired within 10 days of discovery. | AI50: Reduction of wastewater charges for residential/multi-family if leak occurred during the rate calculation period. 100% for commercial if leak occurred outside and 50% reduction if leak occurred inside. | AJ50: 0 | AK50: 13.22 | AL50: 0 | AP50: 1 | AQ50: 1 | AR50: 1 | AS50: 2025 | AT50: 2019 | AU50: 2019 | AV50: 2019 | AW50: 2011 | AX50: 2019 - Implementation | AY50: 2 | AZ50: 2 | BC50: 1 | BD50: 0 | BE50: 0 | BF50: 0 | BG50: 1 | BH50: 1 | BJ50: 1 | BK50: 1 | BL50: 0 | BM50: 0 | BN50: 0 | BO50: 1 | BP50: 1 | BQ50: 1 | BS50: 1 | BT50: 1 | BU50: 1 | BV50: 1 | BW50: 2025 | BX50: 1 | BY50: 3.02 | BZ50: 0 | CA50: 1 | CB50: 0 | CC50: 0 | CD50: 0 | CE50: 0 | CG50: 3 | CI50: 46.81 | CJ50: 1 | CK50: 2025 | CL50: 1 | CM50: 3.02 | CN50: 0 | CO50: 1 | CP50: 0 | CQ50: 0 | CR50: 0 | CS50: 0 | CU50: 4 | CV50: Commercial based on water use | CX50: 1 | CY50: 7 | CZ50: 1 | DA50: 3.02 | DB50: 1 | DC50: 1 | DD50: 1 | DE50: 0 | DF50: 0 | DG50: 1 | DH50: 0 | DJ50: 1 | DL50: 1 | DM50: Parcel must include on site stormwater mitigation facility maintained by property owner C=Fx45% C= credit amount F= total monthly amount w/out credit | DN50: 9.08 | DO50: 1 | DP50: 39900 | DT50: 10453 | DV50: 1500 | DX50: 191 | DZ50: 8228 | EA50: 179.5 | EB50: 13 | EC50: 6 | ED50: 0 | EE50: 1930 | EF50: 1984 | EG50: 82.5 | EH50: 20 | EI50: 5.6792 | EJ50: 0.92 | EK50: 12.7 | EM50: 21.63 | EU50: 2045 | EV50: 1 | EW50: 1 | EX50: 1 | FB50: 100 | FD50: 1 | FE50: 39900 | FI50: 12930 | FK50: 1265 | FO50: 4488 | FP50: 184.5 | FQ50: 5 | FR50: 2 | FS50: 2 | FT50: 0 | FU50: 0 | FV50: 0 | FW50: 0 | FX50: 1 | FY50: 1 | GA50: 1935 | GC50: 4 | GD50: 9.4 | GE50: 2492.2 | GF50: 22.3 | GG50: 6.8 | GI50: Unknown | GJ50: Unknown | GK50: 1 | GM50: N/A | GO50: 2 | GQ50: 1 | GR50: 2 | GT50: 1 | GU50: 12438 | GW50: 1302 | HA50: 201.6 | HC50: 3700
A51: Jordan Valley | B51: 131 | C51: 1 | D51: 12 | E51: 1 | G51: 1 | H51: 1 | I51: 0 | J51: 0 | K51: 1 | L51: 0 | M51: 2 | N51: 0 | O51: 1 | P51: 0 | Q51: 1 | R51: 0 | S51: 0 | U51: 0.1 | V51: 0.02 | X51: 8.57 | Y51: 1.71 | Z51: 60 | AC51: 2 | AE51: 3 | AF51: 3 | AG51: 0 | AJ51: 53 | AK51: 47 | AO51: 1 | AP51: 1 | AQ51: 1 | AS51: 2023 | AT51: 2025 | AY51: 2 | AZ51: 4 | BB51: charged normal rate | BC51: 0 | BD51: 0 | BE51: 1 | BF51: 0 | BG51: 0 | BH51: 0 | BJ51: 2 | BS51: 2 | BT51: 2 | BV51: 1 | BW51: 2024 | BX51: 1 | BY51: 65 | BZ51: 1 | CA51: 1 | CB51: 1 | CC51: 0 | CD51: 0 | CE51: 1 | CG51: 1 | CI51: 85.73 | CJ51: 1 | CK51: 2024 | CL51: 1 | CM51: 65 | CN51: 1 | CO51: 1 | CP51: 1 | CQ51: 0 | CR51: 0 | CS51: 1 | CU51: 1 | CW51: 40.29 | CX51: 2 | DO51: 1 | DP51: 80 | DR51: 120 | DT51: 80 | DV51: 20 | DX51: 5 | EA51: 3.98 | EB51: 1 | ED51: 0 | EE51: 1976 | EF51: 2007 | EG51: 150000 | EI51: 60 | EJ51: 0 | EK51: 120000 | EM51: 150000 | EV51: 2 | EW51: 2 | EX51: 3 | FB51: 100 | FD51: 1 | FE51: 80 | FG51: 120 | FI51: 80 | FK51: 20 | FM51: 5 | FO51: 20 | FP51: 3.24 | FR51: 1 | FS51: 4 | FT51: 0 | FU51: 0 | FV51: 0 | FW51: 0 | FX51: 1 | FY51: 0 | GA51: 1974 | GC51: 0.047 | GD51: 0.047 | GF51: 0.046 | GG51: 0.028 | GH51: 50 | GI51: n/a | GJ51: n/a | GK51: 2 | GL51: 2 | GM51: n/a | GO51: 2 | GQ51: 2 | GT51: 1 | GU51: 0 | GW51: 0 | HA51: 0.44 | HB51: 0 | HC51: 1900
A52: Bandon | B52: 3592 | C52: 4 | D52: 6 | E52: 1 | G52: 1 | H52: 1 | I52: 1 | J52: 0 | K52: 1 | L52: 1 | M52: 1 | N52: 1 | O52: 1 | P52: 1 | Q52: 1 | R52: 0 | S52: 0 | U52: 10 | V52: 0.75 | W52: 20 | X52: 10 | Y52: 0.0075 | Z52: 30 | AA52: 50 | AB52: 30 | AC52: 2 | AE52: 3 | AF52: 1 | AG52: 90 | AI52: Calculate a 12-month history of water bills, divide by 12 to get the approximate usage per month. If over the first 2,000 gallons (base rate), adjusted by a 1,000 fee rate. Leak adjustment is leak usage minus average usage. | AM52: 1 | AN52: 1 | AO52: 1 | AT52: Do not have this information | AU52: Do not have this information | AW52: Do not have this information | AX52: Do not have this information | AY52: 2 | AZ52: 2 | BC52: 1 | BD52: 0 | BE52: 0 | BF52: 1 | BG52: 1 | BH52: 0 | BI52: City Tax 10% | BJ52: 2 | BS52: 2 | BT52: 2 | BU52: 2 | BV52: 1 | BW52: 2023 | BX52: 1 | BZ52: 0 | CA52: 1 | CB52: 1 | CC52: 0 | CD52: 0 | CE52: 1 | CG52: 5 | CH52: Consumption charge per 1000 gallons | CJ52: 1 | CK52: 2023 | CL52: 1 | CN52: 0 | CO52: 1 | CP52: 1 | CQ52: 0 | CR52: 0 | CS52: 1 | CU52: 4 | CV52: Consumption summer 2.70 winter 4.01 per 1,000 | CX52: 2 | DO52: 1 | DP52: 3304 | DT52: 1779 | DU52: 131 | DV52: 370 | DW52: 10 | DX52: 56 | DZ52: 75596726 | EA52: 34 | EB52: 0 | EC52: 2 | ED52: 2 | EE52: 1955 | EF52: 2023 | EG52: 1.06 | EH52: 2.02 | EI52: 0.534 | EJ52: 0.85 | EK52: 984539 | EM52: 3 | EU52: 2040 | EV52: 1 | EW52: 1 | EX52: 1 | EZ52: 0.945 | FB52: 0.055 | FD52: 1 | FE52: 1922 | FF52: 18 | FI52: 1619 | FJ52: 2 | FK52: 303 | FL52: 7 | FM52: 18 | FO52: 3294 | FQ52: 4 | FR52: 2 | FS52: 3 | GK52: 2 | GL52: 2 | GM52: N/A | GO52: 1 | GP52: 38-acre field, used only during dry weather (April-October). | GQ52: 1 | GR52: 6 | GT52: 1 | GU52: 1617 | GV52: 2 | GW52: 270 | GX52: 2 | GY52: 18
A53: Carlton | B53: 2456 | C53: 3 | D53: 3 | E53: 1 | G53: 1 | H53: 1 | I53: 1 | J53: 0 | K53: 1 | L53: 0 | M53: 1 | N53: 1 | O53: 1 | P53: 1 | Q53: 0 | R53: 1 | S53: 0 | Z53: 5 | AC53: 2 | AE53: 3 | AF53: 2 | AG53: 30
A54: Hood River | B54: 8633 | C54: 4 | D54: 8 | E54: 1 | G54: 1 | H54: 1 | I54: 1 | J54: 1 | K54: 1 | L54: 1 | M54: 1 | N54: 1 | O54: 1 | P54: 1 | Q54: 0 | R54: 1 | S54: 0 | U54: 10 | W54: 30 | Z54: 45 | AA54: 10 | AC54: 1 | AD54: Low-Income Assistance Program. If qualified, utility customer bill will be reduced. | AE54: 3 | AF54: 3 | AG54: 30 | AI54: Wastewater adjustments are made only for Commercial Accounts under Sewer Commodity. No wastewater adjustments are made for residential customers. | AJ54: 25 | AK54: 3 | AL54: 0 | AP54: 1 | AQ54: 1 | AR54: 1 | AS54: 2021 | AT54: 2021 | AU54: 2021 | AV54: 2021 | AW54: 2021 | AX54: 2021 | AY54: 2 | AZ54: 4 | BB54: Normal rates charged | BC54: 0 | BD54: 1 | BE54: 0 | BF54: 1 | BG54: 1 | BH54: 0 | BI54: Shut Off and Door Hanger | BJ54: 1 | BS54: 2 | BT54: 2 | BU54: 2 | BV54: 1 | BW54: 2022 | BX54: 1 | BY54: 2 | BZ54: 0 | CA54: 1 | CB54: 0 | CC54: 0 | CD54: 0 | CE54: 0 | CG54: 4 | CI54: 42.69 | CJ54: 1 | CK54: 2023 | CL54: 1 | CM54: 2 | CN54: 1 | CO54: 1 | CP54: 0 | CQ54: 0 | CR54: 0 | CS54: 0 | CU54: 1 | CW54: 67.68 | CX54: 1 | CY54: 7 | CZ54: 1 | DA54: 3 | DB54: 2 | DC54: 1 | DD54: 1 | DE54: 0 | DF54: 0 | DG54: 0 | DH54: 0 | DJ54: 1 | DL54: 2 | DN54: 11.03 | DO54: 1 | DP54: 8574 | DQ54: 357 | DR54: 14290 | DS54: 357 | DT54: 3103 | DU54: 143 | DV54: 441 | DW54: 1 | DX54: 142 | DY54: 1 | DZ54: 60000 | EA54: 83 | EB54: 0 | EC54: 5 | ED54: 16 | EE54: 1985 | EF54: 2010 | EG54: 25 | EI54: 1.3 | EJ54: 1.2 | EK54: 2 | EM54: 6.25 | EU54: 2040 | EV54: 2 | EW54: 2 | EX54: 1 | EZ54: 95 | FB54: 5 | FC54: NA | FD54: 1 | FE54: 8574 | FF54: 450 | FG54: 17148 | FH54: 450 | FI54: 3105 | FJ54: 4 | FK54: 441 | FL54: 1 | FP54: 60 | FQ54: 6 | FR54: 2 | FS54: 2 | FT54: 0 | FU54: 0 | FV54: 0 | FW54: 0 | FX54: 0 | FY54: 1 | GA54: 1974 | GB54: 2001 | GC54: 1.48 | GD54: 6.21 | GE54: 431 | GF54: 3.67 | GG54: 1.38 | GH54: 95 | GI54: 2036 | GJ54: 2036 | GK54: 1 | GL54: 2 | GM54: NA | GO54: 1 | GP54: Various regulated/permitted fields. Biosolids are land applied in bulk to agricultural land. | GQ54: 2 | GS54: NA | GT54: 1 | GU54: 3103 | GV54: 3 | GW54: 441 | GX54: 1 | GY54: 0 | GZ54: 1 | HA54: 50 | HB54: 8 | HC54: 2490 | HD54: NA | HE54: NA
A55: St. Helens | B55: 14552 | C55: 5 | D55: 1 | BV55: 1 | CJ55: 1 | CX55: 1 | DB55: 2 | DL55: 1 | DM55: - The program offers a 27% maximum reduction of the stormwater user charge portion of the water/sewer/stormwater bill if a property meets the following requirements: (1) For a 27% discount, at least 75% of the property’s hard surfaces must drain and remain on the property, without seepage to the street, creek, ditch, or river or flow to any off-site property or facility; (2) For a 14% discount, at least 50% of the property’s hard surfaces drain and remain on the property, without seepage to the street, creek, ditch, or river or flow to any off-site property or facility; and (3) If less than 50% of a property’s hard surfaces drain onto the property, no discount applies. The discount is granted to the active stormwater rate payer for the address listed on the discount application and it is not retroactive | DO55: 1 | EA55: 82 | EB55: 1 | EC55: 3 | ED55: 3 | EE55: 2006 | EF55: 2006 | EH55: 6 | EJ55: 574 | EK55: 2120 | EL55: 2 | EM55: 3.65 | EU55: Current Water Master Plan indicates an existing surplus of 2.7 MGD at the Water Filtration Facility, and a future 20-year projected surplus of 0.9 MGD | EV55: 1 | FD55: 1 | FP55: 62 | FQ55: 9 | FR55: 2 | FS55: 2 | FT55: 0 | FU55: 0 | FV55: 0 | FW55: 0 | FX55: 1 | FY55: 1 | GA55: 1972 | GB55: 1991 | GC55: 2.3 | GD55: 5 | GK55: 1 | GL55: 2 | GO55: 2 | GQ55: 2 | GT55: 1 | HA55: 48 | HB55: 60
A56: Dallas | B56: 17924 | C56: 5 | D56: 3 | E56: 2 | G56: 1 | H56: 1 | I56: 1 | J56: 1 | K56: 1 | L56: 1 | M56: 1 | N56: 1 | O56: 1 | P56: 1 | Q56: 0 | R56: 0 | S56: 0 | U56: 11 | W56: 18 | Z56: 45 | AA56: 0 | AB56: 0 | AC56: 2 | AE56: 3 | AF56: 2 | AG56: 90 | AJ56: 12 | AK56: 1.8 | AO56: 1 | AP56: 1 | AQ56: 1 | AR56: 1 | AS56: 2016 | AT56: 2016 | AU56: 2016 | AY56: 2 | AZ56: 2 | BC56: 0 | BD56: 1 | BE56: 0 | BF56: 0 | BG56: 1 | BH56: 1 | BJ56: 1 | BK56: 1 | BL56: 0 | BM56: 0 | BN56: 0 | BO56: 1 | BP56: 0 | BQ56: 0 | BS56: 2 | BT56: 2 | BU56: 2 | BV56: 1 | BW56: 2025 | BX56: 1 | BY56: 15 | BZ56: 1 | CA56: 1 | CB56: 1 | CC56: 0 | CD56: 0 | CE56: 1 | CG56: 4 | CI56: 50 | CJ56: 1 | CK56: 2019 | CL56: 1 | CM56: 3 | CN56: 1 | CO56: 1 | CP56: 0 | CQ56: 0 | CR56: 0 | CS56: 0 | CU56: 1 | CW56: 45.21 | CX56: 1 | CY56: 7 | CZ56: 1 | DA56: 14 | DB56: 2 | DC56: 1 | DD56: 1 | DE56: 1 | DF56: 0 | DG56: 1 | DH56: 1 | DJ56: 1 | DL56: 2 | DN56: 16 | DO56: 1 | DP56: 17924 | DQ56: 400 | DR56: 17924 | DS56: 400 | DT56: 5649 | DU56: 367 | DV56: 273 | DW56: 1 | DX56: 87 | DY56: 1 | DZ56: 146363 | EA56: 65 | EB56: 4 | EC56: 3 | ED56: 7 | EE56: 1947 | EF56: 2008 | EG56: 400000000 | EH56: 6 | EI56: 2.56 | EJ56: 1 | EK56: 5.06 | EM56: 8.135 | ER56: OPEN RESERVOIR | ES56: 400 | EU56: NA | EV56: 1 | EW56: 1 | EX56: 1 | EZ56: 99 | FB56: 1 | FD56: 1 | FE56: 17924 | FI56: 5630 | FK56: 223 | FM56: 65 | FP56: 88 | FQ56: 6 | FR56: 2 | FS56: 2 | FT56: 0 | FU56: 1 | FV56: 1 | FW56: 0 | FX56: 0 | FY56: 1 | FZ56: UV DISINFECTION | GA56: 1999 | GB56: 1999 | GC56: 2.6 | GD56: 18.5 | GE56: 1123.56 | GF56: 14.72 | GG56: 7.08 | GH56: 50 | GI56: 2050+ | GJ56: 2050+ | GK56: 1 | GL56: 2 | GM56: 0 | GO56: 2 | GQ56: 1 | GR56: 1 | GT56: 1 | GU56: 5630 | GW56: 223 | GY56: 65 | HA56: 77.7 | HB56: NA
A57: Oregon City | B57: 38029 | C57: 5 | D57: 2 | E57: 1 | G57: 1 | H57: 1 | I57: 1 | J57: 1 | K57: 1 | L57: 1 | M57: 1 | N57: 1 | O57: 1 | P57: 1 | Q57: 0 | R57: 1 | S57: 0 | W57: 30 | AA57: 250 | AC57: 1 | AD57: Reduced rate program based on income qualifications inline with the State of Oregon guidelines. The program reduces customer's charges to half of the base rate. | AE57: 3 | AF57: 3 | AI57: Wastewater adjustments are only done on commercial accounts. Residential accounts are flat wastewater fees, commercial sewer is base on water usage. We adjust based on prior usage during the same time period. | AM57: 1 | AN57: 1 | AO57: 1 | AP57: 1 | AQ57: 1 | AR57: 1 | AS57: 2009 | AT57: August 2014 | AU57: March 2021 | AV57: 2020 | AW57: March 2005 | AX57: July 2021 | AY57: 2 | AZ57: 1 | BA57: We suspend base rate for water and wastewater. | BC57: 1 | BD57: 0 | BE57: 0 | BF57: 0 | BG57: 1 | BH57: 1 | BJ57: 1 | BK57: 0 | BL57: 0 | BM57: 0 | BN57: 0 | BO57: 1 | BP57: 1 | BQ57: 0 | BS57: 1 | BT57: 1 | BU57: 1 | BV57: 1 | BW57: 2025 | BX57: 1 | BZ57: 1 | CA57: 1 | CB57: 1 | CC57: 0 | CD57: 0 | CE57: 1 | CG57: 4 | CJ57: 1 | CK57: 2025 | CL57: 1 | CM57: 0.0375 | CN57: 1 | CO57: 1 | CP57: 1 | CQ57: 0 | CR57: 0 | CS57: 1 | CU57: 4 | CV57: Flat rate residential, tiered rate for commercial | CW57: 71.08 | CX57: 1 | CY57: 7 | CZ57: 1 | DA57: 0.08 | DB57: 1 | DC57: 1 | DD57: 1 | DE57: 1 | DF57: 0 | DG57: 0 | DH57: 1 | DJ57: 1 | DL57: 1 | DM57: If the customer provides the City with proof of onsite stormwater management the City will review and adjust if necessary. | DN57: 14.77 | DO57: 1 | DP57: 38029 | DQ57: 120 | DT57: 10134 | DU57: 91 | DV57: 468 | DW57: 5 | DX57: 677 | DY57: 1 | DZ57: 4488 | EA57: 175.275 | EC57: 10 | EL57: 1 | EM57: 18.25 | EN57: 1 | EO57: 1 | EP57: 1 | EQ57: 1 | ES57: 0 | ET57: 0 | EU57: https://sfwb.org | EV57: 2 | EW57: 1 | EX57: 3 | FA57: 0.05 | FB57: 0.95 | FC57: N/A | FD57: 1 | FE57: 38029 | FF57: 0 | FI57: 10149 | FJ57: 2 | FK57: 467 | FL57: 2 | FM57: 571 | FN57: 1 | FP57: 138 | FR57: 5 | FS57: 1 | FT57: 0 | FU57: 0 | FV57: 1 | FW57: 0 | FX57: 0 | FY57: 0 | FZ57: N/A, a 3rd party does our treatment. Clackamas Water Environment Services https://www.clackamas.us/wes/ssewer.html | GA57: 3 | GI57: https://www.clackamas.us/wes/ssewer.html | GJ57: https://www.clackamas.us/wes/ssewer.html | GK57: 2 | GL57: 2 | GM57: N/A | GO57: 2 | GQ57: 2 | GS57: N/A, a 3rd party does treatment, Clackamas Water Environment Services | GT57: 1 | GU57: 10477 | GV57: 1 | GW57: 455 | GX57: 1 | GY57: 585 | GZ57: 1 | HA57: 121 | HB57: 2.5 miles of ditches | HC57: 2500 | HD57: N/A
A58: Lonerock | B58: 25 | C58: 1 | D58: 8 | E58: 4 | F58: April, June, Aug, Oct | G58: 1 | H58: 1 | I58: 0 | J58: 0 | K58: 0 | L58: 1 | M58: 2 | N58: 0 | O58: 0 | P58: 0 | Q58: 0 | R58: 0 | S58: 1 | T58: Have never had to impliment | AC58: 2 | AE58: 2 | AH58: Have never had this yet | AM58: 1 | AN58: 1 | AO58: 1 | AP58: 2 | AT58: N/A | AU58: N/A | AW58: N/A | AX58: N/A | AY58: 2 | AZ58: 2 | BC58: 0 | BD58: 0 | BE58: 1 | BF58: 0 | BG58: 0 | BH58: 0 | BJ58: 2 | BS58: 2 | BT58: 2 | BU58: 2 | BV58: 2 | CJ58: 2 | CX58: 2 | DO58: 2 | FD58: 2 | GT58: 2
A59: Phoenix | B59: 4413 | C59: 4 | D59: 7
A60: Rogue River | B60: 2484 | C60: 3 | D60: 7 | E60: 1 | G60: 1 | H60: 1 | I60: 1 | J60: 1 | K60: 1 | L60: 1 | M60: 1 | N60: 0 | O60: 1 | P60: 0 | Q60: 0 | R60: 0 | S60: 0 | AC60: 2 | AE60: 4 | AF60: 2 | AH60: 10 days after notice or awareness of leak | AP60: 2 | AQ60: 2 | AR60: 2 | AV60: 2016 | AW60: 2016 | AX60: 2016 | AY60: 2 | AZ60: 4 | BC60: 0 | BD60: 0 | BE60: 0 | BF60: 1 | BG60: 0 | BH60: 0 | BI60: Public Safety Fee | BJ60: 2 | BK60: 0 | BL60: 0 | BM60: 0 | BN60: 0 | BO60: 1 | BP60: 0 | BQ60: 0 | BS60: 1 | BT60: 1 | BU60: 2 | BV60: 1 | BW60: 2025 | BX60: 1 | BY60: 0.0009 | BZ60: 0 | CA60: 1 | CB60: 0 | CC60: 0 | CD60: 0 | CE60: 0 | CG60: 4 | CI60: 29.23 | CJ60: 1 | CK60: 2025 | CL60: 1 | CM60: 0.0009 | CN60: 0 | CO60: 1 | CP60: 0 | CQ60: 0 | CR60: 0 | CS60: 0 | CU60: 3 | CW60: 40.05 | CX60: 2 | DO60: 1 | DP60: 2419 | DT60: 658 | DV60: 104 | DX60: 30 | DZ60: 11824975 | EA60: 15 | ED60: 0 | EV60: 1 | FD60: 1
A61: Milwaukie | B61: 21408 | C61: 5 | D61: 2 | E61: 1 | G61: 1 | H61: 1 | I61: 1 | J61: 1 | K61: 0 | L61: 1 | M61: 1 | N61: 1 | O61: 1 | P61: 1 | Q61: 0 | R61: 1 | S61: 0 | AA61: 100 | AC61: 1 | AD61: We have a Utility Assistance Program for residents whose income doesn't exceed the current gross annual household income levels established by the Housing Choice Voucher Program. This program provides reductions and waivers as follows: - A waiver of the established base charge for water service - One half of the established billing and administration charge, treatment charge, and volume charge for wastewater (sewer) - One half of the established base charge and volume charge for stormwater charges - A waiver of the street maintenance and SAFE fee | AE61: 3 | AF61: 3 | AG61: 182.5 | AH61: We reimburse for one half of the charges related to the leak | AI61: We reimburse for one half of the charges related to the leak | AM61: 1 | AO61: 1 | AS61: 2025 | AT61: 2025 | AZ61: 2 | BC61: 0 | BD61: 0 | BE61: 0 | BF61: 1 | BG61: 1 | BH61: 1 | BI61: Public Safety Fee | BJ61: 1 | BK61: 0 | BL61: 1 | BM61: 1 | BN61: 0 | BO61: 1 | BP61: 1 | BQ61: 0 | BR61: Public Safety Fee - this supports police, but also includes additional support for the library, which deals with behavioral health issues, and municipal court. There isn't a separate fee for the library other than the public safety fee. | BS61: 2 | BT61: 2 | BU61: 2 | BV61: 2 | CJ61: 1 | CK61: 2025 | CX61: 1 | DO61: 2 | FD61: 1
A62: Ione | B62: 342 | C62: 1 | D62: 11 | E62: 1 | G62: 1 | H62: 1 | I62: 1 | J62: 1 | K62: 1 | L62: 1 | M62: 2 | N62: 1 | O62: 1 | P62: 1 | Q62: 0 | R62: 0 | S62: 0 | U62: 25 | W62: 5 | Z62: 60 | AB62: 75 | AC62: 2 | AE62: 2 | AG62: 0 | AJ62: 100 | AN62: 1 | AO62: 1 | AP62: 1 | AS62: 2020 | AT62: na | AU62: na | AV62: 2020 | AW62: na | AX62: na | AZ62: 3 | BC62: 0 | BD62: 1 | BE62: 0 | BF62: 0 | BG62: 1 | BH62: 0 | BJ62: 2 | BK62: 0 | BL62: 0 | BM62: 1 | BN62: 0 | BO62: 0 | BP62: 0 | BQ62: 0 | BR62: none | BS62: 2 | BV62: 1 | BW62: 2020 | BX62: 1 | BY62: 0.02 | BZ62: 0 | CA62: 1 | CB62: 1 | CC62: 0 | CD62: 0 | CE62: 0 | CG62: 5 | CH62: Flat Rate with Number of gallons used | CJ62: 2 | CX62: 2 | DO62: 1
A63: Reedsport | B63: 4368 | C63: 4 | D63: 6 | E63: 1 | G63: 1 | H63: 1 | I63: 1 | J63: 1 | K63: 1 | L63: 1 | M63: 1 | N63: 1 | O63: 1 | P63: 1 | Q63: 1 | R63: 0 | S63: 0 | U63: 0.015 | V63: 1.5 | Y63: 0.015 | Z63: 48 | AB63: 60 | AC63: 2 | AE63: 3 | AF63: 3 | AG63: 3 | AI63: When a leak or high cons is reported, we give the customer a leak adjustment form. In order to complete this adjustment request, we need the leak adjustment form, pictures of the break or repair, if available, and receipts of repairs. Once those are collected, we take a 3-month average of before the leak took place and adjust the high cons to that amount. | AK63: 3.3 | AM63: 1 | AO63: 1 | AP63: 1 | AQ63: 1 | AR63: 1 | AS63: 2010 | AT63: 2010 | AU63: 2010 | AV63: 2007 | AW63: 2007 | AX63: 2007 | AY63: 2 | AZ63: 1 | BA63: We can put an account into a readiness to serve until they are ready to have their water back on. | BC63: 0 | BD63: 0 | BE63: 0 | BF63: 1 | BG63: 1 | BH63: 0 | BI63: Water meter purchase | BJ63: 1 | BK63: 0 | BL63: 0 | BM63: 0 | BN63: 0 | BO63: 0 | BP63: 0 | BQ63: 1 | BS63: 2 | BT63: 2 | BU63: 2 | BV63: 1 | BW63: 2006 | BX63: 1 | BZ63: 1 | CA63: 1 | CB63: 1 | CC63: 0 | CD63: 0 | CE63: 1 | CG63: 4 | CJ63: 1 | CK63: 2006 | CL63: 1 | CN63: 1 | CO63: 1 | CP63: 1 | CQ63: 0 | CR63: 0 | CS63: 1 | CU63: 3 | CX63: 1 | CY63: 1 | CZ63: 1 | DB63: 2 | DC63: 1 | DD63: 1 | DE63: 1 | DF63: 0 | DG63: 0 | DH63: 0 | DJ63: 1 | DL63: 2 | DN63: 3 | DO63: 1 | DP63: 4299 | DQ63: 351 | DT63: 1336 | DU63: 364 | DV63: 250 | DW63: 12 | DZ63: 1 | EA63: 29 | EB63: 5 | ED63: 5 | EE63: 1986 | EF63: 2017 | EH63: 5.9 | EI63: 0.735 | EJ63: 1 | EK63: 1.4 | EL63: 1 | EM63: 3.31 | EN63: 1 | EO63: 1 | EP63: 1 | EQ63: 1 | EU63: Unknown | EV63: 2 | EW63: 2 | EX63: 1 | EZ63: 95 | FA63: 0 | FB63: 5 | FC63: No | FD63: 1 | FE63: 4299 | FF63: 351 | FI63: 1336 | FJ63: 1 | FK63: 250 | FL63: 1 | FO63: 220 | FP63: 25 | FQ63: 10 | FR63: 2 | FS63: 2 | FT63: 0 | FU63: 0 | FV63: 0 | FW63: 0 | FX63: 0 | FY63: 1 | GA63: 1958 | GB63: 2010 | GC63: 0.861 | GD63: 5 | GE63: 325 | GF63: 4.3 | GG63: 2.5 | GH63: 100 | GI63: Unknown | GJ63: unknown | GK63: 2 | GL63: 1 | GM63: .5 | GN63: We use reclaimed water at our sewer plant to water the lawn | GO63: 1 | GP63: Private field with hay/graze | GQ63: 2 | GS63: no | GT63: 1 | GU63: 1336 | GV63: 1 | GW63: 250 | GX63: 1 | HA63: 4.48 | HB63: unknown | HC63: 3000 | HD63: no | HE63: no
A64: Rogue River | B64: 2484 | C64: 3 | D64: 7 | E64: 1 | G64: 1 | H64: 1 | I64: 1 | J64: 1 | K64: 1 | L64: 1 | M64: 1 | N64: 0 | O64: 1 | P64: 0 | Q64: 0 | R64: 1 | S64: 0 | AC64: 2 | AE64: 3 | AF64: 2 | AG64: 60 | AH64: Must correct within 10 days of discovery | AJ64: 9 | AK64: 9 | AO64: 1 | AP64: 2 | AQ64: 2 | AR64: 2 | AS64: 2014 | AT64: 2002 | AU64: n/a | AV64: 2006 | AW64: 2006 | AX64: 2006 | AY64: 2 | AZ64: 4 | BB64: Continue to bill, charge minimum if no use | BC64: 0 | BD64: 0 | BE64: 0 | BF64: 1 | BG64: 0 | BH64: 1 | BI64: reconnect fee | BJ64: 2 | BK64: 0 | BL64: 0 | BM64: 0 | BN64: 0 | BO64: 1 | BP64: 0 | BQ64: 0 | BS64: 1 | BT64: 1 | BV64: 1 | BX64: 1 | BY64: 0.09 | BZ64: 0 | CA64: 1 | CB64: 0 | CC64: 0 | CD64: 0 | CE64: 0 | CG64: 5 | CH64: Flat + overage charge flat rate for usage over 500 cubic feet per month | CI64: 29.24 | CJ64: 1 | CL64: 1 | CM64: 0.09 | CN64: 0 | CO64: 1 | CP64: 0 | CQ64: 0 | CR64: 0 | CS64: 0 | CU64: 2 | CW64: 44.76 | CX64: 1 | CY64: 2 | DB64: 1 | DC64: 1 | DD64: 0 | DE64: 0 | DF64: 0 | DG64: 0 | DH64: 0 | DJ64: 2 | DK64: SDC fee based on square footage of impervious space | DL64: 2 | DO64: 1 | DP64: 2419 | DQ64: 53 | DT64: 658 | DU64: 21 | DV64: 104 | DX64: 30 | DZ64: 161178 | EA64: 15 | EB64: 15 | EC64: 1 | ED64: 0 | EE64: 1900 | EF64: 1994 | EI64: 0.45 | EJ64: 0.87 | EK64: 0.83 | EM64: 1.7 | EU64: 2035 | EV64: 1 | EW64: 1 | EX64: 1 | EZ64: 100 | FD64: 1 | FE64: 2419 | FI64: 658 | FK64: 104 | FM64: 25 | FO64: 6840 | FP64: 10 | FQ64: 7 | FR64: 2 | FS64: 2 | FT64: 1 | FU64: 1 | FV64: 0 | FW64: 1 | FX64: 1 | FY64: 1 | GA64: 1972 | GB64: 1994 | GC64: 0.43 | GD64: 0.85 | GE64: 0.34 | GF64: 0.84 | GG64: 0.84 | GH64: 79 | GI64: 2035 | GJ64: 2035 | GK64: 2 | GL64: 2 | GO64: 1 | GP64: Private farm. | GQ64: 2 | GT64: 1
A65: Stayton | B65: 8176 | C65: 4 | D65: 3 | E65: 1 | G65: 1 | H65: 1 | I65: 1 | J65: 1 | K65: 1 | L65: 1 | M65: 1 | N65: 1 | O65: 1 | P65: 1 | Q65: 0 | R65: 0 | S65: 0 | U65: 35 | AA65: 50 | AC65: 1 | AD65: $1 discount for paperless and $1 for autopay | AE65: 3 | AF65: 2 | AG65: 90 | AH65: up to 3 months of over usage | AJ65: 14.3 | AK65: 18.1 | AL65: 8.5 | AP65: 2 | AQ65: 2 | AR65: 2 | AS65: 2023 | AT65: 2023 | AU65: 2023 | AV65: 2023 | AW65: 2023 | AX65: 2023 | AY65: 1 | AZ65: 2 | BC65: 0 | BD65: 0 | BE65: 0 | BF65: 1 | BG65: 1 | BH65: 1 | BI65: transportation fee | BJ65: 1 | BK65: 0 | BL65: 0 | BM65: 1 | BN65: 0 | BO65: 0 | BP65: 0 | BQ65: 0 | BR65: transportation fee | BS65: 2 | BT65: 2 | BU65: 2 | BV65: 1 | BW65: 2025 | BX65: 1 | BY65: 0.03 | BZ65: 0 | CA65: 0 | CB65: 0 | CC65: 1 | CD65: 0 | CE65: 0 | CF65: per rate study (all of the above) | CG65: 1 | CJ65: 1 | CK65: 2025 | CL65: 1 | CN65: 0 | CO65: 0 | CP65: 0 | CQ65: 1 | CR65: 0 | CS65: 0 | CT65: per rate study (all of the above) | CU65: 4 | CV65: winter avg for commercial and industrial only (Dec-Feb) | CW65: 75.35 | CX65: 1 | CY65: 10 | CZ65: 1 | DA65: 0.03 | DB65: 1 | DC65: 0 | DD65: 0 | DE65: 0 | DF65: 1 | DG65: 0 | DH65: 0 | DI65: per rate study (all of the above) | DJ65: 1 | DL65: 2 | DN65: 13.02 | DO65: 1 | DP65: 8176 | DQ65: 0 | DR65: 8176 | DS65: 0 | DT65: 2531 | DU65: 0 | DV65: 229 | DW65: 1 | DX65: 55 | DZ65: 273348000 | EA65: 44.5 | EB65: 2 | EC65: 2 | ED65: 1 | EF65: 2009 | EH65: 7 | EK65: 3800 | EM65: 5.4 | ER65: filter ponds | ES65: 3 | EU65: far into the future depending on growth (we can produce 3mgd more) | EV65: 2 | EW65: 1 | EX65: 4 | EY65: leak detection | EZ65: 100 | FD65: 1 | FE65: 8176 | FF65: 0 | FG65: 8176 | FH65: 0 | FI65: 2483 | FJ65: 1 | FK65: 194 | FL65: 1 | FM65: 44 | FN65: 1 | FP65: 39 | FR65: 2 | FS65: 2 | FT65: 0 | FU65: 1 | FV65: 0 | FW65: 1 | FX65: 1 | FY65: 0 | GA65: 1996 | GB65: 2012 | GC65: 2.71 | GD65: 6.87 | GE65: 615 | GF65: 5.24 | GG65: 2.87 | GH65: 100 | GI65: 2025 | GK65: 2 | GL65: 1 | GM65: 1-10% | GN65: for on site processes at the plant | GO65: 1 | GP65: field near the plant (city owned) or farmers pick it up | GQ65: 2 | GS65: We are looking for more locations to apply our solids. | GT65: 1 | GU65: 2511 | GV65: 1 | GW65: 232 | GX65: 1 | HA65: 29 | HB65: 66 and 5 swales | HC65: 2500
A66: Gladstone | B66: 11992 | C66: 5 | D66: 2 | E66: 1 | G66: 1 | H66: 1 | I66: 1 | J66: 0 | K66: 1 | L66: 1 | M66: 1 | N66: 0 | O66: 1 | P66: 1 | Q66: 0 | R66: 1 | S66: 0 | U66: 7 | W66: 5 | Z66: 10 | AC66: 1 | AD66: Waive of Late Fees or Shut Off Fees if past due balance is received. Low Income Utility Assistance Program | AE66: 3 | AF66: 2 | AH66: 3 months | AM66: 1 | AN66: 1 | AO66: 1 | AP66: 1 | AQ66: 1 | AR66: 1 | AS66: 2014 | AT66: 2017 | AU66: 2014 | AV66: 2014 | AW66: 2017 | AX66: 2014 | AY66: 1 | AZ66: 2 | BC66: 0 | BD66: 0 | BE66: 1 | BF66: 0 | BG66: 0 | BH66: 0 | BJ66: 1 | BK66: 0 | BL66: 0 | BM66: 1 | BN66: 0 | BO66: 0 | BP66: 0 | BQ66: 0 | BR66: 5% ROW Fee | BV66: 1 | BW66: 2024 | BX66: 1 | BY66: 0.04 | BZ66: 0 | CA66: 1 | CB66: 0 | CC66: 1 | CD66: 0 | CE66: 0 | CF66: Maintenance & Improvements | CG66: 3 | CI66: 44.34 | CJ66: 1 | CK66: 2025 | CL66: 1 | CN66: 0 | CO66: 0 | CP66: 0 | CQ66: 1 | CR66: 0 | CS66: 0 | CT66: Passthrough WES and OLWS | CU66: 4 | CV66: Passthrough WES and OLWS | CX66: 1 | CY66: 7 | CZ66: 1 | DA66: 0.04 | DB66: 1 | DC66: 1 | DD66: 1 | DE66: 0 | DF66: 1 | DG66: 0 | DH66: 0 | DI66: Maintenance & Improvement | DJ66: 1 | DL66: 1 | DM66: For properties that construct stormwater systems above and beyond minimum design requirements. The amount of the fee reductions is based on the % the system exceeds minimum requirements. | DN66: 15.44 | DO66: 1 | DP66: 3700 | EA66: 39 | EB66: 2 | EC66: 3 | ED66: 2 | EE66: 1920 | EF66: 2000 | EG66: 42 | EH66: 20 | EI66: 1.31 | EL66: 7 | EM66: 2.2 | EN66: 5 | EO66: 10 | EP66: 7 | EQ66: 6 | EU66: Unknown, not likely to exceed. | EV66: 1 | EW66: 1 | EX66: 1 | EZ66: 0.02 | FB66: 0.98 | FD66: 1 | FE66: 13000 | FP66: 35 | FQ66: 1 | FR66: 8 | FS66: 11 | FT66: 0 | FU66: 0 | FV66: 1 | FW66: 0 | FX66: 0 | FY66: 0 | FZ66: Passthrough WES and OLWS | GH66: 0.85 | GI66: Unknown | GJ66: Unknown | GK66: 2 | GL66: 2 | GM66: n/a | GO66: 2 | GQ66: 2 | GT66: 1 | GU66: 3700 | HA66: 30 | HB66: 1
A67: Clatskanie | B67: 1791 | C67: 3 | D67: 1 | E67: 1 | G67: 1 | H67: 1 | I67: 1 | J67: 1 | K67: 1 | L67: 0 | M67: 1 | N67: 1 | O67: 1 | P67: 1 | Q67: 0 | R67: 0 | S67: 0 | U67: 10 | W67: 45 | Z67: 38 | AC67: 1 | AD67: discounted water/sewer rates for low income customers | AE67: 3 | AF67: 3 | AH67: we get an average of 3 months and take 50% off of the leak after the average is taken off. | AI67: if a leak is suspected, a customer must apply for a leak adjustment after it is fixed. public works verifies leak if fixed and approves the adjustment. we will make an adjustment after the leak has billed out. | AM67: 1 | AN67: 1 | AO67: 1 | AP67: 1 | AQ67: 1 | AR67: 1 | AY67: 2 | AZ67: 4 | BB67: if no one signs up for water service, the water is shut off. if it is a landlord/tenant situation, typically it goes back into the landlords name, unless the landlord has a new tenant moving in right away. | BC67: 0 | BD67: 1 | BE67: 0 | BF67: 0 | BG67: 1 | BH67: 0 | BJ67: 1 | BK67: 0 | BL67: 0 | BM67: 1 | BN67: 0 | BO67: 0 | BP67: 0 | BQ67: 0 | BR67: street/Storm, IMIF | BS67: 2 | BT67: 2 | BU67: 2 | BV67: 2 | CJ67: 2 | CX67: 2 | DO67: 1 | DP67: 639 | DQ67: 171 | DT67: 639 | DU67: 171 | DV67: 93 | DZ67: 13000000 | EA67: 40 | EB67: 3 | EC67: 15 | ED67: 3 | EE67: 1976 | EG67: 50000 | FC67: all of the blank answers are the same as last year. | FD67: 1 | FE67: 783 | FF67: 172 | FP67: 12 | FQ67: 2 | FR67: 2 | FT67: 0 | FU67: 0 | FV67: 1 | FW67: 0 | FX67: 0 | FY67: 0 | FZ67: same answer as last year | GA67: 1974 | GS67: all data is the same as last year. | GT67: 2 | HE67: this seemed to be about infrastructure vs actual water rates.
A68: Gresham | B68: 115233 | C68: 5 | D68: 2 | E68: 2 | G68: 1 | H68: 1 | I68: 1 | J68: 1 | K68: 1 | L68: 1 | M68: 1 | N68: 1 | O68: 1 | P68: 1 | Q68: 0 | R68: 1 | S68: 1 | T68: Automated Phone Calls | Z68: 47 | AB68: 30 | AC68: 1 | AD68: Stormwater discounts with approved run-off plan Customer assistance grant to help pay one bill, one time per year | AE68: 3 | AF68: 2 | AG68: 120 | AJ68: 7.73 | AK68: 1.72 | AL68: 2.04 | AP68: 1 | AQ68: 2 | AR68: 2 | AS68: 2021 | AT68: 2021 | AU68: 2021 | AV68: 2023 | AW68: 2016 | AX68: 2016 | AY68: 1 | AZ68: 4 | BB68: billing continues to owner, stop billing only for non-payment | BC68: 0 | BD68: 0 | BE68: 0 | BF68: 1 | BG68: 1 | BH68: 1 | BI68: pre-disconnection notice, cutlock, after hours reconnection, collection fee on closed account | BJ68: 1 | BK68: 1 | BL68: 0 | BM68: 1 | BN68: 1 | BO68: 1 | BP68: 0 | BQ68: 0 | BR68: Flood Levy Fee, Police, Fire, Parks all in one fee | BS68: 2 | BT68: 2 | BU68: 2 | BV68: 1 | BW68: 2025 | BX68: 1 | BY68: 9.31 | BZ68: 1 | CA68: 1 | CB68: 1 | CC68: 1 | CD68: 0 | CE68: 1 | CF68: Development of groundwater system | CG68: 5 | CH68: Flat plus water use | CI68: 114.52 | CJ68: 1 | CK68: 2025 | CL68: 1 | CM68: 9.43 | CN68: 1 | CO68: 1 | CP68: 1 | CQ68: 0 | CR68: 0 | CS68: 0 | CU68: 4 | CV68: Flat rate plus WWA | CW68: 40.88 | CX68: 1 | CY68: 7 | CZ68: 1 | DA68: 9.43 | DB68: 3 | DC68: 1 | DD68: 1 | DE68: 1 | DF68: 0 | DG68: 0 | DH68: 0 | DJ68: 1 | DL68: 1 | DM68: Residential 27% discount; at least 75% of properties hard surface must drain into ground | DN68: 19.48 | DO68: 1 | DP68: 73932 | DR68: 73932 | DT68: 17668 | DV68: 753 | DX68: 139 | DZ68: 4680 | EA68: 280 | EB68: 9 | EC68: 11 | ED68: 0 | EF68: 2025 | EG68: 18 | EH68: 30 | EI68: 6378000 | EJ68: 6377000 | EK68: 10639000 | EL68: 4 | EM68: 0 | EN68: 1 | EO68: 1 | EP68: 1 | EQ68: 1 | ER68: N/A | ES68: 0 | ET68: 0 | EU68: 2035 | EV68: 1 | EW68: 1 | EX68: 2 | EZ68: 100 | FA68: 0 | FB68: 0 | FC68: None | FD68: 1 | FE68: 124000 | FF68: 0 | FI68: 24627 | FJ68: 1 | FK68: 1092 | FL68: 1 | FM68: 155 | FN68: 1 | FP68: 327 | FQ68: 6 | FR68: 2 | FS68: 2 | FT68: 0 | FU68: 0 | FV68: 1 | FW68: 0 | FX68: 0 | FY68: 1 | FZ68: Activated sludge | GA68: 1954 | GB68: 2000 | GC68: 15 | GD68: 25 | GE68: 12.21 | GF68: 35.46 | GG68: 24.78 | GH68: 61 | GI68: 2030 | GJ68: 2030 | GK68: 1 | GL68: 2 | GM68: 0 | GO68: 1 | GP68: Private farmland in Western and Eastern Oregon | GQ68: 2 | GS68: None | GT68: 1 | GU68: 24671 | GW68: 1034 | GY68: 168 | HB68: unknown | HC68: 2500 | HD68: None
A69: Adams | B69: 410 | C69: 1 | D69: 11 | E69: 1 | G69: 1 | H69: 1 | I69: 1 | J69: 1 | K69: 1 | L69: 1 | M69: 1 | N69: 1 | O69: 1 | P69: 1 | Q69: 0 | R69: 1 | S69: 0 | U69: 20 | W69: 5 | Z69: 60 | AA69: 10 | AB69: 5 | AC69: 2 | AE69: 2 | AH69: No adjustments | AJ69: 12.88 | AP69: 1 | AS69: 2015 | AV69: 2018 | AY69: 2 | AZ69: 2 | BC69: 1 | BD69: 1 | BE69: 0 | BF69: 1 | BG69: 1 | BH69: 1 | BI69: Reconstruction of Customer Service Pipe, meter upgrades, meter replacement, NSF Charge | BJ69: 2 | BS69: 2 | BV69: 2 | CJ69: 2 | CX69: 2 | DO69: 2 | FD69: 2 | GT69: 2
A70: Salem | B70: 177567 | C70: 5 | D70: 3 | E70: 1 | G70: 1 | H70: 1 | I70: 1 | J70: 1 | K70: 1 | L70: 1 | M70: 1 | N70: 1 | O70: 1 | P70: 0 | Q70: 0 | R70: 1 | S70: 0 | Z70: 16 | AA70: 25.01 | AB70: 23 | AC70: 1 | AD70: Utility Rate Relief program - a monthly discount on the sewer portion of the utility bill plus waiver of City Operations Fee and Streetlight Fee. | AE70: 3 | AF70: 3 | AH70: Adjustment for franchise fee | AI70: Reset the wastewater base to either the average of two meter readings after repair - or- last year's wastewater base - or - the City average. If a longtime leak adjustment may be made for the calendar year or for the months of the leak and the rate changed for the remainder of the year. | AJ70: 13 | AK70: 14 | AL70: 1 | AP70: 1 | AQ70: 1 | AR70: 1 | AS70: 2024 | AT70: 2024 | AU70: 2024 | AV70: 2018 | AW70: 2018 | AX70: 2018 | AY70: 2 | AZ70: 1 | BA70: Vacant property accounts are closed or charged a vacant wastewater rate if the owner wants the account to remain open. | BC70: 1 | BD70: 1 | BE70: 0 | BF70: 0 | BG70: 1 | BH70: 1 | BJ70: 1 | BK70: 0 | BL70: 0 | BM70: 1 | BN70: 0 | BO70: 0 | BP70: 0 | BQ70: 0 | BR70: City Operations Fee, Streetlight Fee | BS70: 2 | BT70: 2 | BU70: 2 | BV70: 1 | BW70: 2025 | BX70: 1 | BY70: 4.5 | BZ70: 1 | CA70: 1 | CB70: 1 | CC70: 0 | CD70: 0 | CE70: 1 | CG70: 4 | CJ70: 1 | CK70: 2025 | CL70: 1 | CM70: 4.5 | CN70: 1 | CO70: 1 | CP70: 1 | CQ70: 0 | CR70: 0 | CS70: 1 | CU70: 4 | CV70: Winter average water consumption used for 12 months | CX70: 1 | CY70: 7 | CZ70: 1 | DA70: 4.5 | DB70: 1 | DC70: 0 | DD70: 1 | DE70: 1 | DF70: 0 | DG70: 1 | DH70: 0 | DJ70: 1 | DL70: 1 | DM70: The stormwater credit for non-residential customers varies from 3 percent to 50 percent. To be eligible, a facility must have been designed and constructed to city standards. Flow control facilities are designed to reduce runoff. Treatment facilities remove pollutants. Stormwater credits are based on the type of facility installed, amount of water flowing through the facility, and the impact the facility has on stormwater quality. Single Family Residential customers are eligible if the property meets specific criteria: property zoned Residential Agriculture; total area is at least one acre; amount of impervious surface area is less than ten percent of the total area of the property; and the tree canopy on the property is at least ten percent of the total area on the property. Customers meeting the criteria will receive a monthly credit equal to the impervious surface fee. | DN70: 21.64 | DO70: 1 | DP70: 177567 | DQ70: 35557 | DR70: 177567 | DS70: 35557 | DT70: 42329 | DU70: 8269 | DV70: 3029 | DW70: 8 | DX70: 2957 | DY70: 4 | DZ70: 66305 | EA70: 790.5 | EC70: 28 | ED70: 13 | EE70: 1936 | EF70: 2021 | EI70: 28.8 | EJ70: 0.8585 | EK70: 50.76 | EO70: 3 | EQ70: 5 | EU70: 2050 | EV70: 1 | EW70: 1 | EX70: 1 | EZ70: 8 | FA70: 92 | FD70: 1 | FE70: 177567 | FF70: 77211 | FG70: 177567 | FH70: 77211 | FI70: 42241 | FJ70: 5 | FK70: 3014 | FL70: 8 | FM70: 2242 | FN70: 4 | FO70: 5.26 | FP70: 833.1 | FQ70: 31 | FR70: 3 | FS70: 10 | FT70: 0 | FU70: 0 | FV70: 0 | FW70: 0 | FX70: 0 | FY70: 1 | GA70: 1964 | GB70: 2021 | GC70: 35 | GD70: 205 | GE70: 146.38 | GF70: 16117 | GG70: 76.86 | GK70: 1 | GL70: 1 | GM70: Not measured | GN70: Used in plant only for irrigation, flushing water, and seal water. | GO70: 1 | GP70: Beneficial reuse on farmland. | GQ70: 2 | GT70: 1 | GU70: 42696 | GW70: 2552 | GY70: 1972 | HA70: 520.8 | HB70: 133.36 | HC70: 3000
A71: Carlton | B71: 2456 | C71: 3 | D71: 3 | E71: 1 | G71: 1 | H71: 1 | I71: 1 | J71: 0 | K71: 1 | L71: 0 | M71: 1 | N71: 1 | O71: 1 | P71: 1 | Q71: 0 | R71: 1 | S71: 0 | U71: 5 | W71: 1 | Z71: 30 | AB71: 30 | AC71: 2 | AE71: 1 | AG71: 30 | AJ71: 27 | AK71: 19 | AO71: 1 | AP71: 2 | AQ71: 2 | AR71: 2 | AS71: 2025 | AT71: 2025 | AU71: N/A | AV71: 2025 | AW71: 2025 | AX71: N/A | AY71: 1 | AZ71: 4 | BB71: Billed the same as occupied properties | BC71: 0 | BD71: 1 | BE71: 0 | BF71: 0 | BG71: 1 | BH71: 1 | BJ71: 2 | BK71: 0 | BL71: 0 | BM71: 1 | BN71: 0 | BO71: 0 | BP71: 0 | BQ71: 0 | BR71: None | BS71: 1 | BT71: 1 | BV71: 1 | BW71: 2025 | BX71: 1 | BY71: 2.9 | BZ71: 0 | CA71: 1 | CB71: 0 | CC71: 0 | CD71: 0 | CE71: 0 | CG71: 5 | CH71: Flat Rate + Consumption | CI71: 97.42 | CJ71: 1 | CK71: 2025 | CL71: 1 | CM71: 6.9 | CN71: 0 | CO71: 1 | CP71: 0 | CQ71: 0 | CR71: 0 | CS71: 0 | CU71: 4 | CV71: Flat Rate and Winter Average Consumption | CW71: 132.59 | CX71: 2 | DO71: 1 | DP71: 1027 | DQ71: 104 | DT71: 1021 | DU71: 99 | DV71: 6 | DW71: 7 | DX71: 7 | DY71: 5 | DZ71: 78000000 | EA71: 13 | EB71: 0 | EC71: 1 | ED71: 8 | EE71: 1920 | EF71: 2022 | EG71: 12 | EH71: 1.3 | EI71: 0.344 | EJ71: 0.87 | EK71: 661000 | EL71: 8 | EM71: 1.75 | EN71: 6 | EO71: 11 | EP71: 8 | EQ71: 7 | ER71: Raw Open Reservoir | ES71: 9 | ET71: NA | EU71: Never | EV71: 1 | EW71: 1 | EX71: 1 | EZ71: 100 | FA71: 0 | FB71: 0 | FD71: 1 | FE71: 1041 | FF71: 0 | FG71: 0 | FH71: 0 | FI71: 980 | FJ71: 1 | FK71: 0 | FL71: 1 | FM71: 0 | FN71: 1 | FO71: 600 | FP71: 4.5 | FR71: 2 | FS71: 2 | FT71: 0 | FU71: 0 | FV71: 0 | FW71: 0 | FX71: 1 | FY71: 1 | GA71: 1989 | GB71: 2025 | GC71: 0.3 | GE71: 92.4 | GF71: 3.69 | GG71: 0.44 | GH71: 100 | GI71: 2025 | GJ71: 2025 | GK71: 2 | GL71: 1 | GM71: 5 | GN71: Farmland | GO71: 2 | GQ71: 2 | GS71: NA | GT71: 2
A72: Lowell | B72: 1304 | C72: 2 | D72: 4 | E72: 1 | G72: 1 | H72: 1 | I72: 1 | J72: 1 | K72: 1 | L72: 1 | M72: 1 | N72: 1 | O72: 1 | P72: 1 | Q72: 0 | R72: 1 | S72: 0 | W72: 1 | Z72: 16 | AB72: 90 | AC72: 1 | AD72: Utility assistances | AE72: 3 | AF72: 2 | AG72: 60 | AM72: 1 | AN72: 1 | AO72: 1 | AP72: 1 | AQ72: 1 | AR72: 1 | AT72: N/A | AU72: N/A | AW72: N/A | AX72: N/A | AY72: 2 | AZ72: 1 | BA72: Must shoe no usage on meter | BC72: 0 | BD72: 0 | BE72: 0 | BF72: 0 | BG72: 1 | BH72: 0 | BJ72: 2 | BS72: 2 | BT72: 2 | BU72: 2 | BV72: 1 | BW72: 2025 | BX72: 1 | BY72: 3.5 | BZ72: 0 | CA72: 1 | CB72: 0 | CC72: 0 | CD72: 0 | CE72: 0 | CG72: 1 | CI72: 70.37 | CJ72: 1 | CK72: 2025 | CL72: 1 | CM72: 3.5 | CN72: 0 | CO72: 1 | CP72: 0 | CQ72: 0 | CR72: 0 | CS72: 0 | CU72: 1 | CW72: 74.52 | CX72: 2 | DO72: 1 | DP72: 1270 | DQ72: 0 | DT72: 466 | DU72: 0 | DV72: 42 | DW72: 1 | DX72: 12 | DY72: 1 | DZ72: 3500 | EA72: 7.5 | EB72: 1 | EC72: 0 | ED72: 0 | EE72: 1950 | EF72: 2004 | EG72: 1 | EH72: 0.288 | EI72: 0.127 | EJ72: 85 | EK72: 0.288 | EL72: 1 | EM72: 1 | EN72: 1 | EO72: 1 | EP72: 1 | EQ72: 1 | EU72: 2026 | EV72: 1 | EW72: 1 | EX72: 2 | EZ72: 100 | FD72: 1 | FE72: 1270 | FF72: 0 | FI72: 476 | FJ72: 1 | FK72: 30 | FL72: 1 | FM72: 12 | FN72: 2 | FP72: 8.25 | FQ72: 1 | FR72: 2 | FS72: 2 | FT72: 1 | FU72: 0 | FV72: 0 | FW72: 0 | FX72: 1 | FY72: 1 | GA72: 1954 | GB72: 2004 | GC72: 0.3 | GD72: 1.5 | GE72: 63 | GF72: 0.992 | GG72: 1.452 | GH72: 50 | GI72: N/A | GJ72: N/A | GK72: 2 | GL72: 2 | GM72: 0 | GO72: 2 | GQ72: 2 | GT72: 1 | GU72: 0 | GW72: 0 | GY72: 0 | HA72: 3 | HB72: 4
A73: Canyonville | B73: 1643 | C73: 3 | D73: 7 | E73: 1 | G73: 1 | H73: 1 | I73: 1 | J73: 0 | K73: 1 | L73: 0 | M73: 1 | N73: 1 | O73: 1 | P73: 1 | Q73: 0 | R73: 1 | S73: 0 | U73: 10 | W73: 15 | Z73: 2 | AC73: 2 | AE73: 3 | AF73: 1 | AG73: 90 | AI73: Adjust off the overage on sewer base rate since the leak is would not be going into the sewer system. | AK73: 30 | AM73: 1 | AO73: 1 | AP73: 2 | AQ73: 2 | AR73: 2 | AS73: 2023 | AT73: 2010 | AY73: 2 | AZ73: 4 | BB73: Bill the base rate to owner | BC73: 0 | BD73: 0 | BE73: 1 | BF73: 0 | BG73: 0 | BH73: 0 | BJ73: 2 | BK73: 0 | BL73: 0 | BM73: 1 | BN73: 0 | BO73: 0 | BP73: 0 | BQ73: 0 | BR73: none | BS73: 2 | BT73: 2 | BU73: 2 | BV73: 1 | BX73: 1 | BY73: 10 | BZ73: 1 | CA73: 0 | CB73: 0 | CC73: 0 | CD73: 0 | CE73: 0 | CG73: 5 | CH73: Flat Rate+ Overage rate | CI73: 26.74 | CJ73: 1 | CK73: 2016 | CL73: 1 | CM73: 10 | CN73: 1 | CO73: 0 | CP73: 0 | CQ73: 0 | CR73: 0 | CS73: 0 | CU73: 4 | CV73: flat rate + overage rate | CW73: 7 | CX73: 2 | DO73: 1 | DP73: 1662 | DR73: 1662 | DT73: 533 | DU73: 28 | DV73: 117 | DW73: 4 | EA73: 5.9 | EB73: 1 | ED73: 0.25 | EE73: 1978 | EF73: 2001 | EG73: 300 | EH73: 600 | EJ73: 77 | EK73: 500 | EL73: 1 | EM73: 1753000 | EN73: 1 | EO73: 1 | EP73: 4 | EQ73: 1 | ER73: WTP Clearwell | ET73: 43000 | EU73: never | EV73: 2 | EW73: 1 | EX73: 1 | EZ73: 100 | FD73: 1 | FE73: 1662 | FG73: 1662 | FI73: 415 | FJ73: 3 | FK73: 86 | FL73: 5 | FP73: 7.27 | FQ73: 0 | FR73: 2 | FS73: 2 | FT73: 1 | FU73: 1 | FV73: 1 | FW73: 1 | FX73: 1 | FY73: 1 | FZ73: MBR Plant | GA73: 2019 | GB73: 2019 | GC73: 2.2 | GD73: 2.2 | GE73: 109500000 | GF73: 1.7 | GG73: 0.27 | GH73: 30 | GK73: 2 | GL73: 2 | GM73: 25 at plant | GO73: 2 | GQ73: 1 | GR73: 1 | GT73: 2
A74: Milton-Freewater | B74: 7321 | C74: 4 | D74: 11 | E74: 1 | G74: 1 | H74: 1 | I74: 1 | J74: 0 | K74: 1 | L74: 1 | M74: 1 | N74: 1 | O74: 0 | P74: 1 | Q74: 0 | R74: 0 | S74: 0 | U74: 10 | W74: 30 | AB74: 365 | AC74: 2 | AE74: 3 | AF74: 2 | AG74: 730 | AH74: 6 months for additional charges | AM74: 1 | AN74: 1 | AO74: 1 | AS74: 2009 | AT74: 2015 | AU74: No fees | AV74: 2009 | AW74: 2015 | AX74: No fees | AY74: 2 | AZ74: 4 | BB74: Services may still be active | BC74: 0 | BD74: 1 | BE74: 0 | BF74: 1 | BG74: 1 | BH74: 1 | BI74: Infrastructure | BJ74: 2 | BK74: 0 | BL74: 0 | BM74: 1 | BN74: 0 | BO74: 0 | BP74: 0 | BQ74: 0 | BR74: None | BS74: 2 | BT74: 2 | BU74: 2 | BV74: 1 | BW74: 2025 | BX74: 1 | BY74: 5 | BZ74: 1 | CA74: 1 | CB74: 1 | CC74: 0 | CD74: 1 | CE74: 1 | CG74: 1 | CI74: 34.31 | CJ74: 1 | CK74: 2025 | CL74: 1 | CM74: 5 | CN74: 1 | CO74: 1 | CP74: 1 | CQ74: 0 | CR74: 1 | CS74: 1 | CU74: 1 | CW74: 36.36 | CX74: 2 | DO74: 1 | DP74: 7289 | DQ74: 50 | DR74: 7289 | DS74: 50 | DT74: 2161 | DU74: 25 | DV74: 222 | DW74: 11 | DX74: 61 | DY74: 1 | DZ74: 52000 | EB74: 7 | EC74: 4 | ED74: 0.6 | EF74: 2023 | EG74: 24.528 | EI74: 1.93 | EK74: 4.4 | EL74: 1 | EM74: 3 | EN74: 1 | EO74: 1 | EP74: 1 | EQ74: 1 | EV74: 1 | EW74: 1 | EX74: 2 | EZ74: 99 | FA74: 0 | FB74: 1 | FD74: 1 | FE74: 7289 | FF74: 0 | FG74: 7289 | FH74: 0 | FI74: 2277 | FJ74: 1 | FK74: 243 | FL74: 3 | FM74: 6 | FN74: 1 | FP74: 29 | FQ74: 4 | FR74: 2 | FS74: 6 | FT74: 1 | FU74: 0 | FV74: 0 | FW74: 0 | FX74: 1 | FY74: 1 | GA74: 1948 | GB74: 2015 | GC74: 0.86 | GD74: 0.86 | GE74: 148413000 | GF74: 0.421 | GG74: 0.324 | GK74: 2 | GL74: 2 | GO74: 2 | GQ74: 1 | GR74: 1 | GT74: 1 | GU74: 0 | GV74: 1 | GW74: 0 | GX74: 1 | GY74: 0 | GZ74: 1
A75: Sherwood | B75: 20781 | C75: 5 | D75: 2 | E75: 1 | G75: 1 | H75: 1 | I75: 1 | J75: 0 | K75: 1 | L75: 1 | M75: 1 | N75: 1 | O75: 1 | P75: 1 | Q75: 0 | R75: 0 | S75: 0 | U75: 11.9 | W75: 10 | Z75: 15 | AA75: 24.99 | AB75: 30 | AC75: 1 | AD75: Low Income Assistance Rebates on Low Flow Toilets Water Leak credits | AE75: 3 | AF75: 3 | AG75: 30 | AH75: OR up to two billing cycles as long as leak is repaired within 10 days of discovery. | AI75: We keep track of all customers who had leaks and make sure their winter average is not affected by it when we recalculate it for the next year. We leave the consumption out of the month the leak occured when we recalculate the new average. | AJ75: 17 | AK75: 10 | AL75: 0 | AP75: 1 | AQ75: 1 | AR75: 1 | AS75: 2022 | AT75: 2022 | AU75: 2022 | AV75: 2022 | AW75: 2022 | AX75: 2022 | AY75: 1 | AZ75: 1 | BA75: We continue charging street and swm rates. Sometimes, we don't know why it's vacant and with that we don't know who to bill. | BC75: 1 | BD75: 1 | BE75: 0 | BF75: 0 | BG75: 1 | BH75: 1 | BJ75: 1 | BK75: 0 | BL75: 0 | BM75: 0 | BN75: 0 | BO75: 0 | BP75: 1 | BQ75: 1 | BS75: 2 | BT75: 2 | BU75: 2 | BV75: 1 | BX75: 1 | BY75: 0.02 | BZ75: 1 | CA75: 1 | CB75: 1 | CC75: 0 | CD75: 1 | CE75: 1 | CG75: 3 | CI75: 55.76 | CJ75: 1 | CK75: 2025 | CL75: 1 | CN75: 0 | CO75: 1 | CP75: 1 | CQ75: 0 | CR75: 1 | CS75: 0 | CU75: 3 | CW75: 58.17 | CX75: 1 | CY75: 7 | CZ75: 1 | DB75: 1 | DC75: 0 | DD75: 1 | DE75: 1 | DF75: 0 | DG75: 1 | DH75: 0 | DJ75: 1 | DL75: 1 | DM75: Storm charges based on impervious area. Properties that retain water on site are not assessed storm charges. | DN75: 19.15 | DO75: 1 | DP75: 20450 | DQ75: 0 | DR75: 0 | DS75: 0 | DT75: 5798 | DV75: 230 | DZ75: 715 | EA75: 88 | EB75: 2 | EC75: 4 | ED75: 5 | EE75: 1893 | EF75: 2011 | EG75: 6.7 | EH75: 30 | EI75: 1.97 | EJ75: 1.97 | EK75: 4.5 | EM75: 9 | EU75: 2063 | EW75: 1 | EX75: 1 | EZ75: 1 | FD75: 1 | FE75: 20450 | FF75: 0 | FG75: 0 | FH75: 0 | FI75: 5798 | FJ75: 1 | FK75: 230 | FL75: 1 | FN75: 1 | FO75: 6000 | FP75: 64.4 | FQ75: 0 | FR75: 2 | FS75: 2 | FT75: 0 | FU75: 0 | FV75: 1 | FW75: 0 | FX75: 0 | FY75: 0 | FZ75: Treatment provided by clean water services | GK75: 1 | GL75: 2 | GM75: 0 | GO75: 2 | GQ75: 2 | GT75: 1 | GU75: 5798 | GV75: 1 | GW75: 230 | GX75: 1 | GY75: 52 | GZ75: 1 | HA75: 66.8 | HB75: n/a | HC75: 2640
A76: Portland | B76: 640623 | C76: 5 | D76: 2 | E76: 3 | G76: 1 | H76: 1 | I76: 1 | J76: 1 | K76: 1 | L76: 1 | M76: 1 | N76: 1 | O76: 1 | P76: 1 | Q76: 1 | R76: 1 | S76: 0 | V76: 0.01 | W76: 28 | Y76: 0.01 | Z76: 56 | AA76: 100 | AB76: 49 | AC76: 1 | AD76: All customers are eligible to have one set of late fees removed per year. Our low-income assistance program is based on income and the number of individuals residing in the home. We currently have an application process that includes providing proof of income for our Tier 1 Discount - 50% of the typical bill (5 ccf) for applicants with 60% MFI and our Tier 2 Discount – 80% of the typical bill (5 ccf) for applicants with 30% MFI. Customers must reapply every 2 years. An emergency crisis assistance voucher may be offered one time per year, depending on situation and qualifications met. | AE76: 3 | AF76: 3 | AI76: Adjust wastewater based on water adjustment as wastewater billing is directly related to water usage. | AJ76: 30.5 | AK76: 33 | AL76: 0 | AP76: 1 | AQ76: 1 | AS76: 10 | AT76: 2023 | AU76: 2023 | AV76: 10 | AW76: 2003 | AX76: 2024 | AY76: 2 | AZ76: 4 | BB76: All property, occupied or vacant, includes a base charge, covers for having the service available and O&M of meters, and billing system. | BC76: 0 | BD76: 0 | BE76: 0 | BF76: 1 | BG76: 1 | BH76: 1 | BI76: Any assessed late fee | BJ76: 1 | BK76: 0 | BL76: 0 | BM76: 1 | BN76: 0 | BO76: 0 | BP76: 0 | BQ76: 0 | BR76: Portland Harbor Superfund | BS76: 2 | BT76: 2 | BU76: 2 | BV76: 1 | BW76: 2025 | BX76: 1 | BY76: 0.081 | BZ76: 1 | CA76: 1 | CB76: 1 | CC76: 1 | CD76: 1 | CE76: 1 | CF76: O&M and system maintenance | CG76: 4 | CJ76: 1 | CK76: 2025 | CL76: 1 | CM76: 0.0515 | CN76: 1 | CO76: 1 | CP76: 1 | CQ76: 1 | CR76: 1 | CS76: 1 | CT76: O&M and system maintenance | CU76: 3 | CW76: 90.29 | CX76: 1 | CY76: 7 | CZ76: 1 | DA76: 0.0515 | DB76: 1 | DC76: 1 | DD76: 1 | DE76: 1 | DF76: 1 | DG76: 0 | DH76: 1 | DI76: O&M and system maintenance | DJ76: 1 | DL76: 1 | DM76: Customer has to apply and show they are managing stormwater runoff so we can calculate the discount. The maximum credit is 35% of the total stormwater charge. | DO76: 1 | DP76: 666200 | DQ76: 351000 | DR76: 666200 | DS76: 351000 | DT76: 176200 | DV76: 20100 | DX76: 4600 | DY76: 2 | DZ76: 76 | EA76: 2313 | EC76: 154 | ED76: 26 | EE76: 1895 | EF76: 2023 | EG76: 9900000000 | EI76: 91 | EJ76: 84 | EK76: 135 | EL76: 3 | EM76: 55 | EN76: 1 | EO76: 5 | EP76: 1 | EQ76: 1 | EU76: n/a | EV76: 1 | EW76: 1 | EX76: 2 | EZ76: 1 | FA76: 4 | FB76: 95 | FC76: The City of Portland has one of the most robust affordability programs in the country. | FD76: 1 | FE76: 666200 | FF76: 351100 | FG76: 666200 | FH76: 351100 | FI76: 176200 | FK76: 20100 | FO76: 14.013 | FP76: 2662 | FQ76: 98 | FR76: 3 | FS76: 7 | FT76: 0 | FU76: 0 | FV76: 0 | FW76: 0 | FX76: 0 | FY76: 1 | GI76: As we are a CSO system we already have instances where the max wet weather capacity is exceeded, in those instances a CSO event occurs. Max capacity is defined in the NPDES permit. No plans to preform major system upgrades to expand capacity. | GJ76: We generally only look 20 years out as growth factors and projections can change over time. At this moment, we are not expected to exceed our design capacity until after 2045. | GK76: 1 | GL76: 2 | GO76: 1 | GP76: Dryland crops and pastureland. | GQ76: 1 | GR76: 5 | GS76: The City of Portland rarely landfills biosolids, only as a contingency | GT76: 1 | GU76: 176200 | GW76: 20100 | HA76: 446 | HB76: 117.6 | HC76: 2400
A77: Sandy | B77: 13044 | C77: 5 | D77: 2 | E77: 1 | G77: 1 | H77: 1 | I77: 1 | J77: 1 | K77: 1 | L77: 1 | M77: 1 | N77: 0 | O77: 1 | P77: 1 | Q77: 0 | R77: 1 | S77: 0 | U77: 5 | W77: 30 | Z77: 45 | AC77: 1 | AD77: Water and sewer charges are reduced by 50% for low income. | AE77: 3 | AF77: 3 | AI77: The consumption is compared to the same month of the prior year. If the consumption has doubled then 75% of the excess water consumption is credited to the customer. | AM77: 1 | AN77: 1 | AO77: 1 | AP77: 2 | AQ77: 1 | AR77: 2 | AS77: 2024 | AT77: 2024 | AU77: n/a | AV77: 2024 | AW77: 2024 | AX77: n/a | AY77: 2 | AZ77: 4 | BB77: Bills (base rate & consumption) will be directed to the property owner or manager until occupied. | BC77: 0 | BD77: 0 | BE77: 0 | BF77: 0 | BG77: 1 | BH77: 1 | BJ77: 1 | BK77: 0 | BL77: 0 | BM77: 0 | BN77: 0 | BO77: 1 | BP77: 0 | BQ77: 0 | BV77: 1 | BW77: 2025 | BX77: 1 | BY77: 0.36 | BZ77: 1 | CA77: 1 | CB77: 1 | CC77: 0 | CD77: 0 | CE77: 1 | CG77: 1 | CJ77: 1 | CK77: 2025 | CL77: 1 | CM77: 16 | CN77: 1 | CO77: 1 | CP77: 1 | CQ77: 0 | CR77: 0 | CS77: 1 | CU77: 3 | CX77: 1 | CY77: 7 | CZ77: 1 | DA77: 0.09 | DB77: 2 | DC77: 0 | DD77: 1 | DE77: 1 | DF77: 0 | DG77: 0 | DH77: 0 | DJ77: 1 | DL77: 1 | DM77: Residents that choose to detain/treat stormwater on site can apply for a 33% discount on their rate. | DN77: 11 | DO77: 1 | DP77: 4137 | DQ77: 108 | DT77: 3759 | DU77: 82 | DV77: 251 | DW77: 6 | DX77: 127 | DY77: 1 | DZ77: 60051 | EA77: 67 | EB77: 4 | EC77: 6 | EE77: 1974 | EG77: 2 | EI77: 11 | EK77: 2.3 | EM77: 4.75 | EU77: 2050 with current projects complete | EV77: 1 | EW77: 1 | EX77: 1 | EZ77: 100 | FD77: 1 | FE77: 3936 | FF77: 8 | FI77: 3626 | FJ77: 11 | FK77: 213 | FL77: 1 | FM77: 97 | FN77: 1 | FO77: 60051 | FP77: 41 | FQ77: 6 | FR77: 2 | FS77: 2 | FT77: 1 | FU77: 0 | FV77: 0 | FW77: 0 | FX77: 0 | FY77: 0 | GA77: 1957 | GB77: 2022 | GC77: 5 | GD77: 7 | GE77: 443.02 | GF77: 3.09 | GG77: 1.56 | GH77: 100 | GI77: Current | GL77: 2 | GM77: all flows May through Oct are used for irrigation | GO77: 2 | GQ77: 1 | GR77: 1 | GT77: 1 | GU77: 3736 | GV77: 1 | GW77: 284 | GX77: 1 | GY77: 73 | GZ77: 1 | HA77: 6.5 | HB77: unk | HC77: 2750
A78: Salem | B78: 177567 | C78: 5 | D78: 3 | E78: 1 | G78: 1 | H78: 1 | I78: 1 | J78: 1 | K78: 1 | L78: 1 | M78: 1 | N78: 1 | O78: 1 | P78: 0 | Q78: 0 | R78: 1 | S78: 0 | Z78: 16 | AA78: 25.01 | AB78: 23 | AC78: 1 | AD78: Utility Rate Relief program - a monthly discount on the sewer portion of the utility bill plus waiver of the City Operations Fee and Streetlight Fee | AE78: 3 | AF78: 3 | AH78: Adjustment of franchise fee | AI78: Reset the wastewater base to either the average of two meter readings after repair - or- last year's wastewater base - or - the City average. If a longtime leak adjustment may be made for the calendar year or for the months of the leak and the rate changed for the remainder of the year. | AJ78: 13 | AK78: 14 | AL78: 1 | AP78: 1 | AQ78: 1 | AR78: 1 | AS78: 2024 | AT78: 2024 | AU78: 2024 | AV78: 2018 | AW78: 2018 | AX78: 2018 | AY78: 2 | AZ78: 1 | BA78: Vacant property accounts are closed or charged a vacant wastewater rate if the owner wants the account to remain open.If a vacant property account is open, all charges except wastewater volume are billed at the regular rate. Wastewater volume is billed at the rate of .5 ccf. | BC78: 1 | BD78: 1 | BE78: 0 | BF78: 1 | BG78: 0 | BH78: 1 | BI78: Operational Fees (Streetlight Fee, City Operations Fee) | BJ78: 1 | BK78: 0 | BL78: 0 | BM78: 1 | BN78: 0 | BO78: 0 | BP78: 0 | BQ78: 0 | BR78: Administrative fees for specific account class/area | BS78: 2 | BT78: 2 | BU78: 2 | BV78: 1 | BW78: 2025 | BX78: 1 | BY78: 4.5 | BZ78: 1 | CA78: 1 | CB78: 1 | CC78: 0 | CD78: 0 | CE78: 1 | CG78: 4 | CJ78: 1 | CK78: 2025 | CL78: 1 | CM78: 4.5 | CN78: 1 | CO78: 1 | CP78: 1 | CQ78: 0 | CR78: 0 | CS78: 1 | CU78: 4 | CV78: Winter average water consumption used for 12 months | CX78: 1 | CY78: 7 | CZ78: 1 | DA78: 4.5 | DB78: 1 | DC78: 0 | DD78: 1 | DE78: 1 | DF78: 0 | DG78: 1 | DH78: 0 | DJ78: 1 | DL78: 1 | DM78: The stormwater credit for non-residential customers varies from 3 percent to 50 percent. To be eligible, a facility must have been designed and constructed to city standards. Flow control facilities are designed to reduce runoff. Treatment facilities remove pollutants. Stormwater credits are based on the type of facility installed, amount of water flowing through the facility, and the impact the facility has on stormwater quality. Single Family Residential customers are eligible if the property meets specific criteria: property zoned Residential Agriculture; total area is at least one acre; amount of impervious surface area is less than ten percent of the total area of the property; and the tree canopy on the property is at least ten percent of the total area on the property. Customers meeting the criteria will receive a monthly credit equal to the impervious surface fee. | DN78: 21.64 | DO78: 1 | DP78: 177567 | DQ78: 35557 | DR78: 177567 | DS78: 35557 | DT78: 42329 | DU78: 8269 | DV78: 3029 | DW78: 8 | DX78: 2957 | DY78: 4 | DZ78: 66305 | EA78: 790.5 | EC78: 28 | ED78: 13 | EE78: 1936 | EF78: 2021 | EI78: 28.8 | EJ78: 0.8585 | EK78: 50.76 | EL78: 1 | EN78: 1 | EO78: 8 | EP78: 1 | EQ78: 5 | EU78: 2050 | EV78: 1 | EW78: 1 | EX78: 1 | EZ78: 8 | FA78: 92 | FD78: 1 | FE78: 177567 | FF78: 77211 | FG78: 177567 | FH78: 77211 | FI78: 42241 | FJ78: 6 | FK78: 3014 | FL78: 8 | FM78: 2242 | FN78: 4 | FO78: 5.26 | FP78: 833.1 | FQ78: 31 | FR78: 3 | FS78: 10 | FT78: 0 | FU78: 0 | FV78: 0 | FW78: 0 | FX78: 0 | FY78: 1 | GA78: 1964 | GB78: 2021 | GC78: 35 | GD78: 205 | GE78: 16117 | GF78: 146.38 | GG78: 76.86 | GK78: 1 | GL78: 1 | GM78: Not measured | GN78: Used in plant only for irrigation, flushing water, and seal water. | GO78: 1 | GP78: Beneficial reuse on farmland. | GQ78: 2 | GT78: 1 | GU78: 42696 | GW78: 2552 | GY78: 1972 | HA78: 520.8 | HB78: 133.36 | HC78: 3000
A79: West Linn | B79: 27568 | C79: 5 | D79: 2 | E79: 1 | G79: 1 | H79: 1 | I79: 1 | J79: 0 | K79: 1 | L79: 0 | M79: 1 | N79: 1 | O79: 1 | P79: 1 | Q79: 0 | R79: 0 | S79: 0 | U79: 0.02 | W79: 10 | Z79: 90 | AA79: 100 | AB79: 60 | AC79: 1 | AD79: The City offers a low income assistance program where residents can apply and qualify if their gross household income is less than 185% of the Federal Poverty Guidelines. Right now the reduction on their billing is approximately $70 per month. In addition, occasionally the City offers a targeted program to select customers for a small rebate, for example a lead testing program and if the resident opts in they get a $10 credit on one bill. | AE79: 3 | AF79: 3 | AG79: 365 | AH79: Customers are eligible for one leak adjustment every rolling 12 months where the City writes off half of the excess water consumption compared to the prior year's usage. | AI79: For residential accounts, the sewer charges are flat and do not fluctuate. For commercial accounts, there is a base sewer fee for up to 10 CCUs of water, over 10 CCUs of water there is an additional sewer charge. If a Commercial account has a leak, we compare the excess water consumption of the bill with the leak to the usage from the same time period in the prior year and we write off half of the overage above and beyond the base billing of 10 CCUs of water. | AJ79: 24 | AK79: 14 | AL79: 39 | AP79: 2 | AQ79: 2 | AR79: 2 | AT79: n/a | AU79: n/a | AW79: n/a | AX79: n/a | AY79: 2 | AZ79: 4 | BB79: If a property is vacant we ask that the property owner maintain an account in their name but if there is no water consumed then we "suspend" the billing, which means for those months that no water is used we waive all charges. Once water consumption resumes, billing is resumes. | BC79: 0 | BD79: 0 | BE79: 0 | BF79: 1 | BG79: 1 | BH79: 0 | BI79: For our Shut off process, we charge $7.50 for a mailed shut off notice 10 day prior to shut off, then we charge $15 for a Door Hanger that is placed on the property door two days prior to shut off and then we charge $30 is the water is actually shut off by Public Works. | BJ79: 1 | BK79: 0 | BL79: 0 | BM79: 0 | BN79: 1 | BO79: 0 | BP79: 1 | BQ79: 1 | BS79: 2 | BT79: 2 | BU79: 2 | BV79: 1 | BW79: 2025 | BX79: 1 | BY79: 5 | BZ79: 0 | CA79: 0 | CB79: 0 | CC79: 1 | CD79: 0 | CE79: 0 | CF79: Our municipal code only allows for the City to increase utility rates 5% per year. Historically the 5% increase is not keeping up with costs, so City Council typically approves the 5% increase annually. | CG79: 1 | CI79: 31.71 | CJ79: 1 | CK79: 2025 | CL79: 1 | CM79: 5 | CN79: 0 | CO79: 0 | CP79: 0 | CQ79: 1 | CR79: 0 | CS79: 0 | CT79: Our municipal code only allows for the City to increase utility rates 5% per year. Historically the 5% increase is not keeping up with costs, so City Council typically approves the 5% increase annually. | CU79: 4 | CV79: Residential waste water is a flat rate, Commercial wastewater is flat rate but inclining fee based on additional usage over 10 CCUs of water | CX79: 1 | CY79: 7 | CZ79: 1 | DA79: 5 | DB79: 1 | DC79: 0 | DD79: 0 | DE79: 0 | DF79: 1 | DG79: 0 | DH79: 0 | DI79: Our municipal code only allows for the City to increase utility rates 5% per year. Historically the 5% increase is not keeping up with costs, so City Council typically approves the 5% increase annually. | DJ79: 1 | DL79: 1 | DM79: If a commercial building has their own onsite stormwater management system, after inspection from Public Works, we do not charge them for stormwater fees. | DN79: 9.53 | DO79: 1 | DP79: 28000 | DR79: 28000 | DT79: 9600 | DV79: 400 | DZ79: 748022440 | EA79: 118.5 | EB79: 5 | EC79: 5 | ED79: 3 | EF79: 2018 | EL79: 7 | EM79: 7.5 | EN79: 5 | EO79: 1 | EP79: 7 | EQ79: 1 | EU79: n/a | EV79: 1 | EW79: 1 | EX79: 2 | EZ79: 0 | FA79: 0 | FB79: 100 | FD79: 1 | FE79: 28000 | FG79: 28000 | FI79: 9600 | FK79: 400 | FO79: 7 | FP79: 147 | FQ79: 7 | FR79: 1 | FS79: 2 | FT79: 0 | FU79: 0 | FV79: 1 | FW79: 0 | FX79: 0 | FY79: 0 | FZ79: WES Tri-City Sewer provides the treatment of city wastewater | GI79: n/a | GJ79: n/a | GK79: 2 | GL79: 2 | GM79: n/a | GO79: 2 | GQ79: 2 | GS79: Treatment of city wastewater services is provided by Tri-City sewers | GT79: 1 | GU79: 8600 | GW79: 140 | HA79: 600000 | HB79: 0 | HC79: 2914
A80: North Plains | B80: 3815 | C80: 4 | D80: 2 | E80: 1 | G80: 1 | H80: 1 | I80: 1 | J80: 0 | K80: 1 | L80: 0 | M80: 1 | N80: 0 | O80: 1 | P80: 1 | Q80: 0 | R80: 0 | S80: 0 | U80: 0.1 | Z80: 40 | AC80: 1 | AD80: Limited waivers for select non-profit(s) in the city. | AE80: 3 | AF80: 2 | AG80: 30 | AH80: Receipt of leak repair must also be presented | AJ80: 16 | AN80: 1 | AO80: 1 | AP80: 1 | AS80: 2023 | AU80: 2023 | AY80: 2 | AZ80: 2 | BC80: 1 | BD80: 1 | BE80: 0 | BF80: 1 | BG80: 1 | BH80: 0 | BI80: Monthly transportation utility fee | BJ80: 1 | BK80: 0 | BL80: 0 | BM80: 0 | BN80: 0 | BO80: 0 | BP80: 1 | BQ80: 0 | BS80: 2 | BU80: 2 | BV80: 1 | BW80: 2025 | BX80: 1 | BY80: 4.2 | BZ80: 0 | CA80: 1 | CB80: 0 | CC80: 0 | CD80: 0 | CE80: 0 | CG80: 1 | CJ80: 2 | CX80: 2 | DO80: 1 | DP80: 3815 | DQ80: 1 | DU80: 1 | FD80: 2 | GT80: 2
A81: Veneta | B81: 5300 | C81: 4 | D81: 4 | E81: 1 | G81: 1 | H81: 1 | I81: 1 | J81: 1 | K81: 1 | L81: 1 | M81: 1 | N81: 0 | O81: 1 | P81: 1 | Q81: 1 | R81: 1 | S81: 0 | U81: 40 | V81: 0 | W81: 60 | X81: 0 | Y81: 0 | Z81: 60 | AC81: 2 | AE81: 3 | AF81: 2 | AG81: 90 | AJ81: 72 | AK81: 12 | AO81: 1 | AP81: 1 | AQ81: 2 | AS81: 2022 | AT81: 2022 | AU81: 1999 | AV81: 2013 | AW81: 2018 | AY81: 2 | AZ81: 2 | BC81: 0 | BD81: 0 | BE81: 0 | BF81: 0 | BG81: 1 | BH81: 1 | BJ81: 1 | BK81: 0 | BL81: 0 | BM81: 0 | BN81: 0 | BO81: 1 | BP81: 1 | BQ81: 1 | BS81: 2 | BT81: 2 | BU81: 2 | BV81: 1 | BW81: 2024 | BX81: 1 | BY81: 3 | BZ81: 0 | CA81: 1 | CB81: 0 | CC81: 0 | CD81: 0 | CE81: 0 | CG81: 3 | CI81: 39.72 | CJ81: 1 | CK81: 2024 | CL81: 1 | CM81: 2 | CN81: 0 | CO81: 1 | CP81: 0 | CQ81: 0 | CR81: 0 | CS81: 0 | CU81: 1 | CW81: 67.55 | CX81: 1 | CY81: 4 | CZ81: 1 | DA81: 2 | DB81: 2 | DC81: 0 | DD81: 1 | DE81: 0 | DF81: 0 | DG81: 0 | DH81: 0 | DJ81: 1 | DL81: 2 | DN81: 2.64 | DO81: 1 | DP81: 5241 | DQ81: 0 | DR81: 5241 | DS81: 0 | DT81: 1891 | DU81: 0 | DV81: 90 | DW81: 1 | DY81: 1 | DZ81: 60000 | EA81: 29 | EB81: 3 | EC81: 4 | ED81: 0 | EE81: 1973 | EF81: 2013 | EH81: 1.76 | EI81: 0.32 | EM81: 3.5 | EU81: 2014 | EV81: 1 | EW81: 1 | EX81: 1 | EZ81: 100 | FD81: 1 | FE81: 5241 | FF81: 0 | FG81: 5241 | FH81: 0 | FI81: 1871 | FK81: 90 | FP81: 11.5 | FQ81: 3 | FR81: 2 | FS81: 2 | FT81: 0 | FU81: 0 | FV81: 0 | FW81: 0 | FX81: 1 | FY81: 1 | GA81: 1970 | GB81: 2002 | GC81: 1.25 | GD81: 2.5 | GF81: 1.54 | GG81: 0.65 | GH81: 95 | GI81: 2030 | GJ81: 2030 | GK81: 2 | GL81: 1 | GN81: City wetland area | GO81: 2 | GQ81: 1 | GR81: 1 | GT81: 1 | GU81: 1891 | GW81: 90 | HA81: 5.5 | HB81: 8.5
A82: Florence | B82: 9598 | C82: 4 | D82: 5 | E82: 1 | G82: 1 | H82: 1 | I82: 1 | J82: 1 | K82: 1 | L82: 1 | M82: 1 | N82: 1 | O82: 1 | P82: 1 | Q82: 0 | R82: 1 | S82: 0 | U82: 6.65 | W82: 21 | Z82: 32 | AB82: 120 | AC82: 2 | AE82: 3 | AF82: 3 | AI82: Commercial water and wastewater are adjusted up to 90 days based on the same methodology used for residential of the average for the past 12 months. Since commercial wastewater is based on water consumption so there is an adjustment to that too. Residential leak adjustments are water only since wastewater is a single base rate. | AJ82: 14.3 | AK82: 20.3 | AL82: 10.5 | AP82: 1 | AQ82: 1 | AR82: 1 | AS82: 2017 | AT82: 2017 | AU82: 2017 | AV82: 2017 | AW82: 2017 | AX82: 2017 | AY82: 2 | AZ82: 2 | BC82: 0 | BD82: 1 | BE82: 0 | BF82: 1 | BG82: 1 | BH82: 0 | BI82: Street Maintenance Fee, Public Safety Fee, Late Fees, NSF Fees | BJ82: 1 | BK82: 0 | BL82: 0 | BM82: 0 | BN82: 0 | BO82: 1 | BP82: 1 | BQ82: 0 | BS82: 2 | BT82: 2 | BU82: 2 | BV82: 1 | BX82: 1 | BY82: 0.05 | BZ82: 0 | CA82: 1 | CB82: 0 | CC82: 0 | CD82: 0 | CE82: 0 | CG82: 1 | CJ82: 1 | CL82: 1 | CM82: 0.05 | CN82: 0 | CO82: 1 | CP82: 0 | CQ82: 0 | CR82: 0 | CS82: 0 | CU82: 4 | CV82: Flat Rate for residential, commercial is based on water consumption | CW82: 63.76 | CX82: 1 | CY82: 8 | CZ82: 1 | DA82: 0.05 | DB82: 2 | DC82: 0 | DD82: 1 | DE82: 0 | DF82: 0 | DG82: 0 | DH82: 0 | DJ82: 1 | DL82: 2 | DO82: 1 | DP82: 9598 | DQ82: 2 | DR82: 12500 | DS82: 2 | DT82: 3508 | DU82: 2 | DV82: 529 | DX82: 215 | EA82: 67.93 | EB82: 3 | EC82: 3 | ED82: 0 | EE82: 1968 | EF82: 2004 | EG82: 3 | EH82: 3 | EI82: 1.302 | EJ82: 95 | EK82: 2.195 | EM82: 4.5 | EU82: Not in current forecast, however, depending on growth between 2040 and 2050 | EV82: 1 | EW82: 1 | EX82: 1 | EZ82: 100 | FD82: 1 | FE82: 9598 | FG82: 12500 | FI82: 3492 | FK82: 456 | FM82: 20 | FO82: 6 | FP82: 71.56 | FQ82: 39 | FR82: 2 | FS82: 2 | FT82: 0 | FU82: 0 | FV82: 0 | FW82: 0 | FX82: 1 | FY82: 1 | GA82: 1960 | GB82: 2025 | GC82: 1.3 | GD82: 6 | GE82: 315.275 | GF82: 1.436 | GG82: 1.09 | GH82: 66 | GI82: 2050 | GJ82: 2035 | GK82: 2 | GL82: 1 | GN82: Reclaimed water used for process and irrigation at the wastewater treatment plant. | GO82: 2 | GQ82: 1 | GR82: 4 | GS82: The 85% goes to Heard Farms outside of Roseburg. The City has a biosolids composting program where we take the biosolids and mix with mulched yard debris, use a covered aerated static pile process to produce a Class A Biosolids product. We compost 15% of the biosolids at the WWTP. | GT82: 1 | GU82: 3517 | GW82: 499 | GY82: 21 | HA82: 34.73 | HB82: 4.5 | HC82: 6500 | HD82: street sweeping is part of stormwater
A83: Beaverton | B83: 100778 | C83: 5 | D83: 2 | E83: 1 | G83: 1 | H83: 1 | I83: 1 | J83: 1 | K83: 1 | L83: 1 | M83: 1 | N83: 1 | O83: 1 | P83: 0 | Q83: 0 | R83: 0 | S83: 0 | Z83: 30 | AB83: 120 | AC83: 1 | AD83: We offer utility billing assistance for customers that meet specific income eligibility guidelines. We have partnered up with the non profit agency Community Action, which handles applications, screening, and approvals for assistance. | AE83: 3 | AF83: 2 | AG83: 365 | AJ83: 0.27 | AK83: 0 | AL83: 0 | AP83: 1 | AQ83: 1 | AR83: 1 | AS83: 2024 | AT83: N/A | AU83: N/A | AV83: 2024 | AW83: N/A | AX83: N/A | AY83: 2 | AZ83: 4 | BB83: The City closes the account, shuts off water and locks the meter to prevent further billing charges until the next occupant requests the meter to be turned back on. | BC83: 0 | BD83: 0 | BE83: 0 | BF83: 0 | BG83: 1 | BH83: 1 | BJ83: 1 | BK83: 0 | BL83: 0 | BM83: 0 | BN83: 0 | BO83: 0 | BP83: 0 | BQ83: 1 | BS83: 2 | BT83: 2 | BU83: 2 | BV83: 1 | BW83: 2025 | BX83: 1 | BZ83: 1 | CA83: 0 | CB83: 1 | CC83: 1 | CD83: 0 | CE83: 1 | CF83: Debt requirements from WIFIA Water Loan | CG83: 4 | CI83: 66.27 | CJ83: 1 | CK83: 2025 | CL83: 1 | CN83: 1 | CO83: 1 | CP83: 1 | CQ83: 1 | CR83: 0 | CS83: 0 | CT83: Rates are set by our partnering agency, Clean Water Services | CU83: 4 | CV83: A fixed rate based on the winter average consumption used in the winter months. | CW83: 54.13 | CX83: 1 | CY83: 7 | CZ83: 1 | DA83: 0.0294 | DB83: 1 | DC83: 1 | DD83: 1 | DE83: 1 | DF83: 1 | DG83: 0 | DH83: 0 | DI83: Rates are set by our partner agency, Clean Water Services | DJ83: 1 | DL83: 1 | DM83: Owner of property has to submit a stormwater exemption application that is reviewed by the City's Engineering Department. To qualify, the onsite system must encompass the entire property and must be completely separate from the public system. The City does not offer partial reductions. This is only related to the SDC charge, not the monthly rate or any other charges. There are no reductions or credits offered for the monthly rate. | DN83: 14 | DO83: 1 | DP83: 99843 | DQ83: 0 | DS83: 0 | DT83: 22316 | DU83: 0 | DV83: 1188 | DW83: 1 | DX83: 965 | DY83: 1 | DZ83: 98097 | EA83: 400 | EB83: 6 | EC83: 10 | ED83: 17 | EE83: 1949 | EF83: 2025 | EG83: 29 | EH83: 31.75 | EI83: 9.57 | EJ83: 0.9 | EK83: 17 | EL83: 7 | EN83: 5 | EO83: 7 | EP83: 7 | EQ83: 3 | ET83: JWC reservoir capacity / City owns | EU83: 10 years | EV83: 1 | EW83: 1 | EX83: 2 | EZ83: 0.25 | FB83: 0.75 | FC83: None | FD83: 1 | FE83: 99843 | FI83: 22316 | FJ83: 12 | FK83: 1188 | FL83: 9 | FM83: 965 | FN83: 5 | FP83: 301 | FR83: 4 | FS83: 3 | FT83: 1 | FU83: 1 | FV83: 0 | FW83: 1 | FX83: 1 | FY83: 1 | GI83: N/A - All plants owned by Clean Water Services | GJ83: N/A - All plants owned by Clean Water Services | GK83: 2 | GL83: 2 | GM83: N/A | GO83: 2 | GQ83: 2 | GS83: None | GT83: 1 | GU83: 22316 | GV83: 4 | GW83: 1188 | GX83: 3 | GY83: 965 | GZ83: 2 | HA83: 258 | HB83: 5.3 miles | HC83: 2640 | HD83: None | HE83: Could you make a printable copy of our submitted responses or offer an option to send the completed survey with responses back to the submitting organization so we can file this completed copy in our records? That would be extremely helpful. Thank you very much.
A84: Beaverton | B84: 100778 | C84: 5 | D84: 2
A85: Redmond | B85: 37146 | C85: 5 | D85: 9 | E85: 1 | G85: 1 | H85: 1 | I85: 1 | J85: 1 | K85: 1 | L85: 1 | M85: 1 | N85: 0 | O85: 1 | P85: 1 | Q85: 0 | R85: 1 | S85: 0 | Z85: 2 | AC85: 1 | AD85: 25% monthly discount from rates for those qualified under HUD income limits. | AE85: 2 | AH85: typically only do adjustment for up to six months when notified, this does not apply to leak, but would apply to wma | AP85: 1 | AQ85: 1 | AR85: 1 | AS85: 2025 | AT85: 2025 | AU85: n/a | AW85: 2025 | AY85: 1 | AZ85: 4 | BB85: owner must stop service if home is going to be vacant | BC85: 1 | BD85: 1 | BE85: 0 | BF85: 1 | BG85: 1 | BH85: 1 | BI85: verbatim is delinquent fee prior to restoring service, hydrant permit fee, wastewater violations | BJ85: 1 | BS85: 2 | BT85: 2 | BU85: 2 | BV85: 1 | BW85: 2025 | BX85: 1 | BY85: 0.03 | BZ85: 1 | CA85: 1 | CB85: 1 | CC85: 0 | CD85: 0 | CE85: 1 | CG85: 5 | CH85: flat rate and uniform rate. | CI85: 35.48 | CJ85: 1 | CK85: 2025 | CL85: 1 | CM85: 0.04 | CN85: 1 | CO85: 1 | CP85: 1 | CQ85: 0 | CR85: 0 | CS85: 1 | CU85: 4 | CV85: flat rate, winter average water consumption used all year and other - winter months average only applies to commercial customers, all others are on flat rate | CW85: 37.03 | CX85: 1 | CY85: 7 | CZ85: 1 | DA85: 0.03 | DB85: 3 | DC85: 1 | DD85: 1 | DE85: 1 | DF85: 0 | DG85: 0 | DH85: 1 | DJ85: 1 | DL85: 2 | DN85: 9.03 | DO85: 1 | EV85: 1 | FD85: 1 | GK85: 1 | GL85: 2 | GS85: The City is in the process of construction a Wetlands Complex to replace the existing Wastewater Pollution Control Facility. | GT85: 1

Sheet Analysis
A1: Water Rates Survey 2025 October 16 2025 10 08
A2: 84 respondents. All ranges cover rows 2-125 of the Cleaned sheet (40 blank rows reserved for growth).
A4: How often are bills issued? - Selected Choice | B4: (Cleaned!E)
B5: Monthly | D5: Bi-Monthly | F5: Quarterly | H5: Other (Please Specify) | J5: Responses
B6: # | C6: % | D6: # | E6: % | F6: # | G6: % | H6: # | I6: %
A7: Quintile
A8: 1st Quintile | B8: =COUNTIFS(Cleaned!$C$2:$C$125,1,Cleaned!E$2:E$125,1) -> 12 | C8: =IFERROR(B8/$J8,"") -> 0.8 | D8: =COUNTIFS(Cleaned!$C$2:$C$125,1,Cleaned!E$2:E$125,2) -> 1 | E8: =IFERROR(D8/$J8,"") -> 0.066666667 | F8: =COUNTIFS(Cleaned!$C$2:$C$125,1,Cleaned!E$2:E$125,3) -> 0 | G8: =IFERROR(F8/$J8,"") -> 0 | H8: =COUNTIFS(Cleaned!$C$2:$C$125,1,Cleaned!E$2:E$125,4) -> 2 | I8: =IFERROR(H8/$J8,"") -> 0.13333333 | J8: =B8+D8+F8+H8 -> 15
A9: 2nd Quintile | B9: =COUNTIFS(Cleaned!$C$2:$C$125,2,Cleaned!E$2:E$125,1) -> 12 | C9: =IFERROR(B9/$J9,"") -> 0.92307692 | D9: =COUNTIFS(Cleaned!$C$2:$C$125,2,Cleaned!E$2:E$125,2) -> 1 | E9: =IFERROR(D9/$J9,"") -> 0.076923077 | F9: =COUNTIFS(Cleaned!$C$2:$C$125,2,Cleaned!E$2:E$125,3) -> 0 | G9: =IFERROR(F9/$J9,"") -> 0 | H9: =COUNTIFS(Cleaned!$C$2:$C$125,2,Cleaned!E$2:E$125,4) -> 0 | I9: =IFERROR(H9/$J9,"") -> 0 | J9: =B9+D9+F9+H9 -> 13
A10: 3rd Quintile | B10: =COUNTIFS(Cleaned!$C$2:$C$125,3,Cleaned!E$2:E$125,1) -> 15 | C10: =IFERROR(B10/$J10,"") -> 0.88235294 | D10: =COUNTIFS(Cleaned!$C$2:$C$125,3,Cleaned!E$2:E$125,2) -> 2 | E10: =IFERROR(D10/$J10,"") -> 0.11764706 | F10: =COUNTIFS(Cleaned!$C$2:$C$125,3,Cleaned!E$2:E$125,3) -> 0 | G10: =IFERROR(F10/$J10,"") -> 0 | H10: =COUNTIFS(Cleaned!$C$2:$C$125,3,Cleaned!E$2:E$125,4) -> 0 | I10: =IFERROR(H10/$J10,"") -> 0 | J10: =B10+D10+F10+H10 -> 17
A11: 4th Quintile | B11: =COUNTIFS(Cleaned!$C$2:$C$125,4,Cleaned!E$2:E$125,1) -> 9 | C11: =IFERROR(B11/$J11,"") -> 0.81818182 | D11: =COUNTIFS(Cleaned!$C$2:$C$125,4,Cleaned!E$2:E$125,2) -> 1 | E11: =IFERROR(D11/$J11,"") -> 0.090909091 | F11: =COUNTIFS(Cleaned!$C$2:$C$125,4,Cleaned!E$2:E$125,3) -> 0 | G11: =IFERROR(F11/$J11,"") -> 0 | H11: =COUNTIFS(Cleaned!$C$2:$C$125,4,Cleaned!E$2:E$125,4) -> 1 | I11: =IFERROR(H11/$J11,"") -> 0.090909091 | J11: =B11+D11+F11+H11 -> 11
A12: 5th Quintile | B12: =COUNTIFS(Cleaned!$C$2:$C$125,5,Cleaned!E$2:E$125,1) -> 17 | C12: =IFERROR(B12/$J12,"") -> 0.73913043 | D12: =COUNTIFS(Cleaned!$C$2:$C$125,5,Cleaned!E$2:E$125,2) -> 4 | E12: =IFERROR(D12/$J12,"") -> 0.17391304 | F12: =COUNTIFS(Cleaned!$C$2:$C$125,5,Cleaned!E$2:E$125,3) -> 1 | G12: =IFERROR(F12/$J12,"") -> 0.043478261 | H12: =COUNTIFS(Cleaned!$C$2:$C$125,5,Cleaned!E$2:E$125,4) -> 1 | I12: =IFERROR(H12/$J12,"") -> 0.043478261 | J12: =B12+D12+F12+H12 -> 23
A13: TOTAL (Quintile) | B13: =SUM(B8:B12) -> 65 | C13: =IFERROR(B13/$J13,"") -> 0.82278481 | D13: =SUM(D8:D12) -> 9 | E13: =IFERROR(D13/$J13,"") -> 0.11392405 | F13: =SUM(F8:F12) -> 1 | G13: =IFERROR(F13/$J13,"") -> 0.012658228 | H13: =SUM(H8:H12) -> 4 | I13: =IFERROR(H13/$J13,"") -> 0.050632911 | J13: =SUM(J8:J12) -> 79
A14: Region
A15: N. Coast | B15: =COUNTIFS(Cleaned!$D$2:$D$125,1,Cleaned!E$2:E$125,1) -> 7 | C15: =IFERROR(B15/$J15,"") -> 0.7 | D15: =COUNTIFS(Cleaned!$D$2:$D$125,1,Cleaned!E$2:E$125,2) -> 3 | E15: =IFERROR(D15/$J15,"") -> 0.3 | F15: =COUNTIFS(Cleaned!$D$2:$D$125,1,Cleaned!E$2:E$125,3) -> 0 | G15: =IFERROR(F15/$J15,"") -> 0 | H15: =COUNTIFS(Cleaned!$D$2:$D$125,1,Cleaned!E$2:E$125,4) -> 0 | I15: =IFERROR(H15/$J15,"") -> 0 | J15: =B15+D15+F15+H15 -> 10
A16: Metro | B16: =COUNTIFS(Cleaned!$D$2:$D$125,2,Cleaned!E$2:E$125,1) -> 11 | C16: =IFERROR(B16/$J16,"") -> 0.6875 | D16: =COUNTIFS(Cleaned!$D$2:$D$125,2,Cleaned!E$2:E$125,2) -> 3 | E16: =IFERROR(D16/$J16,"") -> 0.1875 | F16: =COUNTIFS(Cleaned!$D$2:$D$125,2,Cleaned!E$2:E$125,3) -> 1 | G16: =IFERROR(F16/$J16,"") -> 0.0625 | H16: =COUNTIFS(Cleaned!$D$2:$D$125,2,Cleaned!E$2:E$125,4) -> 1 | I16: =IFERROR(H16/$J16,"") -> 0.0625 | J16: =B16+D16+F16+H16 -> 16
A17: N. Willamette | B17: =COUNTIFS(Cleaned!$D$2:$D$125,3,Cleaned!E$2:E$125,1) -> 8 | C17: =IFERROR(B17/$J17,"") -> 0.8 | D17: =COUNTIFS(Cleaned!$D$2:$D$125,3,Cleaned!E$2:E$125,2) -> 1 | E17: =IFERROR(D17/$J17,"") -> 0.1 | F17: =COUNTIFS(Cleaned!$D$2:$D$125,3,Cleaned!E$2:E$125,3) -> 0 | G17: =IFERROR(F17/$J17,"") -> 0 | H17: =COUNTIFS(Cleaned!$D$2:$D$125,3,Cleaned!E$2:E$125,4) -> 1 | I17: =IFERROR(H17/$J17,"") -> 0.1 | J17: =B17+D17+F17+H17 -> 10
A18: S. Willamette | B18: =COUNTIFS(Cleaned!$D$2:$D$125,4,Cleaned!E$2:E$125,1) -> 5 | C18: =IFERROR(B18/$J18,"") -> 0.83333333 | D18: =COUNTIFS(Cleaned!$D$2:$D$125,4,Cleaned!E$2:E$125,2) -> 1 | E18: =IFERROR(D18/$J18,"") -> 0.16666667 | F18: =COUNTIFS(Cleaned!$D$2:$D$125,4,Cleaned!E$2:E$125,3) -> 0 | G18: =IFERROR(F18/$J18,"") -> 0 | H18: =COUNTIFS(Cleaned!$D$2:$D$125,4,Cleaned!E$2:E$125,4) -> 0 | I18: =IFERROR(H18/$J18,"") -> 0 | J18: =B18+D18+F18+H18 -> 6
A19: C. Coast | B19: =COUNTIFS(Cleaned!$D$2:$D$125,5,Cleaned!E$2:E$125,1) -> 1 | C19: =IFERROR(B19/$J19,"") -> 1 | D19: =COUNTIFS(Cleaned!$D$2:$D$125,5,Cleaned!E$2:E$125,2) -> 0 | E19: =IFERROR(D19/$J19,"") -> 0 | F19: =COUNTIFS(Cleaned!$D$2:$D$125,5,Cleaned!E$2:E$125,3) -> 0 | G19: =IFERROR(F19/$J19,"") -> 0 | H19: =COUNTIFS(Cleaned!$D$2:$D$125,5,Cleaned!E$2:E$125,4) -> 0 | I19: =IFERROR(H19/$J19,"") -> 0 | J19: =B19+D19+F19+H19 -> 1
A20: S. Coast | B20: =COUNTIFS(Cleaned!$D$2:$D$125,6,Cleaned!E$2:E$125,1) -> 3 | C20: =IFERROR(B20/$J20,"") -> 1 | D20: =COUNTIFS(Cleaned!$D$2:$D$125,6,Cleaned!E$2:E$125,2) -> 0 | E20: =IFERROR(D20/$J20,"") -> 0 | F20: =COUNTIFS(Cleaned!$D$2:$D$125,6,Cleaned!E$2:E$125,3) -> 0 | G20: =IFERROR(F20/$J20,"") -> 0 | H20: =COUNTIFS(Cleaned!$D$2:$D$125,6,Cleaned!E$2:E$125,4) -> 0 | I20: =IFERROR(H20/$J20,"") -> 0 | J20: =B20+D20+F20+H20 -> 3
A21: S. Oregon | B21: =COUNTIFS(Cleaned!$D$2:$D$125,7,Cleaned!E$2:E$125,1) -> 8 | C21: =IFERROR(B21/$J21,"") -> 0.88888889 | D21: =COUNTIFS(Cleaned!$D$2:$D$125,7,Cleaned!E$2:E$125,2) -> 0 | E21: =IFERROR(D21/$J21,"") -> 0 | F21: =COUNTIFS(Cleaned!$D$2:$D$125,7,Cleaned!E$2:E$125,3) -> 0 | G21: =IFERROR(F21/$J21,"") -> 0 | H21: =COUNTIFS(Cleaned!$D$2:$D$125,7,Cleaned!E$2:E$125,4) -> 1 | I21: =IFERROR(H21/$J21,"") -> 0.11111111 | J21: =B21+D21+F21+H21 -> 9
A22: Gorge | B22: =COUNTIFS(Cleaned!$D$2:$D$125,8,Cleaned!E$2:E$125,1) -> 3 | C22: =IFERROR(B22/$J22,"") -> 0.75 | D22: =COUNTIFS(Cleaned!$D$2:$D$125,8,Cleaned!E$2:E$125,2) -> 0 | E22: =IFERROR(D22/$J22,"") -> 0 | F22: =COUNTIFS(Cleaned!$D$2:$D$125,8,Cleaned!E$2:E$125,3) -> 0 | G22: =IFERROR(F22/$J22,"") -> 0 | H22: =COUNTIFS(Cleaned!$D$2:$D$125,8,Cleaned!E$2:E$125,4) -> 1 | I22: =IFERROR(H22/$J22,"") -> 0.25 | J22: =B22+D22+F22+H22 -> 4
A23: C. Oregon | B23: =COUNTIFS(Cleaned!$D$2:$D$125,9,Cleaned!E$2:E$125,1) -> 2 | C23: =IFERROR(B23/$J23,"") -> 1 | D23: =COUNTIFS(Cleaned!$D$2:$D$125,9,Cleaned!E$2:E$125,2) -> 0 | E23: =IFERROR(D23/$J23,"") -> 0 | F23: =COUNTIFS(Cleaned!$D$2:$D$125,9,Cleaned!E$2:E$125,3) -> 0 | G23: =IFERROR(F23/$J23,"") -> 0 | H23: =COUNTIFS(Cleaned!$D$2:$D$125,9,Cleaned!E$2:E$125,4) -> 0 | I23: =IFERROR(H23/$J23,"") -> 0 | J23: =B23+D23+F23+H23 -> 2
A24: SC Oregon | B24: =COUNTIFS(Cleaned!$D$2:$D$125,10,Cleaned!E$2:E$125,1) -> 1 | C24: =IFERROR(B24/$J24,"") -> 0.5 | D24: =COUNTIFS(Cleaned!$D$2:$D$125,10,Cleaned!E$2:E$125,2) -> 1 | E24: =IFERROR(D24/$J24,"") -> 0.5 | F24: =COUNTIFS(Cleaned!$D$2:$D$125,10,Cleaned!E$2:E$125,3) -> 0 | G24: =IFERROR(F24/$J24,"") -> 0 | H24: =COUNTIFS(Cleaned!$D$2:$D$125,10,Cleaned!E$2:E$125,4) -> 0 | I24: =IFERROR(H24/$J24,"") -> 0 | J24: =B24+D24+F24+H24 -> 2
A25: NE Oregon | B25: =COUNTIFS(Cleaned!$D$2:$D$125,11,Cleaned!E$2:E$125,1) -> 11 | C25: =IFERROR(B25/$J25,"") -> 1 | D25: =COUNTIFS(Cleaned!$D$2:$D$125,11,Cleaned!E$2:E$125,2) -> 0 | E25: =IFERROR(D25/$J25,"") -> 0 | F25: =COUNTIFS(Cleaned!$D$2:$D$125,11,Cleaned!E$2:E$125,3) -> 0 | G25: =IFERROR(F25/$J25,"") -> 0 | H25: =COUNTIFS(Cleaned!$D$2:$D$125,11,Cleaned!E$2:E$125,4) -> 0 | I25: =IFERROR(H25/$J25,"") -> 0 | J25: =B25+D25+F25+H25 -> 11
A26: E. Oregon | B26: =COUNTIFS(Cleaned!$D$2:$D$125,12,Cleaned!E$2:E$125,1) -> 5 | C26: =IFERROR(B26/$J26,"") -> 1 | D26: =COUNTIFS(Cleaned!$D$2:$D$125,12,Cleaned!E$2:E$125,2) -> 0 | E26: =IFERROR(D26/$J26,"") -> 0 | F26: =COUNTIFS(Cleaned!$D$2:$D$125,12,Cleaned!E$2:E$125,3) -> 0 | G26: =IFERROR(F26/$J26,"") -> 0 | H26: =COUNTIFS(Cleaned!$D$2:$D$125,12,Cleaned!E$2:E$125,4) -> 0 | I26: =IFERROR(H26/$J26,"") -> 0 | J26: =B26+D26+F26+H26 -> 5
A27: TOTAL (Region) | B27: =SUM(B15:B26) -> 65 | C27: =IFERROR(B27/$J27,"") -> 0.82278481 | D27: =SUM(D15:D26) -> 9 | E27: =IFERROR(D27/$J27,"") -> 0.11392405 | F27: =SUM(F15:F26) -> 1 | G27: =IFERROR(F27/$J27,"") -> 0.012658228 | H27: =SUM(H15:H26) -> 4 | I27: =IFERROR(H27/$J27,"") -> 0.050632911 | J27: =SUM(J15:J26) -> 79
A30: What methods of payment are accepted? (Check all that apply) [Cash] | B30: (Cleaned!G)
B31: Not selected | D31: Selected | F31: Responses
B32: # | C32: % | D32: # | E32: %
A33: Quintile
A34: 1st Quintile | B34: =COUNTIFS(Cleaned!$C$2:$C$125,1,Cleaned!G$2:G$125,0) -> 0 | C34: =IFERROR(B34/$F34,"") -> 0 | D34: =COUNTIFS(Cleaned!$C$2:$C$125,1,Cleaned!G$2:G$125,1) -> 15 | E34: =IFERROR(D34/$F34,"") -> 1 | F34: =B34+D34 -> 15
A35: 2nd Quintile | B35: =COUNTIFS(Cleaned!$C$2:$C$125,2,Cleaned!G$2:G$125,0) -> 0 | C35: =IFERROR(B35/$F35,"") -> 0 | D35: =COUNTIFS(Cleaned!$C$2:$C$125,2,Cleaned!G$2:G$125,1) -> 13 | E35: =IFERROR(D35/$F35,"") -> 1 | F35: =B35+D35 -> 13
A36: 3rd Quintile | B36: =COUNTIFS(Cleaned!$C$2:$C$125,3,Cleaned!G$2:G$125,0) -> 0 | C36: =IFERROR(B36/$F36,"") -> 0 | D36: =COUNTIFS(Cleaned!$C$2:$C$125,3,Cleaned!G$2:G$125,1) -> 17 | E36: =IFERROR(D36/$F36,"") -> 1 | F36: =B36+D36 -> 17
A37: 4th Quintile | B37: =COUNTIFS(Cleaned!$C$2:$C$125,4,Cleaned!G$2:G$125,0) -> 1 | C37: =IFERROR(B37/$F37,"") -> 0.090909091 | D37: =COUNTIFS(Cleaned!$C$2:$C$125,4,Cleaned!G$2:G$125,1) -> 10 | E37: =IFERROR(D37/$F37,"") -> 0.90909091 | F37: =B37+D37 -> 11
A38: 5th Quintile | B38: =COUNTIFS(Cleaned!$C$2:$C$125,5,Cleaned!G$2:G$125,0) -> 0 | C38: =IFERROR(B38/$F38,"") -> 0 | D38: =COUNTIFS(Cleaned!$C$2:$C$125,5,Cleaned!G$2:G$125,1) -> 22 | E38: =IFERROR(D38/$F38,"") -> 1 | F38: =B38+D38 -> 22
A39: TOTAL (Quintile) | B39: =SUM(B34:B38) -> 1 | C39: =IFERROR(B39/$F39,"") -> 0.012820513 | D39: =SUM(D34:D38) -> 77 | E39: =IFERROR(D39/$F39,"") -> 0.98717949 | F39: =SUM(F34:F38) -> 78
A40: Region
A41: N. Coast | B41: =COUNTIFS(Cleaned!$D$2:$D$125,1,Cleaned!G$2:G$125,0) -> 0 | C41: =IFERROR(B41/$F41,"") -> 0 | D41: =COUNTIFS(Cleaned!$D$2:$D$125,1,Cleaned!G$2:G$125,1) -> 10 | E41: =IFERROR(D41/$F41,"") -> 1 | F41: =B41+D41 -> 10
A42: Metro | B42: =COUNTIFS(Cleaned!$D$2:$D$125,2,Cleaned!G$2:G$125,0) -> 1 | C42: =IFERROR(B42/$F42,"") -> 0.066666667 | D42: =COUNTIFS(Cleaned!$D$2:$D$125,2,Cleaned!G$2:G$125,1) -> 14 | E42: =IFERROR(D42/$F42,"") -> 0.93333333 | F42: =B42+D42 -> 15
A43: N. Willamette | B43: =COUNTIFS(Cleaned!$D$2:$D$125,3,Cleaned!G$2:G$125,0) -> 0 | C43: =IFERROR(B43/$F43,"") -> 0 | D43: =COUNTIFS(Cleaned!$D$2:$D$125,3,Cleaned!G$2:G$125,1) -> 10 | E43: =IFERROR(D43/$F43,"") -> 1 | F43: =B43+D43 -> 10
A44: S. Willamette | B44: =COUNTIFS(Cleaned!$D$2:$D$125,4,Cleaned!G$2:G$125,0) -> 0 | C44: =IFERROR(B44/$F44,"") -> 0 | D44: =COUNTIFS(Cleaned!$D$2:$D$125,4,Cleaned!G$2:G$125,1) -> 6 | E44: =IFERROR(D44/$F44,"") -> 1 | F44: =B44+D44 -> 6
A45: C. Coast | B45: =COUNTIFS(Cleaned!$D$2:$D$125,5,Cleaned!G$2:G$125,0) -> 0 | C45: =IFERROR(B45/$F45,"") -> 0 | D45: =COUNTIFS(Cleaned!$D$2:$D$125,5,Cleaned!G$2:G$125,1) -> 1 | E45: =IFERROR(D45/$F45,"") -> 1 | F45: =B45+D45 -> 1
A46: S. Coast | B46: =COUNTIFS(Cleaned!$D$2:$D$125,6,Cleaned!G$2:G$125,0) -> 0 | C46: =IFERROR(B46/$F46,"") -> 0 | D46: =COUNTIFS(Cleaned!$D$2:$D$125,6,Cleaned!G$2:G$125,1) -> 3 | E46: =IFERROR(D46/$F46,"") -> 1 | F46: =B46+D46 -> 3
A47: S. Oregon | B47: =COUNTIFS(Cleaned!$D$2:$D$125,7,Cleaned!G$2:G$125,0) -> 0 | C47: =IFERROR(B47/$F47,"") -> 0 | D47: =COUNTIFS(Cleaned!$D$2:$D$125,7,Cleaned!G$2:G$125,1) -> 9 | E47: =IFERROR(D47/$F47,"") -> 1 | F47: =B47+D47 -> 9
A48: Gorge | B48: =COUNTIFS(Cleaned!$D$2:$D$125,8,Cleaned!G$2:G$125,0) -> 0 | C48: =IFERROR(B48/$F48,"") -> 0 | D48: =COUNTIFS(Cleaned!$D$2:$D$125,8,Cleaned!G$2:G$125,1) -> 4 | E48: =IFERROR(D48/$F48,"") -> 1 | F48: =B48+D48 -> 4
A49: C. Oregon | B49: =COUNTIFS(Cleaned!$D$2:$D$125,9,Cleaned!G$2:G$125,0) -> 0 | C49: =IFERROR(B49/$F49,"") -> 0 | D49: =COUNTIFS(Cleaned!$D$2:$D$125,9,Cleaned!G$2:G$125,1) -> 2 | E49: =IFERROR(D49/$F49,"") -> 1 | F49: =B49+D49 -> 2
A50: SC Oregon | B50: =COUNTIFS(Cleaned!$D$2:$D$125,10,Cleaned!G$2:G$125,0) -> 0 | C50: =IFERROR(B50/$F50,"") -> 0 | D50: =COUNTIFS(Cleaned!$D$2:$D$125,10,Cleaned!G$2:G$125,1) -> 2 | E50: =IFERROR(D50/$F50,"") -> 1 | F50: =B50+D50 -> 2
A51: NE Oregon | B51: =COUNTIFS(Cleaned!$D$2:$D$125,11,Cleaned!G$2:G$125,0) -> 0 | C51: =IFERROR(B51/$F51,"") -> 0 | D51: =COUNTIFS(Cleaned!$D$2:$D$125,11,Cleaned!G$2:G$125,1) -> 11 | E51: =IFERROR(D51/$F51,"") -> 1 | F51: =B51+D51 -> 11
A52: E. Oregon | B52: =COUNTIFS(Cleaned!$D$2:$D$125,12,Cleaned!G$2:G$125,0) -> 0 | C52: =IFERROR(B52/$F52,"") -> 0 | D52: =COUNTIFS(Cleaned!$D$2:$D$125,12,Cleaned!G$2:G$125,1) -> 5 | E52: =IFERROR(D52/$F52,"") -> 1 | F52: =B52+D52 -> 5
A53: TOTAL (Region) | B53: =SUM(B41:B52) -> 1 | C53: =IFERROR(B53/$F53,"") -> 0.012820513 | D53: =SUM(D41:D52) -> 77 | E53: =IFERROR(D53/$F53,"") -> 0.98717949 | F53: =SUM(F41:F52) -> 78
A56: What methods of payment are accepted? (Check all that apply) [Check] | B56: (Cleaned!H)
B57: Not selected | D57: Selected | F57: Responses
B58: # | C58: % | D58: # | E58: %
A59: Quintile
A60: 1st Quintile | B60: =COUNTIFS(Cleaned!$C$2:$C$125,1,Cleaned!H$2:H$125,0) -> 0 | C60: =IFERROR(B60/$F60,"") -> 0 | D60: =COUNTIFS(Cleaned!$C$2:$C$125,1,Cleaned!H$2:H$125,1) -> 15 | E60: =IFERROR(D60/$F60,"") -> 1 | F60: =B60+D60 -> 15
A61: 2nd Quintile | B61: =COUNTIFS(Cleaned!$C$2:$C$125,2,Cleaned!H$2:H$125,0) -> 0 | C61: =IFERROR(B61/$F61,"") -> 0 | D61: =COUNTIFS(Cleaned!$C$2:$C$125,2,Cleaned!H$2:H$125,1) -> 13 | E61: =IFERROR(D61/$F61,"") -> 1 | F61: =B61+D61 -> 13
A62: 3rd Quintile | B62: =COUNTIFS(Cleaned!$C$2:$C$125,3,Cleaned!H$2:H$125,0) -> 0 | C62: =IFERROR(B62/$F62,"") -> 0 | D62: =COUNTIFS(Cleaned!$C$2:$C$125,3,Cleaned!H$2:H$125,1) -> 17 | E62: =IFERROR(D62/$F62,"") -> 1 | F62: =B62+D62 -> 17
A63: 4th Quintile | B63: =COUNTIFS(Cleaned!$C$2:$C$125,4,Cleaned!H$2:H$125,0) -> 0 | C63: =IFERROR(B63/$F63,"") -> 0 | D63: =COUNTIFS(Cleaned!$C$2:$C$125,4,Cleaned!H$2:H$125,1) -> 11 | E63: =IFERROR(D63/$F63,"") -> 1 | F63: =B63+D63 -> 11
A64: 5th Quintile | B64: =COUNTIFS(Cleaned!$C$2:$C$125,5,Cleaned!H$2:H$125,0) -> 0 | C64: =IFERROR(B64/$F64,"") -> 0 | D64: =COUNTIFS(Cleaned!$C$2:$C$125,5,Cleaned!H$2:H$125,1) -> 22 | E64: =IFERROR(D64/$F64,"") -> 1 | F64: =B64+D64 -> 22
A65: TOTAL (Quintile) | B65: =SUM(B60:B64) -> 0 | C65: =IFERROR(B65/$F65,"") -> 0 | D65: =SUM(D60:D64) -> 78 | E65: =IFERROR(D65/$F65,"") -> 1 | F65: =SUM(F60:F64) -> 78
A66: Region
A67: N. Coast | B67: =COUNTIFS(Cleaned!$D$2:$D$125,1,Cleaned!H$2:H$125,0) -> 0 | C67: =IFERROR(B67/$F67,"") -> 0 | D67: =COUNTIFS(Cleaned!$D$2:$D$125,1,Cleaned!H$2:H$125,1) -> 10 | E67: =IFERROR(D67/$F67,"") -> 1 | F67: =B67+D67 -> 10
A68: Metro | B68: =COUNTIFS(Cleaned!$D$2:$D$125,2,Cleaned!H$2:H$125,0) -> 0 | C68: =IFERROR(B68/$F68,"") -> 0 | D68: =COUNTIFS(Cleaned!$D$2:$D$125,2,Cleaned!H$2:H$125,1) -> 15 | E68: =IFERROR(D68/$F68,"") -> 1 | F68: =B68+D68 -> 15
A69: N. Willamette | B69: =COUNTIFS(Cleaned!$D$2:$D$125,3,Cleaned!H$2:H$125,0) -> 0 | C69: =IFERROR(B69/$F69,"") -> 0 | D69: =COUNTIFS(Cleaned!$D$2:$D$125,3,Cleaned!H$2:H$125,1) -> 10 | E69: =IFERROR(D69/$F69,"") -> 1 | F69: =B69+D69 -> 10
A70: S. Willamette | B70: =COUNTIFS(Cleaned!$D$2:$D$125,4,Cleaned!H$2:H$125,0) -> 0 | C70: =IFERROR(B70/$F70,"") -> 0 | D70: =COUNTIFS(Cleaned!$D$2:$D$125,4,Cleaned!H$2:H$125,1) -> 6 | E70: =IFERROR(D70/$F70,"") -> 1 | F70: =B70+D70 -> 6
A71: C. Coast | B71: =COUNTIFS(Cleaned!$D$2:$D$125,5,Cleaned!H$2:H$125,0) -> 0 | C71: =IFERROR(B71/$F71,"") -> 0 | D71: =COUNTIFS(Cleaned!$D$2:$D$125,5,Cleaned!H$2:H$125,1) -> 1 | E71: =IFERROR(D71/$F71,"") -> 1 | F71: =B71+D71 -> 1
A72: S. Coast | B72: =COUNTIFS(Cleaned!$D$2:$D$125,6,Cleaned!H$2:H$125,0) -> 0 | C72: =IFERROR(B72/$F72,"") -> 0 | D72: =COUNTIFS(Cleaned!$D$2:$D$125,6,Cleaned!H$2:H$125,1) -> 3 | E72: =IFERROR(D72/$F72,"") -> 1 | F72: =B72+D72 -> 3
A73: S. Oregon | B73: =COUNTIFS(Cleaned!$D$2:$D$125,7,Cleaned!H$2:H$125,0) -> 0 | C73: =IFERROR(B73/$F73,"") -> 0 | D73: =COUNTIFS(Cleaned!$D$2:$D$125,7,Cleaned!H$2:H$125,1) -> 9 | E73: =IFERROR(D73/$F73,"") -> 1 | F73: =B73+D73 -> 9
A74: Gorge | B74: =COUNTIFS(Cleaned!$D$2:$D$125,8,Cleaned!H$2:H$125,0) -> 0 | C74: =IFERROR(B74/$F74,"") -> 0 | D74: =COUNTIFS(Cleaned!$D$2:$D$125,8,Cleaned!H$2:H$125,1) -> 4 | E74: =IFERROR(D74/$F74,"") -> 1 | F74: =B74+D74 -> 4
A75: C. Oregon | B75: =COUNTIFS(Cleaned!$D$2:$D$125,9,Cleaned!H$2:H$125,0) -> 0 | C75: =IFERROR(B75/$F75,"") -> 0 | D75: =COUNTIFS(Cleaned!$D$2:$D$125,9,Cleaned!H$2:H$125,1) -> 2 | E75: =IFERROR(D75/$F75,"") -> 1 | F75: =B75+D75 -> 2
A76: SC Oregon | B76: =COUNTIFS(Cleaned!$D$2:$D$125,10,Cleaned!H$2:H$125,0) -> 0 | C76: =IFERROR(B76/$F76,"") -> 0 | D76: =COUNTIFS(Cleaned!$D$2:$D$125,10,Cleaned!H$2:H$125,1) -> 2 | E76: =IFERROR(D76/$F76,"") -> 1 | F76: =B76+D76 -> 2
A77: NE Oregon | B77: =COUNTIFS(Cleaned!$D$2:$D$125,11,Cleaned!H$2:H$125,0) -> 0 | C77: =IFERROR(B77/$F77,"") -> 0 | D77: =COUNTIFS(Cleaned!$D$2:$D$125,11,Cleaned!H$2:H$125,1) -> 11 | E77: =IFERROR(D77/$F77,"") -> 1 | F77: =B77+D77 -> 11
A78: E. Oregon | B78: =COUNTIFS(Cleaned!$D$2:$D$125,12,Cleaned!H$2:H$125,0) -> 0 | C78: =IFERROR(B78/$F78,"") -> 0 | D78: =COUNTIFS(Cleaned!$D$2:$D$125,12,Cleaned!H$2:H$125,1) -> 5 | E78: =IFERROR(D78/$F78,"") -> 1 | F78: =B78+D78 -> 5
A79: TOTAL (Region) | B79: =SUM(B67:B78) -> 0 | C79: =IFERROR(B79/$F79,"") -> 0 | D79: =SUM(D67:D78) -> 78 | E79: =IFERROR(D79/$F79,"") -> 1 | F79: =SUM(F67:F78) -> 78
A82: What methods of payment are accepted? (Check all that apply) [Credit/Debit] | B82: (Cleaned!I)
B83: Not selected | D83: Selected | F83: Responses
B84: # | C84: % | D84: # | E84: %
A85: Quintile
A86: 1st Quintile | B86: =COUNTIFS(Cleaned!$C$2:$C$125,1,Cleaned!I$2:I$125,0) -> 5 | C86: =IFERROR(B86/$F86,"") -> 0.33333333 | D86: =COUNTIFS(Cleaned!$C$2:$C$125,1,Cleaned!I$2:I$125,1) -> 10 | E86: =IFERROR(D86/$F86,"") -> 0.66666667 | F86: =B86+D86 -> 15
A87: 2nd Quintile | B87: =COUNTIFS(Cleaned!$C$2:$C$125,2,Cleaned!I$2:I$125,0) -> 1 | C87: =IFERROR(B87/$F87,"") -> 0.076923077 | D87: =COUNTIFS(Cleaned!$C$2:$C$125,2,Cleaned!I$2:I$125,1) -> 12 | E87: =IFERROR(D87/$F87,"") -> 0.92307692 | F87: =B87+D87 -> 13
A88: 3rd Quintile | B88: =COUNTIFS(Cleaned!$C$2:$C$125,3,Cleaned!I$2:I$125,0) -> 1 | C88: =IFERROR(B88/$F88,"") -> 0.058823529 | D88: =COUNTIFS(Cleaned!$C$2:$C$125,3,Cleaned!I$2:I$125,1) -> 16 | E88: =IFERROR(D88/$F88,"") -> 0.94117647 | F88: =B88+D88 -> 17
A89: 4th Quintile | B89: =COUNTIFS(Cleaned!$C$2:$C$125,4,Cleaned!I$2:I$125,0) -> 0 | C89: =IFERROR(B89/$F89,"") -> 0 | D89: =COUNTIFS(Cleaned!$C$2:$C$125,4,Cleaned!I$2:I$125,1) -> 11 | E89: =IFERROR(D89/$F89,"") -> 1 | F89: =B89+D89 -> 11
A90: 5th Quintile | B90: =COUNTIFS(Cleaned!$C$2:$C$125,5,Cleaned!I$2:I$125,0) -> 0 | C90: =IFERROR(B90/$F90,"") -> 0 | D90: =COUNTIFS(Cleaned!$C$2:$C$125,5,Cleaned!I$2:I$125,1) -> 22 | E90: =IFERROR(D90/$F90,"") -> 1 | F90: =B90+D90 -> 22
A91: TOTAL (Quintile) | B91: =SUM(B86:B90) -> 7 | C91: =IFERROR(B91/$F91,"") -> 0.08974359 | D91: =SUM(D86:D90) -> 71 | E91: =IFERROR(D91/$F91,"") -> 0.91025641 | F91: =SUM(F86:F90) -> 78
A92: Region
A93: N. Coast | B93: =COUNTIFS(Cleaned!$D$2:$D$125,1,Cleaned!I$2:I$125,0) -> 1 | C93: =IFERROR(B93/$F93,"") -> 0.1 | D93: =COUNTIFS(Cleaned!$D$2:$D$125,1,Cleaned!I$2:I$125,1) -> 9 | E93: =IFERROR(D93/$F93,"") -> 0.9 | F93: =B93+D93 -> 10
A94: Metro | B94: =COUNTIFS(Cleaned!$D$2:$D$125,2,Cleaned!I$2:I$125,0) -> 0 | C94: =IFERROR(B94/$F94,"") -> 0 | D94: =COUNTIFS(Cleaned!$D$2:$D$125,2,Cleaned!I$2:I$125,1) -> 15 | E94: =IFERROR(D94/$F94,"") -> 1 | F94: =B94+D94 -> 15
A95: N. Willamette | B95: =COUNTIFS(Cleaned!$D$2:$D$125,3,Cleaned!I$2:I$125,0) -> 1 | C95: =IFERROR(B95/$F95,"") -> 0.1 | D95: =COUNTIFS(Cleaned!$D$2:$D$125,3,Cleaned!I$2:I$125,1) -> 9 | E95: =IFERROR(D95/$F95,"") -> 0.9 | F95: =B95+D95 -> 10
A96: S. Willamette | B96: =COUNTIFS(Cleaned!$D$2:$D$125,4,Cleaned!I$2:I$125,0) -> 0 | C96: =IFERROR(B96/$F96,"") -> 0 | D96: =COUNTIFS(Cleaned!$D$2:$D$125,4,Cleaned!I$2:I$125,1) -> 6 | E96: =IFERROR(D96/$F96,"") -> 1 | F96: =B96+D96 -> 6
A97: C. Coast | B97: =COUNTIFS(Cleaned!$D$2:$D$125,5,Cleaned!I$2:I$125,0) -> 0 | C97: =IFERROR(B97/$F97,"") -> 0 | D97: =COUNTIFS(Cleaned!$D$2:$D$125,5,Cleaned!I$2:I$125,1) -> 1 | E97: =IFERROR(D97/$F97,"") -> 1 | F97: =B97+D97 -> 1
A98: S. Coast | B98: =COUNTIFS(Cleaned!$D$2:$D$125,6,Cleaned!I$2:I$125,0) -> 0 | C98: =IFERROR(B98/$F98,"") -> 0 | D98: =COUNTIFS(Cleaned!$D$2:$D$125,6,Cleaned!I$2:I$125,1) -> 3 | E98: =IFERROR(D98/$F98,"") -> 1 | F98: =B98+D98 -> 3
A99: S. Oregon | B99: =COUNTIFS(Cleaned!$D$2:$D$125,7,Cleaned!I$2:I$125,0) -> 1 | C99: =IFERROR(B99/$F99,"") -> 0.11111111 | D99: =COUNTIFS(Cleaned!$D$2:$D$125,7,Cleaned!I$2:I$125,1) -> 8 | E99: =IFERROR(D99/$F99,"") -> 0.88888889 | F99: =B99+D99 -> 9
A100: Gorge | B100: =COUNTIFS(Cleaned!$D$2:$D$125,8,Cleaned!I$2:I$125,0) -> 1 | C100: =IFERROR(B100/$F100,"") -> 0.25 | D100: =COUNTIFS(Cleaned!$D$2:$D$125,8,Cleaned!I$2:I$125,1) -> 3 | E100: =IFERROR(D100/$F100,"") -> 0.75 | F100: =B100+D100 -> 4
A101: C. Oregon | B101: =COUNTIFS(Cleaned!$D$2:$D$125,9,Cleaned!I$2:I$125,0) -> 1 | C101: =IFERROR(B101/$F101,"") -> 0.5 | D101: =COUNTIFS(Cleaned!$D$2:$D$125,9,Cleaned!I$2:I$125,1) -> 1 | E101: =IFERROR(D101/$F101,"") -> 0.5 | F101: =B101+D101 -> 2
A102: SC Oregon | B102: =COUNTIFS(Cleaned!$D$2:$D$125,10,Cleaned!I$2:I$125,0) -> 0 | C102: =IFERROR(B102/$F102,"") -> 0 | D102: =COUNTIFS(Cleaned!$D$2:$D$125,10,Cleaned!I$2:I$125,1) -> 2 | E102: =IFERROR(D102/$F102,"") -> 1 | F102: =B102+D102 -> 2
A103: NE Oregon | B103: =COUNTIFS(Cleaned!$D$2:$D$125,11,Cleaned!I$2:I$125,0) -> 1 | C103: =IFERROR(B103/$F103,"") -> 0.090909091 | D103: =COUNTIFS(Cleaned!$D$2:$D$125,11,Cleaned!I$2:I$125,1) -> 10 | E103: =IFERROR(D103/$F103,"") -> 0.90909091 | F103: =B103+D103 -> 11
A104: E. Oregon | B104: =COUNTIFS(Cleaned!$D$2:$D$125,12,Cleaned!I$2:I$125,0) -> 1 | C104: =IFERROR(B104/$F104,"") -> 0.2 | D104: =COUNTIFS(Cleaned!$D$2:$D$125,12,Cleaned!I$2:I$125,1) -> 4 | E104: =IFERROR(D104/$F104,"") -> 0.8 | F104: =B104+D104 -> 5
A105: TOTAL (Region) | B105: =SUM(B93:B104) -> 7 | C105: =IFERROR(B105/$F105,"") -> 0.08974359 | D105: =SUM(D93:D104) -> 71 | E105: =IFERROR(D105/$F105,"") -> 0.91025641 | F105: =SUM(F93:F104) -> 78
A108: What methods of payment are accepted? (Check all that apply) [Direct Deposit] | B108: (Cleaned!J)
B109: Not selected | D109: Selected | F109: Responses
...

Sheet Validation
A1: Validation
A2: Every check must read OK. A FAIL means a number on the Analysis sheet disagrees with the same quantity computed independently.
A4: Check | B4: Expected | C4: Actual | D4: Result
A5: Respondent rows on Cleaned sheet | B5: 84 | C5: =COUNTA(Cleaned!$A$2:$A$125) -> 84 | D5: =IF(B5=C5,"OK","FAIL") -> OK
A6: Rows with a quintile in 1-5 | B6: 84 | C6: =COUNTIFS(Cleaned!$C$2:$C$125,">=1",Cleaned!$C$2:$C$125,"<=5") -> 84 | D6: =IF(B6=C6,"OK","FAIL") -> OK
A7: Rows with a region in 1-12 | B7: 84 | C7: =COUNTIFS(Cleaned!$D$2:$D$125,">=1",Cleaned!$D$2:$D$125,"<=12") -> 84 | D7: =IF(B7=C7,"OK","FAIL") -> OK
A8: Quintiles 1-5 sum to the respondent count | B8: 84 | C8: =COUNTIF(Cleaned!$C$2:$C$125,1)+COUNTIF(Cleaned!$C$2:$C$125,2)+COUNTIF(Cleaned!$C$2:$C$125,3)+COUNTIF(Cleaned!$C$2:$C$125,4)+COUNTIF(Cleaned!$C$2:$C$125,5) -> 84 | D8: =IF(B8=C8,"OK","FAIL") -> OK
A9: Regions 1-12 sum to the respondent count | B9: 84 | C9: =COUNTIF(Cleaned!$D$2:$D$125,1)+COUNTIF(Cleaned!$D$2:$D$125,2)+COUNTIF(Cleaned!$D$2:$D$125,3)+COUNTIF(Cleaned!$D$2:$D$125,4)+COUNTIF(Cleaned!$D$2:$D$125,5)+COUNTIF(Cleaned!$D$2:$D$125,6)+COUNTIF(Cleaned!$D$2:$D$125,7)+COUNTIF(Cleaned!$D$2:$D$125,8)+COUNTIF(Cleaned!$D$2:$D$125,9)+COUNTIF(Cleaned!$D$2:$D$125,10)+COUNTIF(Cleaned!$D$2:$D$125,11)+COUNTIF(Cleaned!$D$2:$D$125,12) -> 84 | D9: =IF(B9=C9,"OK","FAIL") -> OK
A10: Rows where population is blank | B10: 0 | C10: =COUNTBLANK(Cleaned!$B$2:$B$85) -> 0 | D10: =IF(B10=C10,"OK","FAIL") -> OK
A11: Crosstab totals agree: How often are bills issued? - Selected Choic | B11: =COUNTIFS(Cleaned!$C$2:$C$125,1,Cleaned!$E$2:$E$125,1)+COUNTIFS(Cleaned!$C$2:$C$125,1,Cleaned!$E$2:$E$125,2)+COUNTIFS(Cleaned!$C$2:$C$125,1,Cleaned!$E$2:$E$125,3)+COUNTIFS(Cleaned!$C$2:$C$125,1,Cleaned!$E$2:$E$125,4)+COUNTIFS(Cleaned!$C$2:$C$125,2,Cleaned!$E$2:$E$125,1)+COUNTIFS(Cleaned!$C$2:$C$125,2,Cleaned!$E$2:$E$125,2)+COUNTIFS(Cleaned!$C$2:$C$125,2,Cleaned!$E$2:$E$125,3)+COUNTIFS(Cleaned!$C$2:$C$125,2,Cleaned!$E$2:$E$125,4)+COUNTIFS(Cleaned!$C$2:$C$125,3,Cleaned!$E$2:$E$125,1)+COUNTIFS(Cleaned!$C$2:$C$125,3,Cleaned!$E$2:$E$125,2)+COUNTIFS(Cleaned!$C$2:$C$125,3,Cleaned!$E$2:$E$125,3)+COUNTIFS(Cleaned!$C$2:$C$125,3,Cleaned!$E$2:$E$125,4)+COUNTIFS(Cleaned!$C$2:$C$125,4,Cleaned!$E$2:$E$125,1)+COUNTIFS(Cleaned!$C$2:$C$125,4,Cleaned!$E$2:$E$125,2)+COUNTIFS(Cleaned!$C$2:$C$125,4,Cleaned!$E$2:$E$125,3)+COUNTIFS(Cleaned!$C$2:$C$125,4,Cleaned!$E$2:$E$125,4)+COUNTIFS(Cleaned!$C$2:$C$125,5,Cleaned!$E$2:$E$125,1)+COUNTIFS(Cleaned!$C$2:$C$125,5,Cleaned!$E$2:$E$125,2)+COUNTIFS(Cleaned!$C$2:$C$125,5,Cleaned!$E$2:$E$125,3)+COUNTIFS(Cleaned!$C$2:$C$125,5,Cleaned!$E$2:$E$125,4) -> 79 | C11: =COUNTIFS(Cleaned!$D$2:$D$125,1,Cleaned!$E$2:$E$125,1)+COUNTIFS(Cleaned!$D$2:$D$125,1,Cleaned!$E$2:$E$125,2)+COUNTIFS(Cleaned!$D$2:$D$125,1,Cleaned!$E$2:$E$125,3)+COUNTIFS(Cleaned!$D$2:$D$125,1,Cleaned!$E$2:$E$125,4)+COUNTIFS(Cleaned!$D$2:$D$125,2,Cleaned!$E$2:$E$125,1)+COUNTIFS(Cleaned!$D$2:$D$125,2,Cleaned!$E$2:$E$125,2)+COUNTIFS(Cleaned!$D$2:$D$125,2,Cleaned!$E$2:$E$125,3)+COUNTIFS(Cleaned!$D$2:$D$125,2,Cleaned!$E$2:$E$125,4)+COUNTIFS(Cleaned!$D$2:$D$125,3,Cleaned!$E$2:$E$125,1)+COUNTIFS(Cleaned!$D$2:$D$125,3,Cleaned!$E$2:$E$125,2)+COUNTIFS(Cleaned!$D$2:$D$125,3,Cleaned!$E$2:$E$125,3)+COUNTIFS(Cleaned!$D$2:$D$125,3,Cleaned!$E$2:$E$125,4)+COUNTIFS(Cleaned!$D$2:$D$125,4,Cleaned!$E$2:$E$125,1)+COUNTIFS(Cleaned!$D$2:$D$125,4,Cleaned!$E$2:$E$125,2)+COUNTIFS(Cleaned!$D$2:$D$125,4,Cleaned!$E$2:$E$125,3)+COUNTIFS(Cleaned!$D$2:$D$125,4,Cleaned!$E$2:$E$125,4)+COUNTIFS(Cleaned!$D$2:$D$125,5,Cleaned!$E$2:$E$125,1)+COUNTIFS(Cleaned!$D$2:$D$125,5,Cleaned!$E$2:$E$125,2)+COUNTIFS(Cleaned!$D$2:$D$125,5,Cleaned!$E$2:$E$125,3)+COUNTIFS(Cleaned!$D$2:$D$125,5,Cleaned!$E$2:$E$125,4)+COUNTIFS(Cleaned!$D$2:$D$125,6,Cleaned!$E$2:$E$125,1)+COUNTIFS(Cleaned!$D$2:$D$125,6,Cleaned!$E$2:$E$125,2)+COUNTIFS(Cleaned!$D$2:$D$125,6,Cleaned!$E$2:$E$125,3)+COUNTIFS(Cleaned!$D$2:$D$125,6,Cleaned!$E$2:$E$125,4)+COUNTIFS(Cleaned!$D$2:$D$125,7,Cleaned!$E$2:$E$125,1)+COUNTIFS(Cleaned!$D$2:$D$125,7,Cleaned!$E$2:$E$125,2)+COUNTIFS(Cleaned!$D$2:$D$125,7,Cleaned!$E$2:$E$125,3)+COUNTIFS(Cleaned!$D$2:$D$125,7,Cleaned!$E$2:$E$125,4)+COUNTIFS(Cleaned!$D$2:$D$125,8,Cleaned!$E$2:$E$125,1)+COUNTIFS(Cleaned!$D$2:$D$125,8,Cleaned!$E$2:$E$125,2)+COUNTIFS(Cleaned!$D$2:$D$125,8,Cleaned!$E$2:$E$125,3)+COUNTIFS(Cleaned!$D$2:$D$125,8,Cleaned!$E$2:$E$125,4)+COUNTIFS(Cleaned!$D$2:$D$125,9,Cleaned!$E$2:$E$125,1)+COUNTIFS(Cleaned!$D$2:$D$125,9,Cleaned!$E$2:$E$125,2)+COUNTIFS(Cleaned!$D$2:$D$125,9,Cleaned!$E$2:$E$125,3)+COUNTIFS(Cleaned!$D$2:$D$125,9,Cleaned!$E$2:$E$125,4)+COUNTIFS(Cleaned!$D$2:$D$125,10,Cleaned!$E$2:$E$125,1)+COUNTIFS(Cleaned!$D$2:$D$125,10,Cleaned!$E$2:$E$125,2)+COUNTIFS(Cleaned!$D$2:$D$125,10,Cleaned!$E$2:$E$125,3)+COUNTIFS(Cleaned!$D$2:$D$125,10,Cleaned!$E$2:$E$125,4)+COUNTIFS(Cleaned!$D$2:$D$125,11,Cleaned!$E$2:$E$125,1)+COUNTIFS(Cleaned!$D$2:$D$125,11,Cleaned!$E$2:$E$125,2)+COUNTIFS(Cleaned!$D$2:$D$125,11,Cleaned!$E$2:$E$125,3)+COUNTIFS(Cleaned!$D$2:$D$125,11,Cleaned!$E$2:$E$125,4)+COUNTIFS(Cleaned!$D$2:$D$125,12,Cleaned!$E$2:$E$125,1)+COUNTIFS(Cleaned!$D$2:$D$125,12,Cleaned!$E$2:$E$125,2)+COUNTIFS(Cleaned!$D$2:$D$125,12,Cleaned!$E$2:$E$125,3)+COUNTIFS(Cleaned!$D$2:$D$125,12,Cleaned!$E$2:$E$125,4) -> 79 | D11: =IF(B11=C11,"OK","FAIL") -> OK
A12: Crosstab totals agree: What methods of payment are accepted? (Check | B12: =COUNTIFS(Cleaned!$C$2:$C$125,1,Cleaned!$G$2:$G$125,0)+COUNTIFS(Cleaned!$C$2:$C$125,1,Cleaned!$G$2:$G$125,1)+COUNTIFS(Cleaned!$C$2:$C$125,2,Cleaned!$G$2:$G$125,0)+COUNTIFS(Cleaned!$C$2:$C$125,2,Cleaned!$G$2:$G$125,1)+COUNTIFS(Cleaned!$C$2:$C$125,3,Cleaned!$G$2:$G$125,0)+COUNTIFS(Cleaned!$C$2:$C$125,3,Cleaned!$G$2:$G$125,1)+COUNTIFS(Cleaned!$C$2:$C$125,4,Cleaned!$G$2:$G$125,0)+COUNTIFS(Cleaned!$C$2:$C$125,4,Cleaned!$G$2:$G$125,1)+COUNTIFS(Cleaned!$C$2:$C$125,5,Cleaned!$G$2:$G$125,0)+COUNTIFS(Cleaned!$C$2:$C$125,5,Cleaned!$G$2:$G$125,1) -> 78 | C12: =COUNTIFS(Cleaned!$D$2:$D$125,1,Cleaned!$G$2:$G$125,0)+COUNTIFS(Cleaned!$D$2:$D$125,1,Cleaned!$G$2:$G$125,1)+COUNTIFS(Cleaned!$D$2:$D$125,2,Cleaned!$G$2:$G$125,0)+COUNTIFS(Cleaned!$D$2:$D$125,2,Cleaned!$G$2:$G$125,1)+COUNTIFS(Cleaned!$D$2:$D$125,3,Cleaned!$G$2:$G$125,0)+COUNTIFS(Cleaned!$D$2:$D$125,3,Cleaned!$G$2:$G$125,1)+COUNTIFS(Cleaned!$D$2:$D$125,4,Cleaned!$G$2:$G$125,0)+COUNTIFS(Cleaned!$D$2:$D$125,4,Cleaned!$G$2:$G$125,1)+COUNTIFS(Cleaned!$D$2:$D$125,5,Cleaned!$G$2:$G$125,0)+COUNTIFS(Cleaned!$D$2:$D$125,5,Cleaned!$G$2:$G$125,1)+COUNTIFS(Cleaned!$D$2:$D$125,6,Cleaned!$G$2:$G$125,0)+COUNTIFS(Cleaned!$D$2:$D$125,6,Cleaned!$G$2:$G$125,1)+COUNTIFS(Cleaned!$D$2:$D$125,7,Cleaned!$G$2:$G$125,0)+COUNTIFS(Cleaned!$D$2:$D$125,7,Cleaned!$G$2:$G$125,1)+COUNTIFS(Cleaned!$D$2:$D$125,8,Cleaned!$G$2:$G$125,0)+COUNTIFS(Cleaned!$D$2:$D$125,8,Cleaned!$G$2:$G$125,1)+COUNTIFS(Cleaned!$D$2:$D$125,9,Cleaned!$G$2:$G$125,0)+COUNTIFS(Cleaned!$D$2:$D$125,9,Cleaned!$G$2:$G$125,1)+COUNTIFS(Cleaned!$D$2:$D$125,10,Cleaned!$G$2:$G$125,0)+COUNTIFS(Cleaned!$D$2:$D$125,10,Cleaned!$G$2:$G$125,1)+COUNTIFS(Cleaned!$D$2:$D$125,11,Cleaned!$G$2:$G$125,0)+COUNTIFS(Cleaned!$D$2:$D$125,11,Cleaned!$G$2:$G$125,1)+COUNTIFS(Cleaned!$D$2:$D$125,12,Cleaned!$G$2:$G$125,0)+COUNTIFS(Cleaned!$D$2:$D$125,12,Cleaned!$G$2:$G$125,1) -> 78 | D12: =IF(B12=C12,"OK","FAIL") -> OK
A13: Crosstab totals agree: What methods of payment are accepted? (Check | B13: =COUNTIFS(Cleaned!$C$2:$C$125,1,Cleaned!$H$2:$H$125,0)+COUNTIFS(Cleaned!$C$2:$C$125,1,Cleaned!$H$2:$H$125,1)+COUNTIFS(Cleaned!$C$2:$C$125,2,Cleaned!$H$2:$H$125,0)+COUNTIFS(Cleaned!$C$2:$C$125,2,Cleaned!$H$2:$H$125,1)+COUNTIFS(Cleaned!$C$2:$C$125,3,Cleaned!$H$2:$H$125,0)+COUNTIFS(Cleaned!$C$2:$C$125,3,Cleaned!$H$2:$H$125,1)+COUNTIFS(Cleaned!$C$2:$C$125,4,Cleaned!$H$2:$H$125,0)+COUNTIFS(Cleaned!$C$2:$C$125,4,Cleaned!$H$2:$H$125,1)+COUNTIFS(Cleaned!$C$2:$C$125,5,Cleaned!$H$2:$H$125,0)+COUNTIFS(Cleaned!$C$2:$C$125,5,Cleaned!$H$2:$H$125,1) -> 78 | C13: =COUNTIFS(Cleaned!$D$2:$D$125,1,Cleaned!$H$2:$H$125,0)+COUNTIFS(Cleaned!$D$2:$D$125,1,Cleaned!$H$2:$H$125,1)+COUNTIFS(Cleaned!$D$2:$D$125,2,Cleaned!$H$2:$H$125,0)+COUNTIFS(Cleaned!$D$2:$D$125,2,Cleaned!$H$2:$H$125,1)+COUNTIFS(Cleaned!$D$2:$D$125,3,Cleaned!$H$2:$H$125,0)+COUNTIFS(Cleaned!$D$2:$D$125,3,Cleaned!$H$2:$H$125,1)+COUNTIFS(Cleaned!$D$2:$D$125,4,Cleaned!$H$2:$H$125,0)+COUNTIFS(Cleaned!$D$2:$D$125,4,Cleaned!$H$2:$H$125,1)+COUNTIFS(Cleaned!$D$2:$D$125,5,Cleaned!$H$2:$H$125,0)+COUNTIFS(Cleaned!$D$2:$D$125,5,Cleaned!$H$2:$H$125,1)+COUNTIFS(Cleaned!$D$2:$D$125,6,Cleaned!$H$2:$H$125,0)+COUNTIFS(Cleaned!$D$2:$D$125,6,Cleaned!$H$2:$H$125,1)+COUNTIFS(Cleaned!$D$2:$D$125,7,Cleaned!$H$2:$H$125,0)+COUNTIFS(Cleaned!$D$2:$D$125,7,Cleaned!$H$2:$H$125,1)+COUNTIFS(Cleaned!$D$2:$D$125,8,Cleaned!$H$2:$H$125,0)+COUNTIFS(Cleaned!$D$2:$D$125,8,Cleaned!$H$2:$H$125,1)+COUNTIFS(Cleaned!$D$2:$D$125,9,Cleaned!$H$2:$H$125,0)+COUNTIFS(Cleaned!$D$2:$D$125,9,Cleaned!$H$2:$H$125,1)+COUNTIFS(Cleaned!$D$2:$D$125,10,Cleaned!$H$2:$H$125,0)+COUNTIFS(Cleaned!$D$2:$D$125,10,Cleaned!$H$2:$H$125,1)+COUNTIFS(Cleaned!$D$2:$D$125,11,Cleaned!$H$2:$H$125,0)+COUNTIFS(Cleaned!$D$2:$D$125,11,Cleaned!$H$2:$H$125,1)+COUNTIFS(Cleaned!$D$2:$D$125,12,Cleaned!$H$2:$H$125,0)+COUNTIFS(Cleaned!$D$2:$D$125,12,Cleaned!$H$2:$H$125,1) -> 78 | D13: =IF(B13=C13,"OK","FAIL") -> OK
A14: Crosstab totals agree: What methods of payment are accepted? (Check | B14: =COUNTIFS(Cleaned!$C$2:$C$125,1,Cleaned!$I$2:$I$125,0)+COUNTIFS(Cleaned!$C$2:$C$125,1,Cleaned!$I$2:$I$125,1)+COUNTIFS(Cleaned!$C$2:$C$125,2,Cleaned!$I$2:$I$125,0)+COUNTIFS(Cleaned!$C$2:$C$125,2,Cleaned!$I$2:$I$125,1)+COUNTIFS(Cleaned!$C$2:$C$125,3,Cleaned!$I$2:$I$125,0)+COUNTIFS(Cleaned!$C$2:$C$125,3,Cleaned!$I$2:$I$125,1)+COUNTIFS(Cleaned!$C$2:$C$125,4,Cleaned!$I$2:$I$125,0)+COUNTIFS(Cleaned!$C$2:$C$125,4,Cleaned!$I$2:$I$125,1)+COUNTIFS(Cleaned!$C$2:$C$125,5,Cleaned!$I$2:$I$125,0)+COUNTIFS(Cleaned!$C$2:$C$125,5,Cleaned!$I$2:$I$125,1) -> 78 | C14: =COUNTIFS(Cleaned!$D$2:$D$125,1,Cleaned!$I$2:$I$125,0)+COUNTIFS(Cleaned!$D$2:$D$125,1,Cleaned!$I$2:$I$125,1)+COUNTIFS(Cleaned!$D$2:$D$125,2,Cleaned!$I$2:$I$125,0)+COUNTIFS(Cleaned!$D$2:$D$125,2,Cleaned!$I$2:$I$125,1)+COUNTIFS(Cleaned!$D$2:$D$125,3,Cleaned!$I$2:$I$125,0)+COUNTIFS(Cleaned!$D$2:$D$125,3,Cleaned!$I$2:$I$125,1)+COUNTIFS(Cleaned!$D$2:$D$125,4,Cleaned!$I$2:$I$125,0)+COUNTIFS(Cleaned!$D$2:$D$125,4,Cleaned!$I$2:$I$125,1)+COUNTIFS(Cleaned!$D$2:$D$125,5,Cleaned!$I$2:$I$125,0)+COUNTIFS(Cleaned!$D$2:$D$125,5,Cleaned!$I$2:$I$125,1)+COUNTIFS(Cleaned!$D$2:$D$125,6,Cleaned!$I$2:$I$125,0)+COUNTIFS(Cleaned!$D$2:$D$125,6,Cleaned!$I$2:$I$125,1)+COUNTIFS(Cleaned!$D$2:$D$125,7,Cleaned!$I$2:$I$125,0)+COUNTIFS(Cleaned!$D$2:$D$125,7,Cleaned!$I$2:$I$125,1)+COUNTIFS(Cleaned!$D$2:$D$125,8,Cleaned!$I$2:$I$125,0)+COUNTIFS(Cleaned!$D$2:$D$125,8,Cleaned!$I$2:$I$125,1)+COUNTIFS(Cleaned!$D$2:$D$125,9,Cleaned!$I$2:$I$125,0)+COUNTIFS(Cleaned!$D$2:$D$125,9,Cleaned!$I$2:$I$125,1)+COUNTIFS(Cleaned!$D$2:$D$125,10,Cleaned!$I$2:$I$125,0)+COUNTIFS(Cleaned!$D$2:$D$125,10,Cleaned!$I$2:$I$125,1)+COUNTIFS(Cleaned!$D$2:$D$125,11,Cleaned!$I$2:$I$125,0)+COUNTIFS(Cleaned!$D$2:$D$125,11,Cleaned!$I$2:$I$125,1)+COUNTIFS(Cleaned!$D$2:$D$125,12,Cleaned!$I$2:$I$125,0)+COUNTIFS(Cleaned!$D$2:$D$125,12,Cleaned!$I$2:$I$125,1) -> 78 | D14: =IF(B14=C14,"OK","FAIL") -> OK
A15: Crosstab totals agree: What methods of payment are accepted? (Check | B15: =COUNTIFS(Cleaned!$C$2:$C$125,1,Cleaned!$J$2:$J$125,0)+COUNTIFS(Cleaned!$C$2:$C$125,1,Cleaned!$J$2:$J$125,1)+COUNTIFS(Cleaned!$C$2:$C$125,2,Cleaned!$J$2:$J$125,0)+COUNTIFS(Cleaned!$C$2:$C$125,2,Cleaned!$J$2:$J$125,1)+COUNTIFS(Cleaned!$C$2:$C$125,3,Cleaned!$J$2:$J$125,0)+COUNTIFS(Cleaned!$C$2:$C$125,3,Cleaned!$J$2:$J$125,1)+COUNTIFS(Cleaned!$C$2:$C$125,4,Cleaned!$J$2:$J$125,0)+COUNTIFS(Cleaned!$C$2:$C$125,4,Cleaned!$J$2:$J$125,1)+COUNTIFS(Cleaned!$C$2:$C$125,5,Cleaned!$J$2:$J$125,0)+COUNTIFS(Cleaned!$C$2:$C$125,5,Cleaned!$J$2:$J$125,1) -> 78 | C15: =COUNTIFS(Cleaned!$D$2:$D$125,1,Cleaned!$J$2:$J$125,0)+COUNTIFS(Cleaned!$D$2:$D$125,1,Cleaned!$J$2:$J$125,1)+COUNTIFS(Cleaned!$D$2:$D$125,2,Cleaned!$J$2:$J$125,0)+COUNTIFS(Cleaned!$D$2:$D$125,2,Cleaned!$J$2:$J$125,1)+COUNTIFS(Cleaned!$D$2:$D$125,3,Cleaned!$J$2:$J$125,0)+COUNTIFS(Cleaned!$D$2:$D$125,3,Cleaned!$J$2:$J$125,1)+COUNTIFS(Cleaned!$D$2:$D$125,4,Cleaned!$J$2:$J$125,0)+COUNTIFS(Cleaned!$D$2:$D$125,4,Cleaned!$J$2:$J$125,1)+COUNTIFS(Cleaned!$D$2:$D$125,5,Cleaned!$J$2:$J$125,0)+COUNTIFS(Cleaned!$D$2:$D$125,5,Cleaned!$J$2:$J$125,1)+COUNTIFS(Cleaned!$D$2:$D$125,6,Cleaned!$J$2:$J$125,0)+COUNTIFS(Cleaned!$D$2:$D$125,6,Cleaned!$J$2:$J$125,1)+COUNTIFS(Cleaned!$D$2:$D$125,7,Cleaned!$J$2:$J$125,0)+COUNTIFS(Cleaned!$D$2:$D$125,7,Cleaned!$J$2:$J$125,1)+COUNTIFS(Cleaned!$D$2:$D$125,8,Cleaned!$J$2:$J$125,0)+COUNTIFS(Cleaned!$D$2:$D$125,8,Cleaned!$J$2:$J$125,1)+COUNTIFS(Cleaned!$D$2:$D$125,9,Cleaned!$J$2:$J$125,0)+COUNTIFS(Cleaned!$D$2:$D$125,9,Cleaned!$J$2:$J$125,1)+COUNTIFS(Cleaned!$D$2:$D$125,10,Cleaned!$J$2:$J$125,0)+COUNTIFS(Cleaned!$D$2:$D$125,10,Cleaned!$J$2:$J$125,1)+COUNTIFS(Cleaned!$D$2:$D$125,11,Cleaned!$J$2:$J$125,0)+COUNTIFS(Cleaned!$D$2:$D$125,11,Cleaned!$J$2:$J$125,1)+COUNTIFS(Cleaned!$D$2:$D$125,12,Cleaned!$J$2:$J$125,0)+COUNTIFS(Cleaned!$D$2:$D$125,12,Cleaned!$J$2:$J$125,1) -> 78 | D15: =IF(B15=C15,"OK","FAIL") -> OK
A16: Crosstab totals agree: What methods of payment are accepted? (Check | B16: =COUNTIFS(Cleaned!$C$2:$C$125,1,Cleaned!$K$2:$K$125,0)+COUNTIFS(Cleaned!$C$2:$C$125,1,Cleaned!$K$2:$K$125,1)+COUNTIFS(Cleaned!$C$2:$C$125,2,Cleaned!$K$2:$K$125,0)+COUNTIFS(Cleaned!$C$2:$C$125,2,Cleaned!$K$2:$K$125,1)+COUNTIFS(Cleaned!$C$2:$C$125,3,Cleaned!$K$2:$K$125,0)+COUNTIFS(Cleaned!$C$2:$C$125,3,Cleaned!$K$2:$K$125,1)+COUNTIFS(Cleaned!$C$2:$C$125,4,Cleaned!$K$2:$K$125,0)+COUNTIFS(Cleaned!$C$2:$C$125,4,Cleaned!$K$2:$K$125,1)+COUNTIFS(Cleaned!$C$2:$C$125,5,Cleaned!$K$2:$K$125,0)+COUNTIFS(Cleaned!$C$2:$C$125,5,Cleaned!$K$2:$K$125,1) -> 78 | C16: =COUNTIFS(Cleaned!$D$2:$D$125,1,Cleaned!$K$2:$K$125,0)+COUNTIFS(Cleaned!$D$2:$D$125,1,Cleaned!$K$2:$K$125,1)+COUNTIFS(Cleaned!$D$2:$D$125,2,Cleaned!$K$2:$K$125,0)+COUNTIFS(Cleaned!$D$2:$D$125,2,Cleaned!$K$2:$K$125,1)+COUNTIFS(Cleaned!$D$2:$D$125,3,Cleaned!$K$2:$K$125,0)+COUNTIFS(Cleaned!$D$2:$D$125,3,Cleaned!$K$2:$K$125,1)+COUNTIFS(Cleaned!$D$2:$D$125,4,Cleaned!$K$2:$K$125,0)+COUNTIFS(Cleaned!$D$2:$D$125,4,Cleaned!$K$2:$K$125,1)+COUNTIFS(Cleaned!$D$2:$D$125,5,Cleaned!$K$2:$K$125,0)+COUNTIFS(Cleaned!$D$2:$D$125,5,Cleaned!$K$2:$K$125,1)+COUNTIFS(Cleaned!$D$2:$D$125,6,Cleaned!$K$2:$K$125,0)+COUNTIFS(Cleaned!$D$2:$D$125,6,Cleaned!$K$2:$K$125,1)+COUNTIFS(Cleaned!$D$2:$D$125,7,Cleaned!$K$2:$K$125,0)+COUNTIFS(Cleaned!$D$2:$D$125,7,Cleaned!$K$2:$K$125,1)+COUNTIFS(Cleaned!$D$2:$D$125,8,Cleaned!$K$2:$K$125,0)+COUNTIFS(Cleaned!$D$2:$D$125,8,Cleaned!$K$2:$K$125,1)+COUNTIFS(Cleaned!$D$2:$D$125,9,Cleaned!$K$2:$K$125,0)+COUNTIFS(Cleaned!$D$2:$D$125,9,Cleaned!$K$2:$K$125,1)+COUNTIFS(Cleaned!$D$2:$D$125,10,Cleaned!$K$2:$K$125,0)+COUNTIFS(Cleaned!$D$2:$D$125,10,Cleaned!$K$2:$K$125,1)+COUNTIFS(Cleaned!$D$2:$D$125,11,Cleaned!$K$2:$K$125,0)+COUNTIFS(Cleaned!$D$2:$D$125,11,Cleaned!$K$2:$K$125,1)+COUNTIFS(Cleaned!$D$2:$D$125,12,Cleaned!$K$2:$K$125,0)+COUNTIFS(Cleaned!$D$2:$D$125,12,Cleaned!$K$2:$K$125,1) -> 78 | D16: =IF(B16=C16,"OK","FAIL") -> OK
A17: Crosstab totals agree: What methods of payment are accepted? (Check | B17: =COUNTIFS(Cleaned!$C$2:$C$125,1,Cleaned!$L$2:$L$125,0)+COUNTIFS(Cleaned!$C$2:$C$125,1,Cleaned!$L$2:$L$125,1)+COUNTIFS(Cleaned!$C$2:$C$125,2,Cleaned!$L$2:$L$125,0)+COUNTIFS(Cleaned!$C$2:$C$125,2,Cleaned!$L$2:$L$125,1)+COUNTIFS(Cleaned!$C$2:$C$125,3,Cleaned!$L$2:$L$125,0)+COUNTIFS(Cleaned!$C$2:$C$125,3,Cleaned!$L$2:$L$125,1)+COUNTIFS(Cleaned!$C$2:$C$125,4,Cleaned!$L$2:$L$125,0)+COUNTIFS(Cleaned!$C$2:$C$125,4,Cleaned!$L$2:$L$125,1)+COUNTIFS(Cleaned!$C$2:$C$125,5,Cleaned!$L$2:$L$125,0)+COUNTIFS(Cleaned!$C$2:$C$125,5,Cleaned!$L$2:$L$125,1) -> 78 | C17: =COUNTIFS(Cleaned!$D$2:$D$125,1,Cleaned!$L$2:$L$125,0)+COUNTIFS(Cleaned!$D$2:$D$125,1,Cleaned!$L$2:$L$125,1)+COUNTIFS(Cleaned!$D$2:$D$125,2,Cleaned!$L$2:$L$125,0)+COUNTIFS(Cleaned!$D$2:$D$125,2,Cleaned!$L$2:$L$125,1)+COUNTIFS(Cleaned!$D$2:$D$125,3,Cleaned!$L$2:$L$125,0)+COUNTIFS(Cleaned!$D$2:$D$125,3,Cleaned!$L$2:$L$125,1)+COUNTIFS(Cleaned!$D$2:$D$125,4,Cleaned!$L$2:$L$125,0)+COUNTIFS(Cleaned!$D$2:$D$125,4,Cleaned!$L$2:$L$125,1)+COUNTIFS(Cleaned!$D$2:$D$125,5,Cleaned!$L$2:$L$125,0)+COUNTIFS(Cleaned!$D$2:$D$125,5,Cleaned!$L$2:$L$125,1)+COUNTIFS(Cleaned!$D$2:$D$125,6,Cleaned!$L$2:$L$125,0)+COUNTIFS(Cleaned!$D$2:$D$125,6,Cleaned!$L$2:$L$125,1)+COUNTIFS(Cleaned!$D$2:$D$125,7,Cleaned!$L$2:$L$125,0)+COUNTIFS(Cleaned!$D$2:$D$125,7,Cleaned!$L$2:$L$125,1)+COUNTIFS(Cleaned!$D$2:$D$125,8,Cleaned!$L$2:$L$125,0)+COUNTIFS(Cleaned!$D$2:$D$125,8,Cleaned!$L$2:$L$125,1)+COUNTIFS(Cleaned!$D$2:$D$125,9,Cleaned!$L$2:$L$125,0)+COUNTIFS(Cleaned!$D$2:$D$125,9,Cleaned!$L$2:$L$125,1)+COUNTIFS(Cleaned!$D$2:$D$125,10,Cleaned!$L$2:$L$125,0)+COUNTIFS(Cleaned!$D$2:$D$125,10,Cleaned!$L$2:$L$125,1)+COUNTIFS(Cleaned!$D$2:$D$125,11,Cleaned!$L$2:$L$125,0)+COUNTIFS(Cleaned!$D$2:$D$125,11,Cleaned!$L$2:$L$125,1)+COUNTIFS(Cleaned!$D$2:$D$125,12,Cleaned!$L$2:$L$125,0)+COUNTIFS(Cleaned!$D$2:$D$125,12,Cleaned!$L$2:$L$125,1) -> 78 | D17: =IF(B17=C17,"OK","FAIL") -> OK
A18: Crosstab totals agree: Do you provide paperless billing? | B18: =COUNTIFS(Cleaned!$C$2:$C$125,1,Cleaned!$M$2:$M$125,1)+COUNTIFS(Cleaned!$C$2:$C$125,1,Cleaned!$M$2:$M$125,2)+COUNTIFS(Cleaned!$C$2:$C$125,2,Cleaned!$M$2:$M$125,1)+COUNTIFS(Cleaned!$C$2:$C$125,2,Cleaned!$M$2:$M$125,2)+COUNTIFS(Cleaned!$C$2:$C$125,3,Cleaned!$M$2:$M$125,1)+COUNTIFS(Cleaned!$C$2:$C$125,3,Cleaned!$M$2:$M$125,2)+COUNTIFS(Cleaned!$C$2:$C$125,4,Cleaned!$M$2:$M$125,1)+COUNTIFS(Cleaned!$C$2:$C$125,4,Cleaned!$M$2:$M$125,2)+COUNTIFS(Cleaned!$C$2:$C$125,5,Cleaned!$M$2:$M$125,1)+COUNTIFS(Cleaned!$C$2:$C$125,5,Cleaned!$M$2:$M$125,2) -> 78 | C18: =COUNTIFS(Cleaned!$D$2:$D$125,1,Cleaned!$M$2:$M$125,1)+COUNTIFS(Cleaned!$D$2:$D$125,1,Cleaned!$M$2:$M$125,2)+COUNTIFS(Cleaned!$D$2:$D$125,2,Cleaned!$M$2:$M$125,1)+COUNTIFS(Cleaned!$D$2:$D$125,2,Cleaned!$M$2:$M$125,2)+COUNTIFS(Cleaned!$D$2:$D$125,3,Cleaned!$M$2:$M$125,1)+COUNTIFS(Cleaned!$D$2:$D$125,3,Cleaned!$M$2:$M$125,2)+COUNTIFS(Cleaned!$D$2:$D$125,4,Cleaned!$M$2:$M$125,1)+COUNTIFS(Cleaned!$D$2:$D$125,4,Cleaned!$M$2:$M$125,2)+COUNTIFS(Cleaned!$D$2:$D$125,5,Cleaned!$M$2:$M$125,1)+COUNTIFS(Cleaned!$D$2:$D$125,5,Cleaned!$M$2:$M$125,2)+COUNTIFS(Cleaned!$D$2:$D$125,6,Cleaned!$M$2:$M$125,1)+COUNTIFS(Cleaned!$D$2:$D$125,6,Cleaned!$M$2:$M$125,2)+COUNTIFS(Cleaned!$D$2:$D$125,7,Cleaned!$M$2:$M$125,1)+COUNTIFS(Cleaned!$D$2:$D$125,7,Cleaned!$M$2:$M$125,2)+COUNTIFS(Cleaned!$D$2:$D$125,8,Cleaned!$M$2:$M$125,1)+COUNTIFS(Cleaned!$D$2:$D$125,8,Cleaned!$M$2:$M$125,2)+COUNTIFS(Cleaned!$D$2:$D$125,9,Cleaned!$M$2:$M$125,1)+COUNTIFS(Cleaned!$D$2:$D$125,9,Cleaned!$M$2:$M$125,2)+COUNTIFS(Cleaned!$D$2:$D$125,10,Cleaned!$M$2:$M$125,1)+COUNTIFS(Cleaned!$D$2:$D$125,10,Cleaned!$M$2:$M$125,2)+COUNTIFS(Cleaned!$D$2:$D$125,11,Cleaned!$M$2:$M$125,1)+COUNTIFS(Cleaned!$D$2:$D$125,11,Cleaned!$M$2:$M$125,2)+COUNTIFS(Cleaned!$D$2:$D$125,12,Cleaned!$M$2:$M$125,1)+COUNTIFS(Cleaned!$D$2:$D$125,12,Cleaned!$M$2:$M$125,2) -> 78 | D18: =IF(B18=C18,"OK","FAIL") -> OK
A19: Crosstab totals agree: What methods of enforcement are used for lat | B19: =COUNTIFS(Cleaned!$C$2:$C$125,1,Cleaned!$N$2:$N$125,0)+COUNTIFS(Cleaned!$C$2:$C$125,1,Cleaned!$N$2:$N$125,1)+COUNTIFS(Cleaned!$C$2:$C$125,2,Cleaned!$N$2:$N$125,0)+COUNTIFS(Cleaned!$C$2:$C$125,2,Cleaned!$N$2:$N$125,1)+COUNTIFS(Cleaned!$C$2:$C$125,3,Cleaned!$N$2:$N$125,0)+COUNTIFS(Cleaned!$C$2:$C$125,3,Cleaned!$N$2:$N$125,1)+COUNTIFS(Cleaned!$C$2:$C$125,4,Cleaned!$N$2:$N$125,0)+COUNTIFS(Cleaned!$C$2:$C$125,4,Cleaned!$N$2:$N$125,1)+COUNTIFS(Cleaned!$C$2:$C$125,5,Cleaned!$N$2:$N$125,0)+COUNTIFS(Cleaned!$C$2:$C$125,5,Cleaned!$N$2:$N$125,1) -> 78 | C19: =COUNTIFS(Cleaned!$D$2:$D$125,1,Cleaned!$N$2:$N$125,0)+COUNTIFS(Cleaned!$D$2:$D$125,1,Cleaned!$N$2:$N$125,1)+COUNTIFS(Cleaned!$D$2:$D$125,2,Cleaned!$N$2:$N$125,0)+COUNTIFS(Cleaned!$D$2:$D$125,2,Cleaned!$N$2:$N$125,1)+COUNTIFS(Cleaned!$D$2:$D$125,3,Cleaned!$N$2:$N$125,0)+COUNTIFS(Cleaned!$D$2:$D$125,3,Cleaned!$N$2:$N$125,1)+COUNTIFS(Cleaned!$D$2:$D$125,4,Cleaned!$N$2:$N$125,0)+COUNTIFS(Cleaned!$D$2:$D$125,4,Cleaned!$N$2:$N$125,1)+COUNTIFS(Cleaned!$D$2:$D$125,5,Cleaned!$N$2:$N$125,0)+COUNTIFS(Cleaned!$D$2:$D$125,5,Cleaned!$N$2:$N$125,1)+COUNTIFS(Cleaned!$D$2:$D$125,6,Cleaned!$N$2:$N$125,0)+COUNTIFS(Cleaned!$D$2:$D$125,6,Cleaned!$N$2:$N$125,1)+COUNTIFS(Cleaned!$D$2:$D$125,7,Cleaned!$N$2:$N$125,0)+COUNTIFS(Cleaned!$D$2:$D$125,7,Cleaned!$N$2:$N$125,1)+COUNTIFS(Cleaned!$D$2:$D$125,8,Cleaned!$N$2:$N$125,0)+COUNTIFS(Cleaned!$D$2:$D$125,8,Cleaned!$N$2:$N$125,1)+COUNTIFS(Cleaned!$D$2:$D$125,9,Cleaned!$N$2:$N$125,0)+COUNTIFS(Cleaned!$D$2:$D$125,9,Cleaned!$N$2:$N$125,1)+COUNTIFS(Cleaned!$D$2:$D$125,10,Cleaned!$N$2:$N$125,0)+COUNTIFS(Cleaned!$D$2:$D$125,10,Cleaned!$N$2:$N$125,1)+COUNTIFS(Cleaned!$D$2:$D$125,11,Cleaned!$N$2:$N$125,0)+COUNTIFS(Cleaned!$D$2:$D$125,11,Cleaned!$N$2:$N$125,1)+COUNTIFS(Cleaned!$D$2:$D$125,12,Cleaned!$N$2:$N$125,0)+COUNTIFS(Cleaned!$D$2:$D$125,12,Cleaned!$N$2:$N$125,1) -> 78 | D19: =IF(B19=C19,"OK","FAIL") -> OK
A20: Crosstab totals agree: What methods of enforcement are used for lat | B20: =COUNTIFS(Cleaned!$C$2:$C$125,1,Cleaned!$O$2:$O$125,0)+COUNTIFS(Cleaned!$C$2:$C$125,1,Cleaned!$O$2:$O$125,1)+COUNTIFS(Cleaned!$C$2:$C$125,2,Cleaned!$O$2:$O$125,0)+COUNTIFS(Cleaned!$C$2:$C$125,2,Cleaned!$O$2:$O$125,1)+COUNTIFS(Cleaned!$C$2:$C$125,3,Cleaned!$O$2:$O$125,0)+COUNTIFS(Cleaned!$C$2:$C$125,3,Cleaned!$O$2:$O$125,1)+COUNTIFS(Cleaned!$C$2:$C$125,4,Cleaned!$O$2:$O$125,0)+COUNTIFS(Cleaned!$C$2:$C$125,4,Cleaned!$O$2:$O$125,1)+COUNTIFS(Cleaned!$C$2:$C$125,5,Cleaned!$O$2:$O$125,0)+COUNTIFS(Cleaned!$C$2:$C$125,5,Cleaned!$O$2:$O$125,1) -> 78 | C20: =COUNTIFS(Cleaned!$D$2:$D$125,1,Cleaned!$O$2:$O$125,0)+COUNTIFS(Cleaned!$D$2:$D$125,1,Cleaned!$O$2:$O$125,1)+COUNTIFS(Cleaned!$D$2:$D$125,2,Cleaned!$O$2:$O$125,0)+COUNTIFS(Cleaned!$D$2:$D$125,2,Cleaned!$O$2:$O$125,1)+COUNTIFS(Cleaned!$D$2:$D$125,3,Cleaned!$O$2:$O$125,0)+COUNTIFS(Cleaned!$D$2:$D$125,3,Cleaned!$O$2:$O$125,1)+COUNTIFS(Cleaned!$D$2:$D$125,4,Cleaned!$O$2:$O$125,0)+COUNTIFS(Cleaned!$D$2:$D$125,4,Cleaned!$O$2:$O$125,1)+COUNTIFS(Cleaned!$D$2:$D$125,5,Cleaned!$O$2:$O$125,0)+COUNTIFS(Cleaned!$D$2:$D$125,5,Cleaned!$O$2:$O$125,1)+COUNTIFS(Cleaned!$D$2:$D$125,6,Cleaned!$O$2:$O$125,0)+COUNTIFS(Cleaned!$D$2:$D$125,6,Cleaned!$O$2:$O$125,1)+COUNTIFS(Cleaned!$D$2:$D$125,7,Cleaned!$O$2:$O$125,0)+COUNTIFS(Cleaned!$D$2:$D$125,7,Cleaned!$O$2:$O$125,1)+COUNTIFS(Cleaned!$D$2:$D$125,8,Cleaned!$O$2:$O$125,0)+COUNTIFS(Cleaned!$D$2:$D$125,8,Cleaned!$O$2:$O$125,1)+COUNTIFS(Cleaned!$D$2:$D$125,9,Cleaned!$O$2:$O$125,0)+COUNTIFS(Cleaned!$D$2:$D$125,9,Cleaned!$O$2:$O$125,1)+COUNTIFS(Cleaned!$D$2:$D$125,10,Cleaned!$O$2:$O$125,0)+COUNTIFS(Cleaned!$D$2:$D$125,10,Cleaned!$O$2:$O$125,1)+COUNTIFS(Cleaned!$D$2:$D$125,11,Cleaned!$O$2:$O$125,0)+COUNTIFS(Cleaned!$D$2:$D$125,11,Cleaned!$O$2:$O$125,1)+COUNTIFS(Cleaned!$D$2:$D$125,12,Cleaned!$O$2:$O$125,0)+COUNTIFS(Cleaned!$D$2:$D$125,12,Cleaned!$O$2:$O$125,1) -> 78 | D20: =IF(B20=C20,"OK","FAIL") -> OK
A21: Crosstab totals agree: What methods of enforcement are used for lat | B21: =COUNTIFS(Cleaned!$C$2:$C$125,1,Cleaned!$P$2:$P$125,0)+COUNTIFS(Cleaned!$C$2:$C$125,1,Cleaned!$P$2:$P$125,1)+COUNTIFS(Cleaned!$C$2:$C$125,2,Cleaned!$P$2:$P$125,0)+COUNTIFS(Cleaned!$C$2:$C$125,2,Cleaned!$P$2:$P$125,1)+COUNTIFS(Cleaned!$C$2:$C$125,3,Cleaned!$P$2:$P$125,0)+COUNTIFS(Cleaned!$C$2:$C$125,3,Cleaned!$P$2:$P$125,1)+COUNTIFS(Cleaned!$C$2:$C$125,4,Cleaned!$P$2:$P$125,0)+COUNTIFS(Cleaned!$C$2:$C$125,4,Cleaned!$P$2:$P$125,1)+COUNTIFS(Cleaned!$C$2:$C$125,5,Cleaned!$P$2:$P$125,0)+COUNTIFS(Cleaned!$C$2:$C$125,5,Cleaned!$P$2:$P$125,1) -> 78 | C21: =COUNTIFS(Cleaned!$D$2:$D$125,1,Cleaned!$P$2:$P$125,0)+COUNTIFS(Cleaned!$D$2:$D$125,1,Cleaned!$P$2:$P$125,1)+COUNTIFS(Cleaned!$D$2:$D$125,2,Cleaned!$P$2:$P$125,0)+COUNTIFS(Cleaned!$D$2:$D$125,2,Cleaned!$P$2:$P$125,1)+COUNTIFS(Cleaned!$D$2:$D$125,3,Cleaned!$P$2:$P$125,0)+COUNTIFS(Cleaned!$D$2:$D$125,3,Cleaned!$P$2:$P$125,1)+COUNTIFS(Cleaned!$D$2:$D$125,4,Cleaned!$P$2:$P$125,0)+COUNTIFS(Cleaned!$D$2:$D$125,4,Cleaned!$P$2:$P$125,1)+COUNTIFS(Cleaned!$D$2:$D$125,5,Cleaned!$P$2:$P$125,0)+COUNTIFS(Cleaned!$D$2:$D$125,5,Cleaned!$P$2:$P$125,1)+COUNTIFS(Cleaned!$D$2:$D$125,6,Cleaned!$P$2:$P$125,0)+COUNTIFS(Cleaned!$D$2:$D$125,6,Cleaned!$P$2:$P$125,1)+COUNTIFS(Cleaned!$D$2:$D$125,7,Cleaned!$P$2:$P$125,0)+COUNTIFS(Cleaned!$D$2:$D$125,7,Cleaned!$P$2:$P$125,1)+COUNTIFS(Cleaned!$D$2:$D$125,8,Cleaned!$P$2:$P$125,0)+COUNTIFS(Cleaned!$D$2:$D$125,8,Cleaned!$P$2:$P$125,1)+COUNTIFS(Cleaned!$D$2:$D$125,9,Cleaned!$P$2:$P$125,0)+COUNTIFS(Cleaned!$D$2:$D$125,9,Cleaned!$P$2:$P$125,1)+COUNTIFS(Cleaned!$D$2:$D$125,10,Cleaned!$P$2:$P$125,0)+COUNTIFS(Cleaned!$D$2:$D$125,10,Cleaned!$P$2:$P$125,1)+COUNTIFS(Cleaned!$D$2:$D$125,11,Cleaned!$P$2:$P$125,0)+COUNTIFS(Cleaned!$D$2:$D$125,11,Cleaned!$P$2:$P$125,1)+COUNTIFS(Cleaned!$D$2:$D$125,12,Cleaned!$P$2:$P$125,0)+COUNTIFS(Cleaned!$D$2:$D$125,12,Cleaned!$P$2:$P$125,1) -> 78 | D21: =IF(B21=C21,"OK","FAIL") -> OK
A22: Crosstab totals agree: What methods of enforcement are used for lat | B22: =COUNTIFS(Cleaned!$C$2:$C$125,1,Cleaned!$Q$2:$Q$125,0)+COUNTIFS(Cleaned!$C$2:$C$125,1,Cleaned!$Q$2:$Q$125,1)+COUNTIFS(Cleaned!$C$2:$C$125,2,Cleaned!$Q$2:$Q$125,0)+COUNTIFS(Cleaned!$C$2:$C$125,2,Cleaned!$Q$2:$Q$125,1)+COUNTIFS(Cleaned!$C$2:$C$125,3,Cleaned!$Q$2:$Q$125,0)+COUNTIFS(Cleaned!$C$2:$C$125,3,Cleaned!$Q$2:$Q$125,1)+COUNTIFS(Cleaned!$C$2:$C$125,4,Cleaned!$Q$2:$Q$125,0)+COUNTIFS(Cleaned!$C$2:$C$125,4,Cleaned!$Q$2:$Q$125,1)+COUNTIFS(Cleaned!$C$2:$C$125,5,Cleaned!$Q$2:$Q$125,0)+COUNTIFS(Cleaned!$C$2:$C$125,5,Cleaned!$Q$2:$Q$125,1) -> 78 | C22: =COUNTIFS(Cleaned!$D$2:$D$125,1,Cleaned!$Q$2:$Q$125,0)+COUNTIFS(Cleaned!$D$2:$D$125,1,Cleaned!$Q$2:$Q$125,1)+COUNTIFS(Cleaned!$D$2:$D$125,2,Cleaned!$Q$2:$Q$125,0)+COUNTIFS(Cleaned!$D$2:$D$125,2,Cleaned!$Q$2:$Q$125,1)+COUNTIFS(Cleaned!$D$2:$D$125,3,Cleaned!$Q$2:$Q$125,0)+COUNTIFS(Cleaned!$D$2:$D$125,3,Cleaned!$Q$2:$Q$125,1)+COUNTIFS(Cleaned!$D$2:$D$125,4,Cleaned!$Q$2:$Q$125,0)+COUNTIFS(Cleaned!$D$2:$D$125,4,Cleaned!$Q$2:$Q$125,1)+COUNTIFS(Cleaned!$D$2:$D$125,5,Cleaned!$Q$2:$Q$125,0)+COUNTIFS(Cleaned!$D$2:$D$125,5,Cleaned!$Q$2:$Q$125,1)+COUNTIFS(Cleaned!$D$2:$D$125,6,Cleaned!$Q$2:$Q$125,0)+COUNTIFS(Cleaned!$D$2:$D$125,6,Cleaned!$Q$2:$Q$125,1)+COUNTIFS(Cleaned!$D$2:$D$125,7,Cleaned!$Q$2:$Q$125,0)+COUNTIFS(Cleaned!$D$2:$D$125,7,Cleaned!$Q$2:$Q$125,1)+COUNTIFS(Cleaned!$D$2:$D$125,8,Cleaned!$Q$2:$Q$125,0)+COUNTIFS(Cleaned!$D$2:$D$125,8,Cleaned!$Q$2:$Q$125,1)+COUNTIFS(Cleaned!$D$2:$D$125,9,Cleaned!$Q$2:$Q$125,0)+COUNTIFS(Cleaned!$D$2:$D$125,9,Cleaned!$Q$2:$Q$125,1)+COUNTIFS(Cleaned!$D$2:$D$125,10,Cleaned!$Q$2:$Q$125,0)+COUNTIFS(Cleaned!$D$2:$D$125,10,Cleaned!$Q$2:$Q$125,1)+COUNTIFS(Cleaned!$D$2:$D$125,11,Cleaned!$Q$2:$Q$125,0)+COUNTIFS(Cleaned!$D$2:$D$125,11,Cleaned!$Q$2:$Q$125,1)+COUNTIFS(Cleaned!$D$2:$D$125,12,Cleaned!$Q$2:$Q$125,0)+COUNTIFS(Cleaned!$D$2:$D$125,12,Cleaned!$Q$2:$Q$125,1) -> 78 | D22: =IF(B22=C22,"OK","FAIL") -> OK
A23: Crosstab totals agree: What methods of enforcement are used for lat | B23: =COUNTIFS(Cleaned!$C$2:$C$125,1,Cleaned!$R$2:$R$125,0)+COUNTIFS(Cleaned!$C$2:$C$125,1,Cleaned!$R$2:$R$125,1)+COUNTIFS(Cleaned!$C$2:$C$125,2,Cleaned!$R$2:$R$125,0)+COUNTIFS(Cleaned!$C$2:$C$125,2,Cleaned!$R$2:$R$125,1)+COUNTIFS(Cleaned!$C$2:$C$125,3,Cleaned!$R$2:$R$125,0)+COUNTIFS(Cleaned!$C$2:$C$125,3,Cleaned!$R$2:$R$125,1)+COUNTIFS(Cleaned!$C$2:$C$125,4,Cleaned!$R$2:$R$125,0)+COUNTIFS(Cleaned!$C$2:$C$125,4,Cleaned!$R$2:$R$125,1)+COUNTIFS(Cleaned!$C$2:$C$125,5,Cleaned!$R$2:$R$125,0)+COUNTIFS(Cleaned!$C$2:$C$125,5,Cleaned!$R$2:$R$125,1) -> 78 | C23: =COUNTIFS(Cleaned!$D$2:$D$125,1,Cleaned!$R$2:$R$125,0)+COUNTIFS(Cleaned!$D$2:$D$125,1,Cleaned!$R$2:$R$125,1)+COUNTIFS(Cleaned!$D$2:$D$125,2,Cleaned!$R$2:$R$125,0)+COUNTIFS(Cleaned!$D$2:$D$125,2,Cleaned!$R$2:$R$125,1)+COUNTIFS(Cleaned!$D$2:$D$125,3,Cleaned!$R$2:$R$125,0)+COUNTIFS(Cleaned!$D$2:$D$125,3,Cleaned!$R$2:$R$125,1)+COUNTIFS(Cleaned!$D$2:$D$125,4,Cleaned!$R$2:$R$125,0)+COUNTIFS(Cleaned!$D$2:$D$125,4,Cleaned!$R$2:$R$125,1)+COUNTIFS(Cleaned!$D$2:$D$125,5,Cleaned!$R$2:$R$125,0)+COUNTIFS(Cleaned!$D$2:$D$125,5,Cleaned!$R$2:$R$125,1)+COUNTIFS(Cleaned!$D$2:$D$125,6,Cleaned!$R$2:$R$125,0)+COUNTIFS(Cleaned!$D$2:$D$125,6,Cleaned!$R$2:$R$125,1)+COUNTIFS(Cleaned!$D$2:$D$125,7,Cleaned!$R$2:$R$125,0)+COUNTIFS(Cleaned!$D$2:$D$125,7,Cleaned!$R$2:$R$125,1)+COUNTIFS(Cleaned!$D$2:$D$125,8,Cleaned!$R$2:$R$125,0)+COUNTIFS(Cleaned!$D$2:$D$125,8,Cleaned!$R$2:$R$125,1)+COUNTIFS(Cleaned!$D$2:$D$125,9,Cleaned!$R$2:$R$125,0)+COUNTIFS(Cleaned!$D$2:$D$125,9,Cleaned!$R$2:$R$125,1)+COUNTIFS(Cleaned!$D$2:$D$125,10,Cleaned!$R$2:$R$125,0)+COUNTIFS(Cleaned!$D$2:$D$125,10,Cleaned!$R$2:$R$125,1)+COUNTIFS(Cleaned!$D$2:$D$125,11,Cleaned!$R$2:$R$125,0)+COUNTIFS(Cleaned!$D$2:$D$125,11,Cleaned!$R$2:$R$125,1)+COUNTIFS(Cleaned!$D$2:$D$125,12,Cleaned!$R$2:$R$125,0)+COUNTIFS(Cleaned!$D$2:$D$125,12,Cleaned!$R$2:$R$125,1) -> 78 | D23: =IF(B23=C23,"OK","FAIL") -> OK
A24: Crosstab totals agree: What methods of enforcement are used for lat | B24: =COUNTIFS(Cleaned!$C$2:$C$125,1,Cleaned!$S$2:$S$125,0)+COUNTIFS(Cleaned!$C$2:$C$125,1,Cleaned!$S$2:$S$125,1)+COUNTIFS(Cleaned!$C$2:$C$125,2,Cleaned!$S$2:$S$125,0)+COUNTIFS(Cleaned!$C$2:$C$125,2,Cleaned!$S$2:$S$125,1)+COUNTIFS(Cleaned!$C$2:$C$125,3,Cleaned!$S$2:$S$125,0)+COUNTIFS(Cleaned!$C$2:$C$125,3,Cleaned!$S$2:$S$125,1)+COUNTIFS(Cleaned!$C$2:$C$125,4,Cleaned!$S$2:$S$125,0)+COUNTIFS(Cleaned!$C$2:$C$125,4,Cleaned!$S$2:$S$125,1)+COUNTIFS(Cleaned!$C$2:$C$125,5,Cleaned!$S$2:$S$125,0)+COUNTIFS(Cleaned!$C$2:$C$125,5,Cleaned!$S$2:$S$125,1) -> 78 | C24: =COUNTIFS(Cleaned!$D$2:$D$125,1,Cleaned!$S$2:$S$125,0)+COUNTIFS(Cleaned!$D$2:$D$125,1,Cleaned!$S$2:$S$125,1)+COUNTIFS(Cleaned!$D$2:$D$125,2,Cleaned!$S$2:$S$125,0)+COUNTIFS(Cleaned!$D$2:$D$125,2,Cleaned!$S$2:$S$125,1)+COUNTIFS(Cleaned!$D$2:$D$125,3,Cleaned!$S$2:$S$125,0)+COUNTIFS(Cleaned!$D$2:$D$125,3,Cleaned!$S$2:$S$125,1)+COUNTIFS(Cleaned!$D$2:$D$125,4,Cleaned!$S$2:$S$125,0)+COUNTIFS(Cleaned!$D$2:$D$125,4,Cleaned!$S$2:$S$125,1)+COUNTIFS(Cleaned!$D$2:$D$125,5,Cleaned!$S$2:$S$125,0)+COUNTIFS(Cleaned!$D$2:$D$125,5,Cleaned!$S$2:$S$125,1)+COUNTIFS(Cleaned!$D$2:$D$125,6,Cleaned!$S$2:$S$125,0)+COUNTIFS(Cleaned!$D$2:$D$125,6,Cleaned!$S$2:$S$125,1)+COUNTIFS(Cleaned!$D$2:$D$125,7,Cleaned!$S$2:$S$125,0)+COUNTIFS(Cleaned!$D$2:$D$125,7,Cleaned!$S$2:$S$125,1)+COUNTIFS(Cleaned!$D$2:$D$125,8,Cleaned!$S$2:$S$125,0)+COUNTIFS(Cleaned!$D$2:$D$125,8,Cleaned!$S$2:$S$125,1)+COUNTIFS(Cleaned!$D$2:$D$125,9,Cleaned!$S$2:$S$125,0)+COUNTIFS(Cleaned!$D$2:$D$125,9,Cleaned!$S$2:$S$125,1)+COUNTIFS(Cleaned!$D$2:$D$125,10,Cleaned!$S$2:$S$125,0)+COUNTIFS(Cleaned!$D$2:$D$125,10,Cleaned!$S$2:$S$125,1)+COUNTIFS(Cleaned!$D$2:$D$125,11,Cleaned!$S$2:$S$125,0)+COUNTIFS(Cleaned!$D$2:$D$125,11,Cleaned!$S$2:$S$125,1)+COUNTIFS(Cleaned!$D$2:$D$125,12,Cleaned!$S$2:$S$125,0)+COUNTIFS(Cleaned!$D$2:$D$125,12,Cleaned!$S$2:$S$125,1) -> 78 | D24: =IF(B24=C24,"OK","FAIL") -> OK
A25: Crosstab totals agree: Does the city provide waivers, discounts or | B25: =COUNTIFS(Cleaned!$C$2:$C$125,1,Cleaned!$AC$2:$AC$125,1)+COUNTIFS(Cleaned!$C$2:$C$125,1,Cleaned!$AC$2:$AC$125,2)+COUNTIFS(Cleaned!$C$2:$C$125,2,Cleaned!$AC$2:$AC$125,1)+COUNTIFS(Cleaned!$C$2:$C$125,2,Cleaned!$AC$2:$AC$125,2)+COUNTIFS(Cleaned!$C$2:$C$125,3,Cleaned!$AC$2:$AC$125,1)+COUNTIFS(Cleaned!$C$2:$C$125,3,Cleaned!$AC$2:$AC$125,2)+COUNTIFS(Cleaned!$C$2:$C$125,4,Cleaned!$AC$2:$AC$125,1)+COUNTIFS(Cleaned!$C$2:$C$125,4,Cleaned!$AC$2:$AC$125,2)+COUNTIFS(Cleaned!$C$2:$C$125,5,Cleaned!$AC$2:$AC$125,1)+COUNTIFS(Cleaned!$C$2:$C$125,5,Cleaned!$AC$2:$AC$125,2) -> 75 | C25: =COUNTIFS(Cleaned!$D$2:$D$125,1,Cleaned!$AC$2:$AC$125,1)+COUNTIFS(Cleaned!$D$2:$D$125,1,Cleaned!$AC$2:$AC$125,2)+COUNTIFS(Cleaned!$D$2:$D$125,2,Cleaned!$AC$2:$AC$125,1)+COUNTIFS(Cleaned!$D$2:$D$125,2,Cleaned!$AC$2:$AC$125,2)+COUNTIFS(Cleaned!$D$2:$D$125,3,Cleaned!$AC$2:$AC$125,1)+COUNTIFS(Cleaned!$D$2:$D$125,3,Cleaned!$AC$2:$AC$125,2)+COUNTIFS(Cleaned!$D$2:$D$125,4,Cleaned!$AC$2:$AC$125,1)+COUNTIFS(Cleaned!$D$2:$D$125,4,Cleaned!$AC$2:$AC$125,2)+COUNTIFS(Cleaned!$D$2:$D$125,5,Cleaned!$AC$2:$AC$125,1)+COUNTIFS(Cleaned!$D$2:$D$125,5,Cleaned!$AC$2:$AC$125,2)+COUNTIFS(Cleaned!$D$2:$D$125,6,Cleaned!$AC$2:$AC$125,1)+COUNTIFS(Cleaned!$D$2:$D$125,6,Cleaned!$AC$2:$AC$125,2)+COUNTIFS(Cleaned!$D$2:$D$125,7,Cleaned!$AC$2:$AC$125,1)+COUNTIFS(Cleaned!$D$2:$D$125,7,Cleaned!$AC$2:$AC$125,2)+COUNTIFS(Cleaned!$D$2:$D$125,8,Cleaned!$AC$2:$AC$125,1)+COUNTIFS(Cleaned!$D$2:$D$125,8,Cleaned!$AC$2:$AC$125,2)+COUNTIFS(Cleaned!$D$2:$D$125,9,Cleaned!$AC$2:$AC$125,1)+COUNTIFS(Cleaned!$D$2:$D$125,9,Cleaned!$AC$2:$AC$125,2)+COUNTIFS(Cleaned!$D$2:$D$125,10,Cleaned!$AC$2:$AC$125,1)+COUNTIFS(Cleaned!$D$2:$D$125,10,Cleaned!$AC$2:$AC$125,2)+COUNTIFS(Cleaned!$D$2:$D$125,11,Cleaned!$AC$2:$AC$125,1)+COUNTIFS(Cleaned!$D$2:$D$125,11,Cleaned!$AC$2:$AC$125,2)+COUNTIFS(Cleaned!$D$2:$D$125,12,Cleaned!$AC$2:$AC$125,1)+COUNTIFS(Cleaned!$D$2:$D$125,12,Cleaned!$AC$2:$AC$125,2) -> 75 | D25: =IF(B25=C25,"OK","FAIL") -> OK
